Workbook

Sheet Cover
B4: RESELLER TOOLKIT • KIT PARA REVENDEDORES
B6: ProfitTrack
B9: Free Flip Profit Calculator
B10: Calculadora Gratis de Ganancia por Reventa
B11: eBay • Facebook Marketplace • Etsy • Poshmark • Mercari • Depop
B15: WHAT'S INSIDE / CONTENIDO (click to open • clic para abrir)
C17: 🧮 Flip Calculator / Calculadora
C18: Is it worth buying? Know your profit before you pay / ¿Vale la pena? Sabe tu ganancia antes de pagar
C20: ⚙️ Fees / Comisiones
C21: Typical platform fees – edit to match yours / Comisiones típicas – edítalas
C23: 🧰 More Tools / Más Herramientas
C24: The full ProfitTrack reseller toolkit / El kit completo
B27: FREE • GRATIS — 💻 PC / Mac • 📱 iPhone / Android — Excel • Google Sheets
B29: Start here → Quick Start Guide | Empieza aquí → Guía Rápida
B32: © ProfitTrack • v1.0 • For personal use only – do not resell or redistribute / Solo para uso personal – prohibida su reventa o distribución

Sheet Flip Calculator
B1: ProfitTrack
B2: Flip Calculator / Calculadora de Reventa
B3: Type what you'd pay and what it sells for. Compare up to 25 items before you buy. • Escribe cuánto pagarías y en cuánto se vende. Compara hasta 25 artículos antes de comprar.
B5: Item Artículo | C5: Platform Plataforma | D5: Buy Price Precio de Compra | E5: Sale Price Precio de Venta | F5: Shipping You Pay Envío que Pagas | G5: Other Costs Otros Costos | H5: Fee % Comisión % | I5: Fees $ Comisiones $ | J5: Profit Ganancia | K5: Margin Margen | L5: ROI Retorno | M5: Verdict Veredicto
B6: Nike Air Max 90 | C6: eBay | D6: 22 | E6: 89.99 | F6: 12.45 | G6: 0 | H6: =IF(OR(B6="",E6=""),"",IFERROR(INDEX(Fees!$C$7:$C$13,MATCH(C6,Fees!$B$7:$B$13,0)),0)) -> 0.1325 | I6: =IF(H6="","",E6*H6+IFERROR(INDEX(Fees!$D$7:$D$13,MATCH(C6,Fees!$B$7:$B$13,0)),0)) -> 12.323675 | J6: =IF(I6="","",E6-D6-F6-G6-I6) -> 43.216325 | K6: =IF(J6="","",IF(E6=0,0,J6/E6)) -> 0.48023475 | L6: =IF(J6="","",IF(D6+G6=0,"∞",J6/(D6+G6))) -> 1.9643784 | M6: =IF(J6="","",IF(J6<0,"⚠ LOSS / PÉRDIDA",IF(K6>=Fees!$D$17,"✔ GOOD FLIP / BUENA REVENTA","● THIN MARGIN / MARGEN BAJO"))) -> ✔ GOOD FLIP / BUENA REVENTA
B7: Levi's 501 Jeans | C7: Poshmark | D7: 6 | E7: 45 | F7: 0 | G7: 0 | H7: =IF(OR(B7="",E7=""),"",IFERROR(INDEX(Fees!$C$7:$C$13,MATCH(C7,Fees!$B$7:$B$13,0)),0)) -> 0.2 | I7: =IF(H7="","",E7*H7+IFERROR(INDEX(Fees!$D$7:$D$13,MATCH(C7,Fees!$B$7:$B$13,0)),0)) -> 9 | J7: =IF(I7="","",E7-D7-F7-G7-I7) -> 30 | K7: =IF(J7="","",IF(E7=0,0,J7/E7)) -> 0.66666667 | L7: =IF(J7="","",IF(D7+G7=0,"∞",J7/(D7+G7))) -> 5 | M7: =IF(J7="","",IF(J7<0,"⚠ LOSS / PÉRDIDA",IF(K7>=Fees!$D$17,"✔ GOOD FLIP / BUENA REVENTA","● THIN MARGIN / MARGEN BAJO"))) -> ✔ GOOD FLIP / BUENA REVENTA
B8: Pyrex Bowl Set | C8: Local / Cash | D8: 8 | E8: 40 | F8: 0 | G8: 0 | H8: =IF(OR(B8="",E8=""),"",IFERROR(INDEX(Fees!$C$7:$C$13,MATCH(C8,Fees!$B$7:$B$13,0)),0)) -> 0 | I8: =IF(H8="","",E8*H8+IFERROR(INDEX(Fees!$D$7:$D$13,MATCH(C8,Fees!$B$7:$B$13,0)),0)) -> 0 | J8: =IF(I8="","",E8-D8-F8-G8-I8) -> 32 | K8: =IF(J8="","",IF(E8=0,0,J8/E8)) -> 0.8 | L8: =IF(J8="","",IF(D8+G8=0,"∞",J8/(D8+G8))) -> 4 | M8: =IF(J8="","",IF(J8<0,"⚠ LOSS / PÉRDIDA",IF(K8>=Fees!$D$17,"✔ GOOD FLIP / BUENA REVENTA","● THIN MARGIN / MARGEN BAJO"))) -> ✔ GOOD FLIP / BUENA REVENTA
B9: Funko Pop | C9: Mercari | D9: 14 | E9: 22 | F9: 4.5 | G9: 0 | H9: =IF(OR(B9="",E9=""),"",IFERROR(INDEX(Fees!$C$7:$C$13,MATCH(C9,Fees!$B$7:$B$13,0)),0)) -> 0.1 | I9: =IF(H9="","",E9*H9+IFERROR(INDEX(Fees!$D$7:$D$13,MATCH(C9,Fees!$B$7:$B$13,0)),0)) -> 2.7 | J9: =IF(I9="","",E9-D9-F9-G9-I9) -> 0.8 | K9: =IF(J9="","",IF(E9=0,0,J9/E9)) -> 0.036363636 | L9: =IF(J9="","",IF(D9+G9=0,"∞",J9/(D9+G9))) -> 0.057142857 | M9: =IF(J9="","",IF(J9<0,"⚠ LOSS / PÉRDIDA",IF(K9>=Fees!$D$17,"✔ GOOD FLIP / BUENA REVENTA","● THIN MARGIN / MARGEN BAJO"))) -> ● THIN MARGIN / MARGEN BAJO
B10: Bose Headphones | C10: eBay | D10: 95 | E10: 140 | F10: 10 | G10: 0 | H10: =IF(OR(B10="",E10=""),"",IFERROR(INDEX(Fees!$C$7:$C$13,MATCH(C10,Fees!$B$7:$B$13,0)),0)) -> 0.1325 | I10: =IF(H10="","",E10*H10+IFERROR(INDEX(Fees!$D$7:$D$13,MATCH(C10,Fees!$B$7:$B$13,0)),0)) -> 18.95 | J10: =IF(I10="","",E10-D10-F10-G10-I10) -> 16.05 | K10: =IF(J10="","",IF(E10=0,0,J10/E10)) -> 0.11464286 | L10: =IF(J10="","",IF(D10+G10=0,"∞",J10/(D10+G10))) -> 0.16894737 | M10: =IF(J10="","",IF(J10<0,"⚠ LOSS / PÉRDIDA",IF(K10>=Fees!$D$17,"✔ GOOD FLIP / BUENA REVENTA","● THIN MARGIN / MARGEN BAJO"))) -> ● THIN MARGIN / MARGEN BAJO
H11: =IF(OR(B11="",E11=""),"",IFERROR(INDEX(Fees!$C$7:$C$13,MATCH(C11,Fees!$B$7:$B$13,0)),0)) | I11: =IF(H11="","",E11*H11+IFERROR(INDEX(Fees!$D$7:$D$13,MATCH(C11,Fees!$B$7:$B$13,0)),0)) | J11: =IF(I11="","",E11-D11-F11-G11-I11) | K11: =IF(J11="","",IF(E11=0,0,J11/E11)) | L11: =IF(J11="","",IF(D11+G11=0,"∞",J11/(D11+G11))) | M11: =IF(J11="","",IF(J11<0,"⚠ LOSS / PÉRDIDA",IF(K11>=Fees!$D$17,"✔ GOOD FLIP / BUENA REVENTA","● THIN MARGIN / MARGEN BAJO")))
H12: =IF(OR(B12="",E12=""),"",IFERROR(INDEX(Fees!$C$7:$C$13,MATCH(C12,Fees!$B$7:$B$13,0)),0)) | I12: =IF(H12="","",E12*H12+IFERROR(INDEX(Fees!$D$7:$D$13,MATCH(C12,Fees!$B$7:$B$13,0)),0)) | J12: =IF(I12="","",E12-D12-F12-G12-I12) | K12: =IF(J12="","",IF(E12=0,0,J12/E12)) | L12: =IF(J12="","",IF(D12+G12=0,"∞",J12/(D12+G12))) | M12: =IF(J12="","",IF(J12<0,"⚠ LOSS / PÉRDIDA",IF(K12>=Fees!$D$17,"✔ GOOD FLIP / BUENA REVENTA","● THIN MARGIN / MARGEN BAJO")))
H13: =IF(OR(B13="",E13=""),"",IFERROR(INDEX(Fees!$C$7:$C$13,MATCH(C13,Fees!$B$7:$B$13,0)),0)) | I13: =IF(H13="","",E13*H13+IFERROR(INDEX(Fees!$D$7:$D$13,MATCH(C13,Fees!$B$7:$B$13,0)),0)) | J13: =IF(I13="","",E13-D13-F13-G13-I13) | K13: =IF(J13="","",IF(E13=0,0,J13/E13)) | L13: =IF(J13="","",IF(D13+G13=0,"∞",J13/(D13+G13))) | M13: =IF(J13="","",IF(J13<0,"⚠ LOSS / PÉRDIDA",IF(K13>=Fees!$D$17,"✔ GOOD FLIP / BUENA REVENTA","● THIN MARGIN / MARGEN BAJO")))
H14: =IF(OR(B14="",E14=""),"",IFERROR(INDEX(Fees!$C$7:$C$13,MATCH(C14,Fees!$B$7:$B$13,0)),0)) | I14: =IF(H14="","",E14*H14+IFERROR(INDEX(Fees!$D$7:$D$13,MATCH(C14,Fees!$B$7:$B$13,0)),0)) | J14: =IF(I14="","",E14-D14-F14-G14-I14) | K14: =IF(J14="","",IF(E14=0,0,J14/E14)) | L14: =IF(J14="","",IF(D14+G14=0,"∞",J14/(D14+G14))) | M14: =IF(J14="","",IF(J14<0,"⚠ LOSS / PÉRDIDA",IF(K14>=Fees!$D$17,"✔ GOOD FLIP / BUENA REVENTA","● THIN MARGIN / MARGEN BAJO")))
H15: =IF(OR(B15="",E15=""),"",IFERROR(INDEX(Fees!$C$7:$C$13,MATCH(C15,Fees!$B$7:$B$13,0)),0)) | I15: =IF(H15="","",E15*H15+IFERROR(INDEX(Fees!$D$7:$D$13,MATCH(C15,Fees!$B$7:$B$13,0)),0)) | J15: =IF(I15="","",E15-D15-F15-G15-I15) | K15: =IF(J15="","",IF(E15=0,0,J15/E15)) | L15: =IF(J15="","",IF(D15+G15=0,"∞",J15/(D15+G15))) | M15: =IF(J15="","",IF(J15<0,"⚠ LOSS / PÉRDIDA",IF(K15>=Fees!$D$17,"✔ GOOD FLIP / BUENA REVENTA","● THIN MARGIN / MARGEN BAJO")))
H16: =IF(OR(B16="",E16=""),"",IFERROR(INDEX(Fees!$C$7:$C$13,MATCH(C16,Fees!$B$7:$B$13,0)),0)) | I16: =IF(H16="","",E16*H16+IFERROR(INDEX(Fees!$D$7:$D$13,MATCH(C16,Fees!$B$7:$B$13,0)),0)) | J16: =IF(I16="","",E16-D16-F16-G16-I16) | K16: =IF(J16="","",IF(E16=0,0,J16/E16)) | L16: =IF(J16="","",IF(D16+G16=0,"∞",J16/(D16+G16))) | M16: =IF(J16="","",IF(J16<0,"⚠ LOSS / PÉRDIDA",IF(K16>=Fees!$D$17,"✔ GOOD FLIP / BUENA REVENTA","● THIN MARGIN / MARGEN BAJO")))
H17: =IF(OR(B17="",E17=""),"",IFERROR(INDEX(Fees!$C$7:$C$13,MATCH(C17,Fees!$B$7:$B$13,0)),0)) | I17: =IF(H17="","",E17*H17+IFERROR(INDEX(Fees!$D$7:$D$13,MATCH(C17,Fees!$B$7:$B$13,0)),0)) | J17: =IF(I17="","",E17-D17-F17-G17-I17) | K17: =IF(J17="","",IF(E17=0,0,J17/E17)) | L17: =IF(J17="","",IF(D17+G17=0,"∞",J17/(D17+G17))) | M17: =IF(J17="","",IF(J17<0,"⚠ LOSS / PÉRDIDA",IF(K17>=Fees!$D$17,"✔ GOOD FLIP / BUENA REVENTA","● THIN MARGIN / MARGEN BAJO")))
H18: =IF(OR(B18="",E18=""),"",IFERROR(INDEX(Fees!$C$7:$C$13,MATCH(C18,Fees!$B$7:$B$13,0)),0)) | I18: =IF(H18="","",E18*H18+IFERROR(INDEX(Fees!$D$7:$D$13,MATCH(C18,Fees!$B$7:$B$13,0)),0)) | J18: =IF(I18="","",E18-D18-F18-G18-I18) | K18: =IF(J18="","",IF(E18=0,0,J18/E18)) | L18: =IF(J18="","",IF(D18+G18=0,"∞",J18/(D18+G18))) | M18: =IF(J18="","",IF(J18<0,"⚠ LOSS / PÉRDIDA",IF(K18>=Fees!$D$17,"✔ GOOD FLIP / BUENA REVENTA","● THIN MARGIN / MARGEN BAJO")))
H19: =IF(OR(B19="",E19=""),"",IFERROR(INDEX(Fees!$C$7:$C$13,MATCH(C19,Fees!$B$7:$B$13,0)),0)) | I19: =IF(H19="","",E19*H19+IFERROR(INDEX(Fees!$D$7:$D$13,MATCH(C19,Fees!$B$7:$B$13,0)),0)) | J19: =IF(I19="","",E19-D19-F19-G19-I19) | K19: =IF(J19="","",IF(E19=0,0,J19/E19)) | L19: =IF(J19="","",IF(D19+G19=0,"∞",J19/(D19+G19))) | M19: =IF(J19="","",IF(J19<0,"⚠ LOSS / PÉRDIDA",IF(K19>=Fees!$D$17,"✔ GOOD FLIP / BUENA REVENTA","● THIN MARGIN / MARGEN BAJO")))
H20: =IF(OR(B20="",E20=""),"",IFERROR(INDEX(Fees!$C$7:$C$13,MATCH(C20,Fees!$B$7:$B$13,0)),0)) | I20: =IF(H20="","",E20*H20+IFERROR(INDEX(Fees!$D$7:$D$13,MATCH(C20,Fees!$B$7:$B$13,0)),0)) | J20: =IF(I20="","",E20-D20-F20-G20-I20) | K20: =IF(J20="","",IF(E20=0,0,J20/E20)) | L20: =IF(J20="","",IF(D20+G20=0,"∞",J20/(D20+G20))) | M20: =IF(J20="","",IF(J20<0,"⚠ LOSS / PÉRDIDA",IF(K20>=Fees!$D$17,"✔ GOOD FLIP / BUENA REVENTA","● THIN MARGIN / MARGEN BAJO")))
H21: =IF(OR(B21="",E21=""),"",IFERROR(INDEX(Fees!$C$7:$C$13,MATCH(C21,Fees!$B$7:$B$13,0)),0)) | I21: =IF(H21="","",E21*H21+IFERROR(INDEX(Fees!$D$7:$D$13,MATCH(C21,Fees!$B$7:$B$13,0)),0)) | J21: =IF(I21="","",E21-D21-F21-G21-I21) | K21: =IF(J21="","",IF(E21=0,0,J21/E21)) | L21: =IF(J21="","",IF(D21+G21=0,"∞",J21/(D21+G21))) | M21: =IF(J21="","",IF(J21<0,"⚠ LOSS / PÉRDIDA",IF(K21>=Fees!$D$17,"✔ GOOD FLIP / BUENA REVENTA","● THIN MARGIN / MARGEN BAJO")))
H22: =IF(OR(B22="",E22=""),"",IFERROR(INDEX(Fees!$C$7:$C$13,MATCH(C22,Fees!$B$7:$B$13,0)),0)) | I22: =IF(H22="","",E22*H22+IFERROR(INDEX(Fees!$D$7:$D$13,MATCH(C22,Fees!$B$7:$B$13,0)),0)) | J22: =IF(I22="","",E22-D22-F22-G22-I22) | K22: =IF(J22="","",IF(E22=0,0,J22/E22)) | L22: =IF(J22="","",IF(D22+G22=0,"∞",J22/(D22+G22))) | M22: =IF(J22="","",IF(J22<0,"⚠ LOSS / PÉRDIDA",IF(K22>=Fees!$D$17,"✔ GOOD FLIP / BUENA REVENTA","● THIN MARGIN / MARGEN BAJO")))
... H30: =IF(OR(B30="",E30=""),"",IFERROR(INDEX(Fees!$C$7:$C$13,MATCH(C30,Fees!$B$7:$B$13,0)),0)) | I30: =IF(H30="","",E30*H30+IFERROR(INDEX(Fees!$D$7:$D$13,MATCH(C30,Fees!$B$7:$B$13,0)),0)) | J30: =IF(I30="","",E30-D30-F30-G30-I30) | K30: =IF(J30="","",IF(E30=0,0,J30/E30)) | L30: =IF(J30="","",IF(D30+G30=0,"∞",J30/(D30+G30))) | M30: =IF(J30="","",IF(J30<0,"⚠ LOSS / PÉRDIDA",IF(K30>=Fees!$D$17,"✔ GOOD FLIP / BUENA REVENTA","● THIN MARGIN / MARGEN BAJO")))
B32: Want automatic dashboards, inventory alerts and tax-ready expense & mileage logs? → See the 'More Tools' tab. / ¿Quieres paneles automáticos, alertas de inventario y registro de gastos y millaje? → Mira la pestaña 'More Tools'.

Sheet Fees
B1: ProfitTrack
B2: Platform Fees / Comisiones por Plataforma
B3: Typical fees (US, 2026). Fees change – edit the yellow cells to match what you pay. • Comisiones típicas (EE. UU., 2026). Edita las celdas amarillas con lo que tú pagas.
B6: Platform Plataforma | C6: Fee % Comisión % | D6: Fixed Fee $ Tarifa Fija $ | E6: Notes Notas
B7: eBay | C7: 0.1325 | D7: 0.4 | E7: Most categories; fixed fee per order. / La mayoría de categorías.
B8: Poshmark | C8: 0.2 | D8: 0 | E8: Sales $15+. Under $15: flat $2.95 → set 0% and $2.95. / Ventas de $15+.
B9: Etsy | C9: 0.095 | D9: 0.45 | E9: 6.5% transaction + 3% processing; $0.25 + $0.20 listing. / Transacción + procesamiento.
B10: Facebook Marketplace | C10: 0.1 | D10: 0 | E10: Shipped orders. Local cash pickup: use 'Local / Cash'. / Pedidos con envío.
B11: Mercari | C11: 0.1 | D11: 0.5 | E11: Check Mercari's current fees. / Revisa las comisiones actuales de Mercari.
B12: Local / Cash | C12: 0 | D12: 0 | E12: No fees on local cash sales. / Sin comisión en ventas locales.
B13: Other / Otro | C13: 0.1 | D13: 0 | E13: Enter your rate. / Escribe tu comisión.
B16: Your Rule / Tu Regla
B17: Good flip = margin at least / Buena reventa = margen mínimo | D17: 0.3

Sheet More Tools
B1: ProfitTrack
B2: The Full ProfitTrack Toolkit / El Kit Completo
B3: Liked this calculator? These tools do the rest – same design, same English + Español layout. • ¿Te gustó? Estas herramientas hacen el resto.
B6: 📊 Profit Tracker | C6: Log every sale – fees, net profit & margin automatic, low-margin alerts, dashboard by platform & month. / Registro de ventas con panel automático.
B7: 📦 Inventory Tracker | C7: 1,000 items, days held, Fresh → Watch → Stale alerts, stock value, sell-through, 10 oldest items. / Inventario con alertas.
B8: 🧾 Expenses & Mileage | C8: Reseller expense categories, receipt check, mileage at the IRS rate by trip date, total tax deductions. / Gastos y millaje.
B9: 🧰 Reseller Bundle | C9: All three tools together for less. / Las tres herramientas juntas por menos.
B11: 👉 Get them here / Consíguelas aquí: https://YOURSHOP.etsy.com
B13: Free for personal use. Please share the download link, not the file. / Gratis para uso personal. Comparte el enlace, no el archivo.
