Workbook

Sheet Cover
B4: MAKER TOOLKIT • KIT PARA CREADORES
B6: ProfitTrack
B9: Handmade Pricing Calculator
B10: Calculadora de Precios para Productos Hechos a Mano
B11: Etsy • Shopify • Craft Fairs • Markets • Ferias y Mercados
B15: WHAT'S INSIDE / CONTENIDO (click to open • clic para abrir)
C17: 🧮 Calculator / Calculadora
C18: Price one product in detail – materials, time, fees, profit / Calcula un producto en detalle
C20: 📋 Product List / Lista de Productos
C21: Price your whole shop at once & check every margin / Todo tu catálogo y sus márgenes
C23: 🧵 Materials / Materiales
C24: Your supply library – cost per unit calculated / Tu lista de materiales – costo por unidad automático
C26: ⚙️ Settings / Configuración
C27: Hourly rate, Etsy fees, rounding / Tarifa por hora, comisiones de Etsy, redondeo
C29: 🚀 Quick Start Guide / Guía Rápida
C30: Step-by-step setup in 5 minutes / Configuración paso a paso en 5 minutos
B33: 💻 PC / Mac • 📱 iPhone / Android — Excel • Google Sheets | Computadora y celular — Excel • Google Sheets
B35: Start here → Quick Start Guide | Empieza aquí → Guía Rápida
B38: © ProfitTrack • v1.0 • For personal use only – do not resell or redistribute / Solo para uso personal – prohibida su reventa o distribución

Sheet Calculator
B1: ProfitTrack
B2: Pricing Calculator / Calculadora de Precios
B3: Price one product in detail. Type in the light-teal cells – everything else is calculated. • Calcula un producto en detalle. Escribe en las celdas verde claro – lo demás se calcula solo.
B6: 1 · Product / Producto | I6: Your Prices / Tus Precios
B7: Product name / Nombre del producto | C7: Soy Candle – 8 oz Amber Jar | I7: BREAK-EVEN PRICE Precio mínimo (sin ganancia) | J7: =MAX(0,($C$31+$C$36-$C$30*(1-$C$35))/(1-$C$35)) -> 17.236077
B9: 2 · Materials / Materiales | I9: RECOMMENDED PRICE Precio recomendado | J9: =IF(1-$C$35-$C$34<=0,0,MAX(0,IF(Settings!$C$16="Yes / Sí",IF(ROUNDUP(($C$31+$C$36-$C$30*(1-$C$35))/(1-$C$35-$C$34),0)-0.01>=($C$31+$C$36-$C$30*(1-$C$35))/(1-$C$35-$C$34),ROUNDUP(($C$31+$C$36-$C$30*(1-$C$35))/(1-$C$35-$C$34),0)-0.01,ROUNDUP(($C$31+$C$36-$C$30*(1-$C$35))/(1-$C$35-$C$34),0)+0.99),ROUNDUP(($C$31+$C$36-$C$30*(1-$C$35))/(1-$C$35-$C$34),2)))) -> 25.99
B10: Material (pick from list) Material (elige de la lista) | C10: Qty Used Cantidad | D10: Unit Unidad | E10: Library Cost Costo de Lista | F10: Your Cost (optional) Tu Costo (opcional) | G10: Line Cost Costo
B11: Soy wax | C11: 7 | D11: =IF(B11="","",IFERROR(INDEX(Materials!$F$6:$F$205,MATCH(B11,Materials!$B$6:$B$205,0)),"")) -> oz | E11: =IF(B11="","",IFERROR(INDEX(Materials!$G$6:$G$205,MATCH(B11,Materials!$B$6:$B$205,0)),"")) -> 0.28125 | G11: =IF(OR(B11="",C11=""),"",IF(F11<>"",C11*F11,IF(E11="","",C11*E11))) -> 1.96875 | I11: Etsy fees at this price / Comisiones de Etsy | J11: =IF($J$9=0,0,(($J$9+$C$30)*$C$35+$C$36)) -> 2.91905
B12: Fragrance oil | C12: 0.6 | D12: =IF(B12="","",IFERROR(INDEX(Materials!$F$6:$F$205,MATCH(B12,Materials!$B$6:$B$205,0)),"")) -> oz | E12: =IF(B12="","",IFERROR(INDEX(Materials!$G$6:$G$205,MATCH(B12,Materials!$B$6:$B$205,0)),"")) -> 1.1 | G12: =IF(OR(B12="",C12=""),"",IF(F12<>"",C12*F12,IF(E12="","",C12*E12))) -> 0.66 | I12: Your profit per sale / Tu ganancia por venta | J12: =IF($J$9=0,0,($J$9+$C$30-(($J$9+$C$30)*$C$35+$C$36)-$C$31)) -> 7.9223
B13: Cotton wick | C13: 1 | D13: =IF(B13="","",IFERROR(INDEX(Materials!$F$6:$F$205,MATCH(B13,Materials!$B$6:$B$205,0)),"")) -> each | E13: =IF(B13="","",IFERROR(INDEX(Materials!$G$6:$G$205,MATCH(B13,Materials!$B$6:$B$205,0)),"")) -> 0.1199 | G13: =IF(OR(B13="",C13=""),"",IF(F13<>"",C13*F13,IF(E13="","",C13*E13))) -> 0.1199 | I13: Profit margin / Margen de ganancia | J13: =IF($J$9=0,0,J12/$J$9) -> 0.30482109
B14: Amber jar 8 oz | C14: 1 | D14: =IF(B14="","",IFERROR(INDEX(Materials!$F$6:$F$205,MATCH(B14,Materials!$B$6:$B$205,0)),"")) -> each | E14: =IF(B14="","",IFERROR(INDEX(Materials!$G$6:$G$205,MATCH(B14,Materials!$B$6:$B$205,0)),"")) -> 1.45 | G14: =IF(OR(B14="",C14=""),"",IF(F14<>"",C14*F14,IF(E14="","",C14*E14))) -> 1.45 | I14: You earn per hour (profit + labor) / Ganas por hora | J14: =IF(OR(C24="",C24=0),0,(J12+C26)/(C24/60)) -> 59.6115
B15: Product label | C15: 1 | D15: =IF(B15="","",IFERROR(INDEX(Materials!$F$6:$F$205,MATCH(B15,Materials!$B$6:$B$205,0)),"")) -> each | E15: =IF(B15="","",IFERROR(INDEX(Materials!$G$6:$G$205,MATCH(B15,Materials!$B$6:$B$205,0)),"")) -> 0.15 | G15: =IF(OR(B15="",C15=""),"",IF(F15<>"",C15*F15,IF(E15="","",C15*E15))) -> 0.15 | I15: =IF(1-$C$35-$C$34<=0,"⚠ Target margin too high for these fees / Margen objetivo demasiado alto","")
D16: =IF(B16="","",IFERROR(INDEX(Materials!$F$6:$F$205,MATCH(B16,Materials!$B$6:$B$205,0)),"")) | E16: =IF(B16="","",IFERROR(INDEX(Materials!$G$6:$G$205,MATCH(B16,Materials!$B$6:$B$205,0)),"")) | G16: =IF(OR(B16="",C16=""),"",IF(F16<>"",C16*F16,IF(E16="","",C16*E16))) | I16: =IF(AND(B16<>"",E16="",F16=""),"⚠ Not in Materials – type Your Cost / Escribe tu costo","")
D17: =IF(B17="","",IFERROR(INDEX(Materials!$F$6:$F$205,MATCH(B17,Materials!$B$6:$B$205,0)),"")) | E17: =IF(B17="","",IFERROR(INDEX(Materials!$G$6:$G$205,MATCH(B17,Materials!$B$6:$B$205,0)),"")) | G17: =IF(OR(B17="",C17=""),"",IF(F17<>"",C17*F17,IF(E17="","",C17*E17))) | I17: Test Your Own Price / Prueba tu Precio
D18: =IF(B18="","",IFERROR(INDEX(Materials!$F$6:$F$205,MATCH(B18,Materials!$B$6:$B$205,0)),"")) | E18: =IF(B18="","",IFERROR(INDEX(Materials!$G$6:$G$205,MATCH(B18,Materials!$B$6:$B$205,0)),"")) | G18: =IF(OR(B18="",C18=""),"",IF(F18<>"",C18*F18,IF(E18="","",C18*E18))) | I18: Your price / Tu precio | J18: 29.99
D19: =IF(B19="","",IFERROR(INDEX(Materials!$F$6:$F$205,MATCH(B19,Materials!$B$6:$B$205,0)),"")) | E19: =IF(B19="","",IFERROR(INDEX(Materials!$G$6:$G$205,MATCH(B19,Materials!$B$6:$B$205,0)),"")) | G19: =IF(OR(B19="",C19=""),"",IF(F19<>"",C19*F19,IF(E19="","",C19*E19))) | I19: Etsy fees / Comisiones | J19: =IF($J$18="",0,(($J$18+$C$30)*$C$35+$C$36)) -> 3.29905
D20: =IF(B20="","",IFERROR(INDEX(Materials!$F$6:$F$205,MATCH(B20,Materials!$B$6:$B$205,0)),"")) | E20: =IF(B20="","",IFERROR(INDEX(Materials!$G$6:$G$205,MATCH(B20,Materials!$B$6:$B$205,0)),"")) | G20: =IF(OR(B20="",C20=""),"",IF(F20<>"",C20*F20,IF(E20="","",C20*E20))) | I20: Profit per sale / Ganancia por venta | J20: =IF($J$18="",0,($J$18+$C$30-(($J$18+$C$30)*$C$35+$C$36)-$C$31)) -> 11.5423
B21: MATERIALS TOTAL / TOTAL MATERIALES | G21: =SUM(G11:G20) -> 4.34865 | I21: Profit margin / Margen | J21: =IF(OR($J$18="",$J$18=0),0,J20/$J$18) -> 0.38487162
I22: You earn per hour / Ganas por hora | J22: =IF(OR(C24="",C24=0,J18=""),0,(J20+C26)/(C24/60)) -> 77.7115
B23: 3 · Time & Other Costs / Tiempo y Otros Costos | I23: =IF($J$18="","",IF(J20<0,"⚠ LOSING MONEY / PIERDES DINERO",IF(J21<$C$34,"● BELOW YOUR TARGET / DEBAJO DE TU OBJETIVO","✔ ON TARGET / EN TU OBJETIVO"))) -> ✔ ON TARGET / EN TU OBJETIVO
B24: Minutes to make one / Minutos para hacer uno | C24: 12
B25: Hourly rate / Tarifa por hora | C25: =Settings!$C$7 -> 20 | I25: Classic Formula / Fórmula Clásica
B26: Labor cost / Costo de mano de obra | C26: =IF(C24="",0,C24/60*C25) -> 4 | I26: Wholesale = cost × 2 / Mayoreo = costo × 2 | J26: =$C$31*2 -> 30.2973
B27: Packaging / Empaque | C27: 0.8 | I27: Retail = wholesale × 2 / Menudeo = mayoreo × 2 | J27: =$C$31*4 -> 60.5946
B28: Overhead per item / Gastos generales | C28: =Settings!$C$8 -> 0.5 | I28: Profit at retail after Etsy fees / Ganancia al menudeo | J28: =(J27+$C$30-((J27+$C$30)*$C$35+$C$36)-$C$31) -> 39.239463
B29: Shipping label you pay / Etiqueta de envío que pagas | C29: 5.5 | I29: Compare: the classic 2×2 formula ignores Etsy fees and your time. The recommended price above includes both. Compara: la fórmula clásica ignora las comisiones y tu tiempo. El precio recomendado incluye ambos.
B30: Shipping you charge the buyer (0 = free) / Envío que cobras | C30: 0
B31: TOTAL COST / COSTO TOTAL | C31: =G21+C26+C27+C28+C29 -> 15.14865
B33: 4 · Your Target / Tu Objetivo
B34: Target profit margin / Margen objetivo | C34: =Settings!$C$9 -> 0.3
B35: Etsy % fees (from Settings) / Comisiones % de Etsy | C35: =(Settings!$C$10+Settings!$C$11+IF(Settings!$C$15="Yes / Sí",Settings!$C$14,0)) -> 0.095
B36: Etsy fixed fees per order / Comisiones fijas por pedido | C36: =(Settings!$C$12+Settings!$C$13) -> 0.45

Sheet Product List
B1: ProfitTrack
B2: Product List / Lista de Productos
B3: Price your whole shop. Uses your hourly rate and Etsy fees from Settings. • Calcula todo tu catálogo con tu tarifa y las comisiones de Configuración.
B6: PRODUCTS PRICED | E6: AVERAGE MARGIN | I6: BELOW TARGET | M6: LOSING MONEY
B7: Productos con Precio | E7: Margen Promedio | I7: Debajo del Objetivo | M7: Perdiendo Dinero
B8: =SUM($T$12:$T$211) -> 8 | E8: =IF(SUM($X$12:$X$211)=0,0,SUM($Y$12:$Y$211)/SUM($X$12:$X$211)) -> 0.063486148 | I8: =SUM($V$12:$V$211) -> 2 | M8: =SUM($W$12:$W$211) -> 2
B9: =SUM($Z$12:$Z$211) -> 8 | E9: weighted by price / ponderado | I9: raise these prices / sube estos precios | M9: fix these first / arregla estos primero
B11: Product Producto | C11: Materials $ Materiales $ | D11: Minutes Minutos | E11: Packaging $ Empaque $ | F11: Ship Label $ Etiqueta $ | G11: Ship Charged $ Envío Cobrado $ | H11: Target Margin Margen Objetivo | I11: Total Cost Costo Total | J11: Break-even Precio Mínimo | K11: Recommended Recomendado | L11: Profit @ Rec. Ganancia | M11: Your Price Tu Precio | N11: Etsy Fees Comisiones | O11: Your Profit Tu Ganancia | P11: Your Margin Tu Margen | Q11: $ / Hour $ / Hora | R11: Status Estado | T11: Helper – do not edit: priced | U11: Helper – do not edit: margin | V11: Helper – do not edit: below target | W11: Helper – do not edit: losing | X11: Helper – do not edit: price | Y11: Helper – do not edit: profit | Z11: Helper – do not edit: listed
B12: Soy Candle 8 oz | C12: 4.35 | D12: 12 | E12: 0.8 | F12: 5.5 | G12: 0 | I12: =IF(B12="","",C12+IF(D12="",0,D12/60*Settings!$C$7)+E12+F12+Settings!$C$8) -> 15.15 | J12: =IF(B12="","",MAX(0,($I12+(Settings!$C$12+Settings!$C$13)-$G12*(1-(Settings!$C$10+Settings!$C$11+IF(Settings!$C$15="Yes / Sí",Settings!$C$14,0))))/(1-(Settings!$C$10+Settings!$C$11+IF(Settings!$C$15="Yes / Sí",Settings!$C$14,0))))) -> 17.237569 | K12: =IF(B12="","",IF(1-(Settings!$C$10+Settings!$C$11+IF(Settings!$C$15="Yes / Sí",Settings!$C$14,0))-IF(H12="",Settings!$C$9,H12)<=0,0,MAX(0,IF(Settings!$C$16="Yes / Sí",IF(ROUNDUP(($I12+(Settings!$C$12+Settings!$C$13)-$G12*(1-(Settings!$C$10+Settings!$C$11+IF(Settings!$C$15="Yes / Sí",Settings!$C$14,0))))/(1-(Settings!$C$10+Settings!$C$11+IF(Settings!$C$15="Yes / Sí",Settings!$C$14,0))-IF(H12="",Settings!$C$9,H12)),0)-0.01>=($I12+(Settings!$C$12+Settings!$C$13)-$G12*(1-(Settings!$C$10+Settings!$C$11+IF(Settings!$C$15="Yes / Sí",Settings!$C$14,0))))/(1-(Settings!$C$10+Settings!$C$11+IF(Settings!$C$15="Yes / Sí",Settings!$C$14,0))-IF(H12="",Settings!$C$9,H12)),ROUNDUP(($I12+(Settings!$C$12+Settings!$C$13)-$G12*(1-(Settings!$C$10+Settings!$C$11+IF(Settings!$C$15="Yes / Sí",Settings!$C$14,0))))/(1-(Settings!$C$10+Settings!$C$11+IF(Settings!$C$15="Yes / Sí",Settings!$C$14,0))-IF(H12="",Settings!$C$9,H12)),0)-0.01,ROUNDUP(($I12+(Settings!$C$12+Settings!$C$13)-$G12*(1-(Settings!$C$10+Settings!$C$11+IF(Settings!$C$15="Yes / Sí",Settings!$C$14,0))))/(1-(Settings!$C$10+Settings!$C$11+IF(Settings!$C$15="Yes / Sí",Settings!$C$14,0))-IF(H12="",Settings!$C$9,H12)),0)+0.99),ROUNDUP(($I12+(Settings!$C$12+Settings!$C$13)-$G12*(1-(Settings!$C$10+Settings!$C$11+IF(Settings!$C$15="Yes / Sí",Settings!$C$14,0))))/(1-(Settings!$C$10+Settings!$C$11+IF(Settings!$C$15="Yes / Sí",Settings!$C$14,0))-IF(H12="",Settings!$C$9,H12)),2))))) -> 25.99 | L12: =IF(OR(B12="",K12=0),"",(K12+$G12-((K12+$G12)*(Settings!$C$10+Settings!$C$11+IF(Settings!$C$15="Yes / Sí",Settings!$C$14,0))+(Settings!$C$12+Settings!$C$13))-$I12)) -> 7.92095 | M12: 29.99 | N12: =IF(OR(B12="",M12=""),"",((M12+$G12)*(Settings!$C$10+Settings!$C$11+IF(Settings!$C$15="Yes / Sí",Settings!$C$14,0))+(Settings!$C$12+Settings!$C$13))) -> 3.29905 | O12: =IF(OR(B12="",M12=""),"",(M12+$G12-((M12+$G12)*(Settings!$C$10+Settings!$C$11+IF(Settings!$C$15="Yes / Sí",Settings!$C$14,0))+(Settings!$C$12+Settings!$C$13))-$I12)) -> 11.54095 | P12: =IF(O12="","",IF(M12=0,0,O12/M12)) -> 0.38482661 | Q12: =IF(OR(O12="",D12="",D12=0),"",(O12+D12/60*Settings!$C$7)/(D12/60)) -> 77.70475 | R12: =IF(B12="","",IF(M12="","Enter your price / Escribe tu precio",IF(O12<0,"⚠ LOSING MONEY / PIERDES",IF(P12<IF(H12="",Settings!$C$9,H12),"● BELOW TARGET / DEBAJO","✔ ON TARGET / EN OBJETIVO")))) -> ✔ ON TARGET / EN OBJETIVO | T12: =IF(B12="",0,IF(M12="",0,1)) -> 1 | U12: =IF(T12=1,P12,0) -> 0.38482661 | V12: =IF(T12=1,IF(O12<0,0,IF(P12<IF(H12="",Settings!$C$9,H12),1,0)),0) -> 0 | W12: =IF(T12=1,IF(O12<0,1,0),0) -> 0 | X12: =IF(T12=1,M12,0) -> 29.99 | Y12: =IF(T12=1,O12,0) -> 11.54095 | Z12: =IF(B12="",0,1) -> 1
B13: Beaded Drop Earrings | C13: 2.1 | D13: 25 | E13: 0.6 | F13: 4.2 | G13: 0 | I13: =IF(B13="","",C13+IF(D13="",0,D13/60*Settings!$C$7)+E13+F13+Settings!$C$8) -> 15.733333 | J13: =IF(B13="","",MAX(0,($I13+(Settings!$C$12+Settings!$C$13)-$G13*(1-(Settings!$C$10+Settings!$C$11+IF(Settings!$C$15="Yes / Sí",Settings!$C$14,0))))/(1-(Settings!$C$10+Settings!$C$11+IF(Settings!$C$15="Yes / Sí",Settings!$C$14,0))))) -> 17.882136 | K13: =IF(B13="","",IF(1-(Settings!$C$10+Settings!$C$11+IF(Settings!$C$15="Yes / Sí",Settings!$C$14,0))-IF(H13="",Settings!$C$9,H13)<=0,0,MAX(0,IF(Settings!$C$16="Yes / Sí",IF(ROUNDUP(($I13+(Settings!$C$12+Settings!$C$13)-$G13*(1-(Settings!$C$10+Settings!$C$11+IF(Settings!$C$15="Yes / Sí",Settings!$C$14,0))))/(1-(Settings!$C$10+Settings!$C$11+IF(Settings!$C$15="Yes / Sí",Settings!$C$14,0))-IF(H13="",Settings!$C$9,H13)),0)-0.01>=($I13+(Settings!$C$12+Settings!$C$13)-$G13*(1-(Settings!$C$10+Settings!$C$11+IF(Settings!$C$15="Yes / Sí",Settings!$C$14,0))))/(1-(Settings!$C$10+Settings!$C$11+IF(Settings!$C$15="Yes / Sí",Settings!$C$14,0))-IF(H13="",Settings!$C$9,H13)),ROUNDUP(($I13+(Settings!$C$12+Settings!$C$13)-$G13*(1-(Settings!$C$10+Settings!$C$11+IF(Settings!$C$15="Yes / Sí",Settings!$C$14,0))))/(1-(Settings!$C$10+Settings!$C$11+IF(Settings!$C$15="Yes / Sí",Settings!$C$14,0))-IF(H13="",Settings!$C$9,H13)),0)-0.01,ROUNDUP(($I13+(Settings!$C$12+Settings!$C$13)-$G13*(1-(Settings!$C$10+Settings!$C$11+IF(Settings!$C$15="Yes / Sí",Settings!$C$14,0))))/(1-(Settings!$C$10+Settings!$C$11+IF(Settings!$C$15="Yes / Sí",Settings!$C$14,0))-IF(H13="",Settings!$C$9,H13)),0)+0.99),ROUNDUP(($I13+(Settings!$C$12+Settings!$C$13)-$G13*(1-(Settings!$C$10+Settings!$C$11+IF(Settings!$C$15="Yes / Sí",Settings!$C$14,0))))/(1-(Settings!$C$10+Settings!$C$11+IF(Settings!$C$15="Yes / Sí",Settings!$C$14,0))-IF(H13="",Settings!$C$9,H13)),2))))) -> 26.99 | L13: =IF(OR(B13="",K13=0),"",(K13+$G13-((K13+$G13)*(Settings!$C$10+Settings!$C$11+IF(Settings!$C$15="Yes / Sí",Settings!$C$14,0))+(Settings!$C$12+Settings!$C$13))-$I13)) -> 8.2426167 | M13: 28 | N13: =IF(OR(B13="",M13=""),"",((M13+$G13)*(Settings!$C$10+Settings!$C$11+IF(Settings!$C$15="Yes / Sí",Settings!$C$14,0))+(Settings!$C$12+Settings!$C$13))) -> 3.11 | O13: =IF(OR(B13="",M13=""),"",(M13+$G13-((M13+$G13)*(Settings!$C$10+Settings!$C$11+IF(Settings!$C$15="Yes / Sí",Settings!$C$14,0))+(Settings!$C$12+Settings!$C$13))-$I13)) -> 9.1566667 | P13: =IF(O13="","",IF(M13=0,0,O13/M13)) -> 0.32702381 | Q13: =IF(OR(O13="",D13="",D13=0),"",(O13+D13/60*Settings!$C$7)/(D13/60)) -> 41.976 | R13: =IF(B13="","",IF(M13="","Enter your price / Escribe tu precio",IF(O13<0,"⚠ LOSING MONEY / PIERDES",IF(P13<IF(H13="",Settings!$C$9,H13),"● BELOW TARGET / DEBAJO","✔ ON TARGET / EN OBJETIVO")))) -> ✔ ON TARGET / EN OBJETIVO | T13: =IF(B13="",0,IF(M13="",0,1)) -> 1 | U13: =IF(T13=1,P13,0) -> 0.32702381 | V13: =IF(T13=1,IF(O13<0,0,IF(P13<IF(H13="",Settings!$C$9,H13),1,0)),0) -> 0 | W13: =IF(T13=1,IF(O13<0,1,0),0) -> 0 | X13: =IF(T13=1,M13,0) -> 28 | Y13: =IF(T13=1,O13,0) -> 9.1566667 | Z13: =IF(B13="",0,1) -> 1
B14: Merino Crochet Beanie | C14: 9.5 | D14: 150 | E14: 1 | F14: 5.8 | G14: 0 | I14: =IF(B14="","",C14+IF(D14="",0,D14/60*Settings!$C$7)+E14+F14+Settings!$C$8) -> 66.8 | J14: =IF(B14="","",MAX(0,($I14+(Settings!$C$12+Settings!$C$13)-$G14*(1-(Settings!$C$10+Settings!$C$11+IF(Settings!$C$15="Yes / Sí",Settings!$C$14,0))))/(1-(Settings!$C$10+Settings!$C$11+IF(Settings!$C$15="Yes / Sí",Settings!$C$14,0))))) -> 74.309392 | K14: =IF(B14="","",IF(1-(Settings!$C$10+Settings!$C$11+IF(Settings!$C$15="Yes / Sí",Settings!$C$14,0))-IF(H14="",Settings!$C$9,H14)<=0,0,MAX(0,IF(Settings!$C$16="Yes / Sí",IF(ROUNDUP(($I14+(Settings!$C$12+Settings!$C$13)-$G14*(1-(Settings!$C$10+Settings!$C$11+IF(Settings!$C$15="Yes / Sí",Settings!$C$14,0))))/(1-(Settings!$C$10+Settings!$C$11+IF(Settings!$C$15="Yes / Sí",Settings!$C$14,0))-IF(H14="",Settings!$C$9,H14)),0)-0.01>=($I14+(Settings!$C$12+Settings!$C$13)-$G14*(1-(Settings!$C$10+Settings!$C$11+IF(Settings!$C$15="Yes / Sí",Settings!$C$14,0))))/(1-(Settings!$C$10+Settings!$C$11+IF(Settings!$C$15="Yes / Sí",Settings!$C$14,0))-IF(H14="",Settings!$C$9,H14)),ROUNDUP(($I14+(Settings!$C$12+Settings!$C$13)-$G14*(1-(Settings!$C$10+Settings!$C$11+IF(Settings!$C$15="Yes / Sí",Settings!$C$14,0))))/(1-(Settings!$C$10+Settings!$C$11+IF(Settings!$C$15="Yes / Sí",Settings!$C$14,0))-IF(H14="",Settings!$C$9,H14)),0)-0.01,ROUNDUP(($I14+(Settings!$C$12+Settings!$C$13)-$G14*(1-(Settings!$C$10+Settings!$C$11+IF(Settings!$C$15="Yes / Sí",Settings!$C$14,0))))/(1-(Settings!$C$10+Settings!$C$11+IF(Settings!$C$15="Yes / Sí",Settings!$C$14,0))-IF(H14="",Settings!$C$9,H14)),0)+0.99),ROUNDUP(($I14+(Settings!$C$12+Settings!$C$13)-$G14*(1-(Settings!$C$10+Settings!$C$11+IF(Settings!$C$15="Yes / Sí",Settings!$C$14,0))))/(1-(Settings!$C$10+Settings!$C$11+IF(Settings!$C$15="Yes / Sí",Settings!$C$14,0))-IF(H14="",Settings!$C$9,H14)),2))))) -> 111.99 | L14: =IF(OR(B14="",K14=0),"",(K14+$G14-((K14+$G14)*(Settings!$C$10+Settings!$C$11+IF(Settings!$C$15="Yes / Sí",Settings!$C$14,0))+(Settings!$C$12+Settings!$C$13))-$I14)) -> 34.10095 | M14: 45 | N14: =IF(OR(B14="",M14=""),"",((M14+$G14)*(Settings!$C$10+Settings!$C$11+IF(Settings!$C$15="Yes / Sí",Settings!$C$14,0))+(Settings!$C$12+Settings!$C$13))) -> 4.725 | O14: =IF(OR(B14="",M14=""),"",(M14+$G14-((M14+$G14)*(Settings!$C$10+Settings!$C$11+IF(Settings!$C$15="Yes / Sí",Settings!$C$14,0))+(Settings!$C$12+Settings!$C$13))-$I14)) -> -26.525 | P14: =IF(O14="","",IF(M14=0,0,O14/M14)) -> -0.58944444 | Q14: =IF(OR(O14="",D14="",D14=0),"",(O14+D14/60*Settings!$C$7)/(D14/60)) -> 9.39 | R14: =IF(B14="","",IF(M14="","Enter your price / Escribe tu precio",IF(O14<0,"⚠ LOSING MONEY / PIERDES",IF(P14<IF(H14="",Settings!$C$9,H14),"● BELOW TARGET / DEBAJO","✔ ON TARGET / EN OBJETIVO")))) -> ⚠ LOSING MONEY / PIERDES | T14: =IF(B14="",0,IF(M14="",0,1)) -> 1 | U14: =IF(T14=1,P14,0) -> -0.58944444 | V14: =IF(T14=1,IF(O14<0,0,IF(P14<IF(H14="",Settings!$C$9,H14),1,0)),0) -> 0 | W14: =IF(T14=1,IF(O14<0,1,0),0) -> 1 | X14: =IF(T14=1,M14,0) -> 45 | Y14: =IF(T14=1,O14,0) -> -26.525 | Z14: =IF(B14="",0,1) -> 1
B15: Vinyl Sticker Pack (5) | C15: 1.2 | D15: 10 | E15: 0.3 | F15: 1 | G15: 0 | I15: =IF(B15="","",C15+IF(D15="",0,D15/60*Settings!$C$7)+E15+F15+Settings!$C$8) -> 6.3333333 | J15: =IF(B15="","",MAX(0,($I15+(Settings!$C$12+Settings!$C$13)-$G15*(1-(Settings!$C$10+Settings!$C$11+IF(Settings!$C$15="Yes / Sí",Settings!$C$14,0))))/(1-(Settings!$C$10+Settings!$C$11+IF(Settings!$C$15="Yes / Sí",Settings!$C$14,0))))) -> 7.4953959 | K15: =IF(B15="","",IF(1-(Settings!$C$10+Settings!$C$11+IF(Settings!$C$15="Yes / Sí",Settings!$C$14,0))-IF(H15="",Settings!$C$9,H15)<=0,0,MAX(0,IF(Settings!$C$16="Yes / Sí",IF(ROUNDUP(($I15+(Settings!$C$12+Settings!$C$13)-$G15*(1-(Settings!$C$10+Settings!$C$11+IF(Settings!$C$15="Yes / Sí",Settings!$C$14,0))))/(1-(Settings!$C$10+Settings!$C$11+IF(Settings!$C$15="Yes / Sí",Settings!$C$14,0))-IF(H15="",Settings!$C$9,H15)),0)-0.01>=($I15+(Settings!$C$12+Settings!$C$13)-$G15*(1-(Settings!$C$10+Settings!$C$11+IF(Settings!$C$15="Yes / Sí",Settings!$C$14,0))))/(1-(Settings!$C$10+Settings!$C$11+IF(Settings!$C$15="Yes / Sí",Settings!$C$14,0))-IF(H15="",Settings!$C$9,H15)),ROUNDUP(($I15+(Settings!$C$12+Settings!$C$13)-$G15*(1-(Settings!$C$10+Settings!$C$11+IF(Settings!$C$15="Yes / Sí",Settings!$C$14,0))))/(1-(Settings!$C$10+Settings!$C$11+IF(Settings!$C$15="Yes / Sí",Settings!$C$14,0))-IF(H15="",Settings!$C$9,H15)),0)-0.01,ROUNDUP(($I15+(Settings!$C$12+Settings!$C$13)-$G15*(1-(Settings!$C$10+Settings!$C$11+IF(Settings!$C$15="Yes / Sí",Settings!$C$14,0))))/(1-(Settings!$C$10+Settings!$C$11+IF(Settings!$C$15="Yes / Sí",Settings!$C$14,0))-IF(H15="",Settings!$C$9,H15)),0)+0.99),ROUNDUP(($I15+(Settings!$C$12+Settings!$C$13)-$G15*(1-(Settings!$C$10+Settings!$C$11+IF(Settings!$C$15="Yes / Sí",Settings!$C$14,0))))/(1-(Settings!$C$10+Settings!$C$11+IF(Settings!$C$15="Yes / Sí",Settings!$C$14,0))-IF(H15="",Settings!$C$9,H15)),2))))) -> 11.99 | L15: =IF(OR(B15="",K15=0),"",(K15+$G15-((K15+$G15)*(Settings!$C$10+Settings!$C$11+IF(Settings!$C$15="Yes / Sí",Settings!$C$14,0))+(Settings!$C$12+Settings!$C$13))-$I15)) -> 4.0676167 | M15: 12 | N15: =IF(OR(B15="",M15=""),"",((M15+$G15)*(Settings!$C$10+Settings!$C$11+IF(Settings!$C$15="Yes / Sí",Settings!$C$14,0))+(Settings!$C$12+Settings!$C$13))) -> 1.59 | O15: =IF(OR(B15="",M15=""),"",(M15+$G15-((M15+$G15)*(Settings!$C$10+Settings!$C$11+IF(Settings!$C$15="Yes / Sí",Settings!$C$14,0))+(Settings!$C$12+Settings!$C$13))-$I15)) -> 4.0766667 | P15: =IF(O15="","",IF(M15=0,0,O15/M15)) -> 0.33972222 | Q15: =IF(OR(O15="",D15="",D15=0),"",(O15+D15/60*Settings!$C$7)/(D15/60)) -> 44.46 | R15: =IF(B15="","",IF(M15="","Enter your price / Escribe tu precio",IF(O15<0,"⚠ LOSING MONEY / PIERDES",IF(P15<IF(H15="",Settings!$C$9,H15),"● BELOW TARGET / DEBAJO","✔ ON TARGET / EN OBJETIVO")))) -> ✔ ON TARGET / EN OBJETIVO | T15: =IF(B15="",0,IF(M15="",0,1)) -> 1 | U15: =IF(T15=1,P15,0) -> 0.33972222 | V15: =IF(T15=1,IF(O15<0,0,IF(P15<IF(H15="",Settings!$C$9,H15),1,0)),0) -> 0 | W15: =IF(T15=1,IF(O15<0,1,0),0) -> 0 | X15: =IF(T15=1,M15,0) -> 12 | Y15: =IF(T15=1,O15,0) -> 4.0766667 | Z15: =IF(B15="",0,1) -> 1
B16: Personalized Wood Sign | C16: 6.75 | D16: 60 | E16: 2.5 | F16: 9.5 | G16: 0 | H16: 0.35 | I16: =IF(B16="","",C16+IF(D16="",0,D16/60*Settings!$C$7)+E16+F16+Settings!$C$8) -> 39.25 | J16: =IF(B16="","",MAX(0,($I16+(Settings!$C$12+Settings!$C$13)-$G16*(1-(Settings!$C$10+Settings!$C$11+IF(Settings!$C$15="Yes / Sí",Settings!$C$14,0))))/(1-(Settings!$C$10+Settings!$C$11+IF(Settings!$C$15="Yes / Sí",Settings!$C$14,0))))) -> 43.867403 | K16: =IF(B16="","",IF(1-(Settings!$C$10+Settings!$C$11+IF(Settings!$C$15="Yes / Sí",Settings!$C$14,0))-IF(H16="",Settings!$C$9,H16)<=0,0,MAX(0,IF(Settings!$C$16="Yes / Sí",IF(ROUNDUP(($I16+(Settings!$C$12+Settings!$C$13)-$G16*(1-(Settings!$C$10+Settings!$C$11+IF(Settings!$C$15="Yes / Sí",Settings!$C$14,0))))/(1-(Settings!$C$10+Settings!$C$11+IF(Settings!$C$15="Yes / Sí",Settings!$C$14,0))-IF(H16="",Settings!$C$9,H16)),0)-0.01>=($I16+(Settings!$C$12+Settings!$C$13)-$G16*(1-(Settings!$C$10+Settings!$C$11+IF(Settings!$C$15="Yes / Sí",Settings!$C$14,0))))/(1-(Settings!$C$10+Settings!$C$11+IF(Settings!$C$15="Yes / Sí",Settings!$C$14,0))-IF(H16="",Settings!$C$9,H16)),ROUNDUP(($I16+(Settings!$C$12+Settings!$C$13)-$G16*(1-(Settings!$C$10+Settings!$C$11+IF(Settings!$C$15="Yes / Sí",Settings!$C$14,0))))/(1-(Settings!$C$10+Settings!$C$11+IF(Settings!$C$15="Yes / Sí",Settings!$C$14,0))-IF(H16="",Settings!$C$9,H16)),0)-0.01,ROUNDUP(($I16+(Settings!$C$12+Settings!$C$13)-$G16*(1-(Settings!$C$10+Settings!$C$11+IF(Settings!$C$15="Yes / Sí",Settings!$C$14,0))))/(1-(Settings!$C$10+Settings!$C$11+IF(Settings!$C$15="Yes / Sí",Settings!$C$14,0))-IF(H16="",Settings!$C$9,H16)),0)+0.99),ROUNDUP(($I16+(Settings!$C$12+Settings!$C$13)-$G16*(1-(Settings!$C$10+Settings!$C$11+IF(Settings!$C$15="Yes / Sí",Settings!$C$14,0))))/(1-(Settings!$C$10+Settings!$C$11+IF(Settings!$C$15="Yes / Sí",Settings!$C$14,0))-IF(H16="",Settings!$C$9,H16)),2))))) -> 71.99 | L16: =IF(OR(B16="",K16=0),"",(K16+$G16-((K16+$G16)*(Settings!$C$10+Settings!$C$11+IF(Settings!$C$15="Yes / Sí",Settings!$C$14,0))+(Settings!$C$12+Settings!$C$13))-$I16)) -> 25.45095 | M16: 49 | N16: =IF(OR(B16="",M16=""),"",((M16+$G16)*(Settings!$C$10+Settings!$C$11+IF(Settings!$C$15="Yes / Sí",Settings!$C$14,0))+(Settings!$C$12+Settings!$C$13))) -> 5.105 | O16: =IF(OR(B16="",M16=""),"",(M16+$G16-((M16+$G16)*(Settings!$C$10+Settings!$C$11+IF(Settings!$C$15="Yes / Sí",Settings!$C$14,0))+(Settings!$C$12+Settings!$C$13))-$I16)) -> 4.645 | P16: =IF(O16="","",IF(M16=0,0,O16/M16)) -> 0.094795918 | Q16: =IF(OR(O16="",D16="",D16=0),"",(O16+D16/60*Settings!$C$7)/(D16/60)) -> 24.645 | R16: =IF(B16="","",IF(M16="","Enter your price / Escribe tu precio",IF(O16<0,"⚠ LOSING MONEY / PIERDES",IF(P16<IF(H16="",Settings!$C$9,H16),"● BELOW TARGET / DEBAJO","✔ ON TARGET / EN OBJETIVO")))) -> ● BELOW TARGET / DEBAJO | T16: =IF(B16="",0,IF(M16="",0,1)) -> 1 | U16: =IF(T16=1,P16,0) -> 0.094795918 | V16: =IF(T16=1,IF(O16<0,0,IF(P16<IF(H16="",Settings!$C$9,H16),1,0)),0) -> 1 | W16: =IF(T16=1,IF(O16<0,1,0),0) -> 0 | X16: =IF(T16=1,M16,0) -> 49 | Y16: =IF(T16=1,O16,0) -> 4.645 | Z16: =IF(B16="",0,1) -> 1
B17: Goat Milk Soap Bar | C17: 1.35 | D17: 8 | E17: 0.4 | F17: 4.5 | G17: 4.5 | I17: =IF(B17="","",C17+IF(D17="",0,D17/60*Settings!$C$7)+E17+F17+Settings!$C$8) -> 9.4166667 | J17: =IF(B17="","",MAX(0,($I17+(Settings!$C$12+Settings!$C$13)-$G17*(1-(Settings!$C$10+Settings!$C$11+IF(Settings!$C$15="Yes / Sí",Settings!$C$14,0))))/(1-(Settings!$C$10+Settings!$C$11+IF(Settings!$C$15="Yes / Sí",Settings!$C$14,0))))) -> 6.4023941 | K17: =IF(B17="","",IF(1-(Settings!$C$10+Settings!$C$11+IF(Settings!$C$15="Yes / Sí",Settings!$C$14,0))-IF(H17="",Settings!$C$9,H17)<=0,0,MAX(0,IF(Settings!$C$16="Yes / Sí",IF(ROUNDUP(($I17+(Settings!$C$12+Settings!$C$13)-$G17*(1-(Settings!$C$10+Settings!$C$11+IF(Settings!$C$15="Yes / Sí",Settings!$C$14,0))))/(1-(Settings!$C$10+Settings!$C$11+IF(Settings!$C$15="Yes / Sí",Settings!$C$14,0))-IF(H17="",Settings!$C$9,H17)),0)-0.01>=($I17+(Settings!$C$12+Settings!$C$13)-$G17*(1-(Settings!$C$10+Settings!$C$11+IF(Settings!$C$15="Yes / Sí",Settings!$C$14,0))))/(1-(Settings!$C$10+Settings!$C$11+IF(Settings!$C$15="Yes / Sí",Settings!$C$14,0))-IF(H17="",Settings!$C$9,H17)),ROUNDUP(($I17+(Settings!$C$12+Settings!$C$13)-$G17*(1-(Settings!$C$10+Settings!$C$11+IF(Settings!$C$15="Yes / Sí",Settings!$C$14,0))))/(1-(Settings!$C$10+Settings!$C$11+IF(Settings!$C$15="Yes / Sí",Settings!$C$14,0))-IF(H17="",Settings!$C$9,H17)),0)-0.01,ROUNDUP(($I17+(Settings!$C$12+Settings!$C$13)-$G17*(1-(Settings!$C$10+Settings!$C$11+IF(Settings!$C$15="Yes / Sí",Settings!$C$14,0))))/(1-(Settings!$C$10+Settings!$C$11+IF(Settings!$C$15="Yes / Sí",Settings!$C$14,0))-IF(H17="",Settings!$C$9,H17)),0)+0.99),ROUNDUP(($I17+(Settings!$C$12+Settings!$C$13)-$G17*(1-(Settings!$C$10+Settings!$C$11+IF(Settings!$C$15="Yes / Sí",Settings!$C$14,0))))/(1-(Settings!$C$10+Settings!$C$11+IF(Settings!$C$15="Yes / Sí",Settings!$C$14,0))-IF(H17="",Settings!$C$9,H17)),2))))) -> 9.99 | L17: =IF(OR(B17="",K17=0),"",(K17+$G17-((K17+$G17)*(Settings!$C$10+Settings!$C$11+IF(Settings!$C$15="Yes / Sí",Settings!$C$14,0))+(Settings!$C$12+Settings!$C$13))-$I17)) -> 3.2467833 | M17: 10.5 | N17: =IF(OR(B17="",M17=""),"",((M17+$G17)*(Settings!$C$10+Settings!$C$11+IF(Settings!$C$15="Yes / Sí",Settings!$C$14,0))+(Settings!$C$12+Settings!$C$13))) -> 1.875 | O17: =IF(OR(B17="",M17=""),"",(M17+$G17-((M17+$G17)*(Settings!$C$10+Settings!$C$11+IF(Settings!$C$15="Yes / Sí",Settings!$C$14,0))+(Settings!$C$12+Settings!$C$13))-$I17)) -> 3.7083333 | P17: =IF(O17="","",IF(M17=0,0,O17/M17)) -> 0.3531746 | Q17: =IF(OR(O17="",D17="",D17=0),"",(O17+D17/60*Settings!$C$7)/(D17/60)) -> 47.8125 | R17: =IF(B17="","",IF(M17="","Enter your price / Escribe tu precio",IF(O17<0,"⚠ LOSING MONEY / PIERDES",IF(P17<IF(H17="",Settings!$C$9,H17),"● BELOW TARGET / DEBAJO","✔ ON TARGET / EN OBJETIVO")))) -> ✔ ON TARGET / EN OBJETIVO | T17: =IF(B17="",0,IF(M17="",0,1)) -> 1 | U17: =IF(T17=1,P17,0) -> 0.3531746 | V17: =IF(T17=1,IF(O17<0,0,IF(P17<IF(H17="",Settings!$C$9,H17),1,0)),0) -> 0 | W17: =IF(T17=1,IF(O17<0,1,0),0) -> 0 | X17: =IF(T17=1,M17,0) -> 10.5 | Y17: =IF(T17=1,O17,0) -> 3.7083333 | Z17: =IF(B17="",0,1) -> 1
B18: Resin Keychain | C18: 1.8 | D18: 20 | E18: 0.3 | F18: 4.2 | G18: 0 | I18: =IF(B18="","",C18+IF(D18="",0,D18/60*Settings!$C$7)+E18+F18+Settings!$C$8) -> 13.466667 | J18: =IF(B18="","",MAX(0,($I18+(Settings!$C$12+Settings!$C$13)-$G18*(1-(Settings!$C$10+Settings!$C$11+IF(Settings!$C$15="Yes / Sí",Settings!$C$14,0))))/(1-(Settings!$C$10+Settings!$C$11+IF(Settings!$C$15="Yes / Sí",Settings!$C$14,0))))) -> 15.377532 | K18: =IF(B18="","",IF(1-(Settings!$C$10+Settings!$C$11+IF(Settings!$C$15="Yes / Sí",Settings!$C$14,0))-IF(H18="",Settings!$C$9,H18)<=0,0,MAX(0,IF(Settings!$C$16="Yes / Sí",IF(ROUNDUP(($I18+(Settings!$C$12+Settings!$C$13)-$G18*(1-(Settings!$C$10+Settings!$C$11+IF(Settings!$C$15="Yes / Sí",Settings!$C$14,0))))/(1-(Settings!$C$10+Settings!$C$11+IF(Settings!$C$15="Yes / Sí",Settings!$C$14,0))-IF(H18="",Settings!$C$9,H18)),0)-0.01>=($I18+(Settings!$C$12+Settings!$C$13)-$G18*(1-(Settings!$C$10+Settings!$C$11+IF(Settings!$C$15="Yes / Sí",Settings!$C$14,0))))/(1-(Settings!$C$10+Settings!$C$11+IF(Settings!$C$15="Yes / Sí",Settings!$C$14,0))-IF(H18="",Settings!$C$9,H18)),ROUNDUP(($I18+(Settings!$C$12+Settings!$C$13)-$G18*(1-(Settings!$C$10+Settings!$C$11+IF(Settings!$C$15="Yes / Sí",Settings!$C$14,0))))/(1-(Settings!$C$10+Settings!$C$11+IF(Settings!$C$15="Yes / Sí",Settings!$C$14,0))-IF(H18="",Settings!$C$9,H18)),0)-0.01,ROUNDUP(($I18+(Settings!$C$12+Settings!$C$13)-$G18*(1-(Settings!$C$10+Settings!$C$11+IF(Settings!$C$15="Yes / Sí",Settings!$C$14,0))))/(1-(Settings!$C$10+Settings!$C$11+IF(Settings!$C$15="Yes / Sí",Settings!$C$14,0))-IF(H18="",Settings!$C$9,H18)),0)+0.99),ROUNDUP(($I18+(Settings!$C$12+Settings!$C$13)-$G18*(1-(Settings!$C$10+Settings!$C$11+IF(Settings!$C$15="Yes / Sí",Settings!$C$14,0))))/(1-(Settings!$C$10+Settings!$C$11+IF(Settings!$C$15="Yes / Sí",Settings!$C$14,0))-IF(H18="",Settings!$C$9,H18)),2))))) -> 23.99 | L18: =IF(OR(B18="",K18=0),"",(K18+$G18-((K18+$G18)*(Settings!$C$10+Settings!$C$11+IF(Settings!$C$15="Yes / Sí",Settings!$C$14,0))+(Settings!$C$12+Settings!$C$13))-$I18)) -> 7.7942833 | M18: 12 | N18: =IF(OR(B18="",M18=""),"",((M18+$G18)*(Settings!$C$10+Settings!$C$11+IF(Settings!$C$15="Yes / Sí",Settings!$C$14,0))+(Settings!$C$12+Settings!$C$13))) -> 1.59 | O18: =IF(OR(B18="",M18=""),"",(M18+$G18-((M18+$G18)*(Settings!$C$10+Settings!$C$11+IF(Settings!$C$15="Yes / Sí",Settings!$C$14,0))+(Settings!$C$12+Settings!$C$13))-$I18)) -> -3.0566667 | P18: =IF(O18="","",IF(M18=0,0,O18/M18)) -> -0.25472222 | Q18: =IF(OR(O18="",D18="",D18=0),"",(O18+D18/60*Settings!$C$7)/(D18/60)) -> 10.83 | R18: =IF(B18="","",IF(M18="","Enter your price / Escribe tu precio",IF(O18<0,"⚠ LOSING MONEY / PIERDES",IF(P18<IF(H18="",Settings!$C$9,H18),"● BELOW TARGET / DEBAJO","✔ ON TARGET / EN OBJETIVO")))) -> ⚠ LOSING MONEY / PIERDES | T18: =IF(B18="",0,IF(M18="",0,1)) -> 1 | U18: =IF(T18=1,P18,0) -> -0.25472222 | V18: =IF(T18=1,IF(O18<0,0,IF(P18<IF(H18="",Settings!$C$9,H18),1,0)),0) -> 0 | W18: =IF(T18=1,IF(O18<0,1,0),0) -> 1 | X18: =IF(T18=1,M18,0) -> 12 | Y18: =IF(T18=1,O18,0) -> -3.0566667 | Z18: =IF(B18="",0,1) -> 1
B19: Embroidered Tote Bag | C19: 4.2 | D19: 45 | E19: 0.8 | F19: 6.1 | G19: 0 | I19: =IF(B19="","",C19+IF(D19="",0,D19/60*Settings!$C$7)+E19+F19+Settings!$C$8) -> 26.6 | J19: =IF(B19="","",MAX(0,($I19+(Settings!$C$12+Settings!$C$13)-$G19*(1-(Settings!$C$10+Settings!$C$11+IF(Settings!$C$15="Yes / Sí",Settings!$C$14,0))))/(1-(Settings!$C$10+Settings!$C$11+IF(Settings!$C$15="Yes / Sí",Settings!$C$14,0))))) -> 29.889503 | K19: =IF(B19="","",IF(1-(Settings!$C$10+Settings!$C$11+IF(Settings!$C$15="Yes / Sí",Settings!$C$14,0))-IF(H19="",Settings!$C$9,H19)<=0,0,MAX(0,IF(Settings!$C$16="Yes / Sí",IF(ROUNDUP(($I19+(Settings!$C$12+Settings!$C$13)-$G19*(1-(Settings!$C$10+Settings!$C$11+IF(Settings!$C$15="Yes / Sí",Settings!$C$14,0))))/(1-(Settings!$C$10+Settings!$C$11+IF(Settings!$C$15="Yes / Sí",Settings!$C$14,0))-IF(H19="",Settings!$C$9,H19)),0)-0.01>=($I19+(Settings!$C$12+Settings!$C$13)-$G19*(1-(Settings!$C$10+Settings!$C$11+IF(Settings!$C$15="Yes / Sí",Settings!$C$14,0))))/(1-(Settings!$C$10+Settings!$C$11+IF(Settings!$C$15="Yes / Sí",Settings!$C$14,0))-IF(H19="",Settings!$C$9,H19)),ROUNDUP(($I19+(Settings!$C$12+Settings!$C$13)-$G19*(1-(Settings!$C$10+Settings!$C$11+IF(Settings!$C$15="Yes / Sí",Settings!$C$14,0))))/(1-(Settings!$C$10+Settings!$C$11+IF(Settings!$C$15="Yes / Sí",Settings!$C$14,0))-IF(H19="",Settings!$C$9,H19)),0)-0.01,ROUNDUP(($I19+(Settings!$C$12+Settings!$C$13)-$G19*(1-(Settings!$C$10+Settings!$C$11+IF(Settings!$C$15="Yes / Sí",Settings!$C$14,0))))/(1-(Settings!$C$10+Settings!$C$11+IF(Settings!$C$15="Yes / Sí",Settings!$C$14,0))-IF(H19="",Settings!$C$9,H19)),0)+0.99),ROUNDUP(($I19+(Settings!$C$12+Settings!$C$13)-$G19*(1-(Settings!$C$10+Settings!$C$11+IF(Settings!$C$15="Yes / Sí",Settings!$C$14,0))))/(1-(Settings!$C$10+Settings!$C$11+IF(Settings!$C$15="Yes / Sí",Settings!$C$14,0))-IF(H19="",Settings!$C$9,H19)),2))))) -> 44.99 | L19: =IF(OR(B19="",K19=0),"",(K19+$G19-((K19+$G19)*(Settings!$C$10+Settings!$C$11+IF(Settings!$C$15="Yes / Sí",Settings!$C$14,0))+(Settings!$C$12+Settings!$C$13))-$I19)) -> 13.66595 | M19: 42 | N19: =IF(OR(B19="",M19=""),"",((M19+$G19)*(Settings!$C$10+Settings!$C$11+IF(Settings!$C$15="Yes / Sí",Settings!$C$14,0))+(Settings!$C$12+Settings!$C$13))) -> 4.44 | O19: =IF(OR(B19="",M19=""),"",(M19+$G19-((M19+$G19)*(Settings!$C$10+Settings!$C$11+IF(Settings!$C$15="Yes / Sí",Settings!$C$14,0))+(Settings!$C$12+Settings!$C$13))-$I19)) -> 10.96 | P19: =IF(O19="","",IF(M19=0,0,O19/M19)) -> 0.26095238 | Q19: =IF(OR(O19="",D19="",D19=0),"",(O19+D19/60*Settings!$C$7)/(D19/60)) -> 34.613333 | R19: =IF(B19="","",IF(M19="","Enter your price / Escribe tu precio",IF(O19<0,"⚠ LOSING MONEY / PIERDES",IF(P19<IF(H19="",Settings!$C$9,H19),"● BELOW TARGET / DEBAJO","✔ ON TARGET / EN OBJETIVO")))) -> ● BELOW TARGET / DEBAJO | T19: =IF(B19="",0,IF(M19="",0,1)) -> 1 | U19: =IF(T19=1,P19,0) -> 0.26095238 | V19: =IF(T19=1,IF(O19<0,0,IF(P19<IF(H19="",Settings!$C$9,H19),1,0)),0) -> 1 | W19: =IF(T19=1,IF(O19<0,1,0),0) -> 0 | X19: =IF(T19=1,M19,0) -> 42 | Y19: =IF(T19=1,O19,0) -> 10.96 | Z19: =IF(B19="",0,1) -> 1
I20: =IF(B20="","",C20+IF(D20="",0,D20/60*Settings!$C$7)+E20+F20+Settings!$C$8) | J20: =IF(B20="","",MAX(0,($I20+(Settings!$C$12+Settings!$C$13)-$G20*(1-(Settings!$C$10+Settings!$C$11+IF(Settings!$C$15="Yes / Sí",Settings!$C$14,0))))/(1-(Settings!$C$10+Settings!$C$11+IF(Settings!$C$15="Yes / Sí",Settings!$C$14,0))))) | K20: =IF(B20="","",IF(1-(Settings!$C$10+Settings!$C$11+IF(Settings!$C$15="Yes / Sí",Settings!$C$14,0))-IF(H20="",Settings!$C$9,H20)<=0,0,MAX(0,IF(Settings!$C$16="Yes / Sí",IF(ROUNDUP(($I20+(Settings!$C$12+Settings!$C$13)-$G20*(1-(Settings!$C$10+Settings!$C$11+IF(Settings!$C$15="Yes / Sí",Settings!$C$14,0))))/(1-(Settings!$C$10+Settings!$C$11+IF(Settings!$C$15="Yes / Sí",Settings!$C$14,0))-IF(H20="",Settings!$C$9,H20)),0)-0.01>=($I20+(Settings!$C$12+Settings!$C$13)-$G20*(1-(Settings!$C$10+Settings!$C$11+IF(Settings!$C$15="Yes / Sí",Settings!$C$14,0))))/(1-(Settings!$C$10+Settings!$C$11+IF(Settings!$C$15="Yes / Sí",Settings!$C$14,0))-IF(H20="",Settings!$C$9,H20)),ROUNDUP(($I20+(Settings!$C$12+Settings!$C$13)-$G20*(1-(Settings!$C$10+Settings!$C$11+IF(Settings!$C$15="Yes / Sí",Settings!$C$14,0))))/(1-(Settings!$C$10+Settings!$C$11+IF(Settings!$C$15="Yes / Sí",Settings!$C$14,0))-IF(H20="",Settings!$C$9,H20)),0)-0.01,ROUNDUP(($I20+(Settings!$C$12+Settings!$C$13)-$G20*(1-(Settings!$C$10+Settings!$C$11+IF(Settings!$C$15="Yes / Sí",Settings!$C$14,0))))/(1-(Settings!$C$10+Settings!$C$11+IF(Settings!$C$15="Yes / Sí",Settings!$C$14,0))-IF(H20="",Settings!$C$9,H20)),0)+0.99),ROUNDUP(($I20+(Settings!$C$12+Settings!$C$13)-$G20*(1-(Settings!$C$10+Settings!$C$11+IF(Settings!$C$15="Yes / Sí",Settings!$C$14,0))))/(1-(Settings!$C$10+Settings!$C$11+IF(Settings!$C$15="Yes / Sí",Settings!$C$14,0))-IF(H20="",Settings!$C$9,H20)),2))))) | L20: =IF(OR(B20="",K20=0),"",(K20+$G20-((K20+$G20)*(Settings!$C$10+Settings!$C$11+IF(Settings!$C$15="Yes / Sí",Settings!$C$14,0))+(Settings!$C$12+Settings!$C$13))-$I20)) | N20: =IF(OR(B20="",M20=""),"",((M20+$G20)*(Settings!$C$10+Settings!$C$11+IF(Settings!$C$15="Yes / Sí",Settings!$C$14,0))+(Settings!$C$12+Settings!$C$13))) | O20: =IF(OR(B20="",M20=""),"",(M20+$G20-((M20+$G20)*(Settings!$C$10+Settings!$C$11+IF(Settings!$C$15="Yes / Sí",Settings!$C$14,0))+(Settings!$C$12+Settings!$C$13))-$I20)) | P20: =IF(O20="","",IF(M20=0,0,O20/M20)) | Q20: =IF(OR(O20="",D20="",D20=0),"",(O20+D20/60*Settings!$C$7)/(D20/60)) | R20: =IF(B20="","",IF(M20="","Enter your price / Escribe tu precio",IF(O20<0,"⚠ LOSING MONEY / PIERDES",IF(P20<IF(H20="",Settings!$C$9,H20),"● BELOW TARGET / DEBAJO","✔ ON TARGET / EN OBJETIVO")))) | T20: =IF(B20="",0,IF(M20="",0,1)) -> 0 | U20: =IF(T20=1,P20,0) -> 0 | V20: =IF(T20=1,IF(O20<0,0,IF(P20<IF(H20="",Settings!$C$9,H20),1,0)),0) -> 0 | W20: =IF(T20=1,IF(O20<0,1,0),0) -> 0 | X20: =IF(T20=1,M20,0) -> 0 | Y20: =IF(T20=1,O20,0) -> 0 | Z20: =IF(B20="",0,1) -> 0
I21: =IF(B21="","",C21+IF(D21="",0,D21/60*Settings!$C$7)+E21+F21+Settings!$C$8) | J21: =IF(B21="","",MAX(0,($I21+(Settings!$C$12+Settings!$C$13)-$G21*(1-(Settings!$C$10+Settings!$C$11+IF(Settings!$C$15="Yes / Sí",Settings!$C$14,0))))/(1-(Settings!$C$10+Settings!$C$11+IF(Settings!$C$15="Yes / Sí",Settings!$C$14,0))))) | K21: =IF(B21="","",IF(1-(Settings!$C$10+Settings!$C$11+IF(Settings!$C$15="Yes / Sí",Settings!$C$14,0))-IF(H21="",Settings!$C$9,H21)<=0,0,MAX(0,IF(Settings!$C$16="Yes / Sí",IF(ROUNDUP(($I21+(Settings!$C$12+Settings!$C$13)-$G21*(1-(Settings!$C$10+Settings!$C$11+IF(Settings!$C$15="Yes / Sí",Settings!$C$14,0))))/(1-(Settings!$C$10+Settings!$C$11+IF(Settings!$C$15="Yes / Sí",Settings!$C$14,0))-IF(H21="",Settings!$C$9,H21)),0)-0.01>=($I21+(Settings!$C$12+Settings!$C$13)-$G21*(1-(Settings!$C$10+Settings!$C$11+IF(Settings!$C$15="Yes / Sí",Settings!$C$14,0))))/(1-(Settings!$C$10+Settings!$C$11+IF(Settings!$C$15="Yes / Sí",Settings!$C$14,0))-IF(H21="",Settings!$C$9,H21)),ROUNDUP(($I21+(Settings!$C$12+Settings!$C$13)-$G21*(1-(Settings!$C$10+Settings!$C$11+IF(Settings!$C$15="Yes / Sí",Settings!$C$14,0))))/(1-(Settings!$C$10+Settings!$C$11+IF(Settings!$C$15="Yes / Sí",Settings!$C$14,0))-IF(H21="",Settings!$C$9,H21)),0)-0.01,ROUNDUP(($I21+(Settings!$C$12+Settings!$C$13)-$G21*(1-(Settings!$C$10+Settings!$C$11+IF(Settings!$C$15="Yes / Sí",Settings!$C$14,0))))/(1-(Settings!$C$10+Settings!$C$11+IF(Settings!$C$15="Yes / Sí",Settings!$C$14,0))-IF(H21="",Settings!$C$9,H21)),0)+0.99),ROUNDUP(($I21+(Settings!$C$12+Settings!$C$13)-$G21*(1-(Settings!$C$10+Settings!$C$11+IF(Settings!$C$15="Yes / Sí",Settings!$C$14,0))))/(1-(Settings!$C$10+Settings!$C$11+IF(Settings!$C$15="Yes / Sí",Settings!$C$14,0))-IF(H21="",Settings!$C$9,H21)),2))))) | L21: =IF(OR(B21="",K21=0),"",(K21+$G21-((K21+$G21)*(Settings!$C$10+Settings!$C$11+IF(Settings!$C$15="Yes / Sí",Settings!$C$14,0))+(Settings!$C$12+Settings!$C$13))-$I21)) | N21: =IF(OR(B21="",M21=""),"",((M21+$G21)*(Settings!$C$10+Settings!$C$11+IF(Settings!$C$15="Yes / Sí",Settings!$C$14,0))+(Settings!$C$12+Settings!$C$13))) | O21: =IF(OR(B21="",M21=""),"",(M21+$G21-((M21+$G21)*(Settings!$C$10+Settings!$C$11+IF(Settings!$C$15="Yes / Sí",Settings!$C$14,0))+(Settings!$C$12+Settings!$C$13))-$I21)) | P21: =IF(O21="","",IF(M21=0,0,O21/M21)) | Q21: =IF(OR(O21="",D21="",D21=0),"",(O21+D21/60*Settings!$C$7)/(D21/60)) | R21: =IF(B21="","",IF(M21="","Enter your price / Escribe tu precio",IF(O21<0,"⚠ LOSING MONEY / PIERDES",IF(P21<IF(H21="",Settings!$C$9,H21),"● BELOW TARGET / DEBAJO","✔ ON TARGET / EN OBJETIVO")))) | T21: =IF(B21="",0,IF(M21="",0,1)) -> 0 | U21: =IF(T21=1,P21,0) -> 0 | V21: =IF(T21=1,IF(O21<0,0,IF(P21<IF(H21="",Settings!$C$9,H21),1,0)),0) -> 0 | W21: =IF(T21=1,IF(O21<0,1,0),0) -> 0 | X21: =IF(T21=1,M21,0) -> 0 | Y21: =IF(T21=1,O21,0) -> 0 | Z21: =IF(B21="",0,1) -> 0
I22: =IF(B22="","",C22+IF(D22="",0,D22/60*Settings!$C$7)+E22+F22+Settings!$C$8) | J22: =IF(B22="","",MAX(0,($I22+(Settings!$C$12+Settings!$C$13)-$G22*(1-(Settings!$C$10+Settings!$C$11+IF(Settings!$C$15="Yes / Sí",Settings!$C$14,0))))/(1-(Settings!$C$10+Settings!$C$11+IF(Settings!$C$15="Yes / Sí",Settings!$C$14,0))))) | K22: =IF(B22="","",IF(1-(Settings!$C$10+Settings!$C$11+IF(Settings!$C$15="Yes / Sí",Settings!$C$14,0))-IF(H22="",Settings!$C$9,H22)<=0,0,MAX(0,IF(Settings!$C$16="Yes / Sí",IF(ROUNDUP(($I22+(Settings!$C$12+Settings!$C$13)-$G22*(1-(Settings!$C$10+Settings!$C$11+IF(Settings!$C$15="Yes / Sí",Settings!$C$14,0))))/(1-(Settings!$C$10+Settings!$C$11+IF(Settings!$C$15="Yes / Sí",Settings!$C$14,0))-IF(H22="",Settings!$C$9,H22)),0)-0.01>=($I22+(Settings!$C$12+Settings!$C$13)-$G22*(1-(Settings!$C$10+Settings!$C$11+IF(Settings!$C$15="Yes / Sí",Settings!$C$14,0))))/(1-(Settings!$C$10+Settings!$C$11+IF(Settings!$C$15="Yes / Sí",Settings!$C$14,0))-IF(H22="",Settings!$C$9,H22)),ROUNDUP(($I22+(Settings!$C$12+Settings!$C$13)-$G22*(1-(Settings!$C$10+Settings!$C$11+IF(Settings!$C$15="Yes / Sí",Settings!$C$14,0))))/(1-(Settings!$C$10+Settings!$C$11+IF(Settings!$C$15="Yes / Sí",Settings!$C$14,0))-IF(H22="",Settings!$C$9,H22)),0)-0.01,ROUNDUP(($I22+(Settings!$C$12+Settings!$C$13)-$G22*(1-(Settings!$C$10+Settings!$C$11+IF(Settings!$C$15="Yes / Sí",Settings!$C$14,0))))/(1-(Settings!$C$10+Settings!$C$11+IF(Settings!$C$15="Yes / Sí",Settings!$C$14,0))-IF(H22="",Settings!$C$9,H22)),0)+0.99),ROUNDUP(($I22+(Settings!$C$12+Settings!$C$13)-$G22*(1-(Settings!$C$10+Settings!$C$11+IF(Settings!$C$15="Yes / Sí",Settings!$C$14,0))))/(1-(Settings!$C$10+Settings!$C$11+IF(Settings!$C$15="Yes / Sí",Settings!$C$14,0))-IF(H22="",Settings!$C$9,H22)),2))))) | L22: =IF(OR(B22="",K22=0),"",(K22+$G22-((K22+$G22)*(Settings!$C$10+Settings!$C$11+IF(Settings!$C$15="Yes / Sí",Settings!$C$14,0))+(Settings!$C$12+Settings!$C$13))-$I22)) | N22: =IF(OR(B22="",M22=""),"",((M22+$G22)*(Settings!$C$10+Settings!$C$11+IF(Settings!$C$15="Yes / Sí",Settings!$C$14,0))+(Settings!$C$12+Settings!$C$13))) | O22: =IF(OR(B22="",M22=""),"",(M22+$G22-((M22+$G22)*(Settings!$C$10+Settings!$C$11+IF(Settings!$C$15="Yes / Sí",Settings!$C$14,0))+(Settings!$C$12+Settings!$C$13))-$I22)) | P22: =IF(O22="","",IF(M22=0,0,O22/M22)) | Q22: =IF(OR(O22="",D22="",D22=0),"",(O22+D22/60*Settings!$C$7)/(D22/60)) | R22: =IF(B22="","",IF(M22="","Enter your price / Escribe tu precio",IF(O22<0,"⚠ LOSING MONEY / PIERDES",IF(P22<IF(H22="",Settings!$C$9,H22),"● BELOW TARGET / DEBAJO","✔ ON TARGET / EN OBJETIVO")))) | T22: =IF(B22="",0,IF(M22="",0,1)) -> 0 | U22: =IF(T22=1,P22,0) -> 0 | V22: =IF(T22=1,IF(O22<0,0,IF(P22<IF(H22="",Settings!$C$9,H22),1,0)),0) -> 0 | W22: =IF(T22=1,IF(O22<0,1,0),0) -> 0 | X22: =IF(T22=1,M22,0) -> 0 | Y22: =IF(T22=1,O22,0) -> 0 | Z22: =IF(B22="",0,1) -> 0
I23: =IF(B23="","",C23+IF(D23="",0,D23/60*Settings!$C$7)+E23+F23+Settings!$C$8) | J23: =IF(B23="","",MAX(0,($I23+(Settings!$C$12+Settings!$C$13)-$G23*(1-(Settings!$C$10+Settings!$C$11+IF(Settings!$C$15="Yes / Sí",Settings!$C$14,0))))/(1-(Settings!$C$10+Settings!$C$11+IF(Settings!$C$15="Yes / Sí",Settings!$C$14,0))))) | K23: =IF(B23="","",IF(1-(Settings!$C$10+Settings!$C$11+IF(Settings!$C$15="Yes / Sí",Settings!$C$14,0))-IF(H23="",Settings!$C$9,H23)<=0,0,MAX(0,IF(Settings!$C$16="Yes / Sí",IF(ROUNDUP(($I23+(Settings!$C$12+Settings!$C$13)-$G23*(1-(Settings!$C$10+Settings!$C$11+IF(Settings!$C$15="Yes / Sí",Settings!$C$14,0))))/(1-(Settings!$C$10+Settings!$C$11+IF(Settings!$C$15="Yes / Sí",Settings!$C$14,0))-IF(H23="",Settings!$C$9,H23)),0)-0.01>=($I23+(Settings!$C$12+Settings!$C$13)-$G23*(1-(Settings!$C$10+Settings!$C$11+IF(Settings!$C$15="Yes / Sí",Settings!$C$14,0))))/(1-(Settings!$C$10+Settings!$C$11+IF(Settings!$C$15="Yes / Sí",Settings!$C$14,0))-IF(H23="",Settings!$C$9,H23)),ROUNDUP(($I23+(Settings!$C$12+Settings!$C$13)-$G23*(1-(Settings!$C$10+Settings!$C$11+IF(Settings!$C$15="Yes / Sí",Settings!$C$14,0))))/(1-(Settings!$C$10+Settings!$C$11+IF(Settings!$C$15="Yes / Sí",Settings!$C$14,0))-IF(H23="",Settings!$C$9,H23)),0)-0.01,ROUNDUP(($I23+(Settings!$C$12+Settings!$C$13)-$G23*(1-(Settings!$C$10+Settings!$C$11+IF(Settings!$C$15="Yes / Sí",Settings!$C$14,0))))/(1-(Settings!$C$10+Settings!$C$11+IF(Settings!$C$15="Yes / Sí",Settings!$C$14,0))-IF(H23="",Settings!$C$9,H23)),0)+0.99),ROUNDUP(($I23+(Settings!$C$12+Settings!$C$13)-$G23*(1-(Settings!$C$10+Settings!$C$11+IF(Settings!$C$15="Yes / Sí",Settings!$C$14,0))))/(1-(Settings!$C$10+Settings!$C$11+IF(Settings!$C$15="Yes / Sí",Settings!$C$14,0))-IF(H23="",Settings!$C$9,H23)),2))))) | L23: =IF(OR(B23="",K23=0),"",(K23+$G23-((K23+$G23)*(Settings!$C$10+Settings!$C$11+IF(Settings!$C$15="Yes / Sí",Settings!$C$14,0))+(Settings!$C$12+Settings!$C$13))-$I23)) | N23: =IF(OR(B23="",M23=""),"",((M23+$G23)*(Settings!$C$10+Settings!$C$11+IF(Settings!$C$15="Yes / Sí",Settings!$C$14,0))+(Settings!$C$12+Settings!$C$13))) | O23: =IF(OR(B23="",M23=""),"",(M23+$G23-((M23+$G23)*(Settings!$C$10+Settings!$C$11+IF(Settings!$C$15="Yes / Sí",Settings!$C$14,0))+(Settings!$C$12+Settings!$C$13))-$I23)) | P23: =IF(O23="","",IF(M23=0,0,O23/M23)) | Q23: =IF(OR(O23="",D23="",D23=0),"",(O23+D23/60*Settings!$C$7)/(D23/60)) | R23: =IF(B23="","",IF(M23="","Enter your price / Escribe tu precio",IF(O23<0,"⚠ LOSING MONEY / PIERDES",IF(P23<IF(H23="",Settings!$C$9,H23),"● BELOW TARGET / DEBAJO","✔ ON TARGET / EN OBJETIVO")))) | T23: =IF(B23="",0,IF(M23="",0,1)) -> 0 | U23: =IF(T23=1,P23,0) -> 0 | V23: =IF(T23=1,IF(O23<0,0,IF(P23<IF(H23="",Settings!$C$9,H23),1,0)),0) -> 0 | W23: =IF(T23=1,IF(O23<0,1,0),0) -> 0 | X23: =IF(T23=1,M23,0) -> 0 | Y23: =IF(T23=1,O23,0) -> 0 | Z23: =IF(B23="",0,1) -> 0
I24: =IF(B24="","",C24+IF(D24="",0,D24/60*Settings!$C$7)+E24+F24+Settings!$C$8) | J24: =IF(B24="","",MAX(0,($I24+(Settings!$C$12+Settings!$C$13)-$G24*(1-(Settings!$C$10+Settings!$C$11+IF(Settings!$C$15="Yes / Sí",Settings!$C$14,0))))/(1-(Settings!$C$10+Settings!$C$11+IF(Settings!$C$15="Yes / Sí",Settings!$C$14,0))))) | K24: =IF(B24="","",IF(1-(Settings!$C$10+Settings!$C$11+IF(Settings!$C$15="Yes / Sí",Settings!$C$14,0))-IF(H24="",Settings!$C$9,H24)<=0,0,MAX(0,IF(Settings!$C$16="Yes / Sí",IF(ROUNDUP(($I24+(Settings!$C$12+Settings!$C$13)-$G24*(1-(Settings!$C$10+Settings!$C$11+IF(Settings!$C$15="Yes / Sí",Settings!$C$14,0))))/(1-(Settings!$C$10+Settings!$C$11+IF(Settings!$C$15="Yes / Sí",Settings!$C$14,0))-IF(H24="",Settings!$C$9,H24)),0)-0.01>=($I24+(Settings!$C$12+Settings!$C$13)-$G24*(1-(Settings!$C$10+Settings!$C$11+IF(Settings!$C$15="Yes / Sí",Settings!$C$14,0))))/(1-(Settings!$C$10+Settings!$C$11+IF(Settings!$C$15="Yes / Sí",Settings!$C$14,0))-IF(H24="",Settings!$C$9,H24)),ROUNDUP(($I24+(Settings!$C$12+Settings!$C$13)-$G24*(1-(Settings!$C$10+Settings!$C$11+IF(Settings!$C$15="Yes / Sí",Settings!$C$14,0))))/(1-(Settings!$C$10+Settings!$C$11+IF(Settings!$C$15="Yes / Sí",Settings!$C$14,0))-IF(H24="",Settings!$C$9,H24)),0)-0.01,ROUNDUP(($I24+(Settings!$C$12+Settings!$C$13)-$G24*(1-(Settings!$C$10+Settings!$C$11+IF(Settings!$C$15="Yes / Sí",Settings!$C$14,0))))/(1-(Settings!$C$10+Settings!$C$11+IF(Settings!$C$15="Yes / Sí",Settings!$C$14,0))-IF(H24="",Settings!$C$9,H24)),0)+0.99),ROUNDUP(($I24+(Settings!$C$12+Settings!$C$13)-$G24*(1-(Settings!$C$10+Settings!$C$11+IF(Settings!$C$15="Yes / Sí",Settings!$C$14,0))))/(1-(Settings!$C$10+Settings!$C$11+IF(Settings!$C$15="Yes / Sí",Settings!$C$14,0))-IF(H24="",Settings!$C$9,H24)),2))))) | L24: =IF(OR(B24="",K24=0),"",(K24+$G24-((K24+$G24)*(Settings!$C$10+Settings!$C$11+IF(Settings!$C$15="Yes / Sí",Settings!$C$14,0))+(Settings!$C$12+Settings!$C$13))-$I24)) | N24: =IF(OR(B24="",M24=""),"",((M24+$G24)*(Settings!$C$10+Settings!$C$11+IF(Settings!$C$15="Yes / Sí",Settings!$C$14,0))+(Settings!$C$12+Settings!$C$13))) | O24: =IF(OR(B24="",M24=""),"",(M24+$G24-((M24+$G24)*(Settings!$C$10+Settings!$C$11+IF(Settings!$C$15="Yes / Sí",Settings!$C$14,0))+(Settings!$C$12+Settings!$C$13))-$I24)) | P24: =IF(O24="","",IF(M24=0,0,O24/M24)) | Q24: =IF(OR(O24="",D24="",D24=0),"",(O24+D24/60*Settings!$C$7)/(D24/60)) | R24: =IF(B24="","",IF(M24="","Enter your price / Escribe tu precio",IF(O24<0,"⚠ LOSING MONEY / PIERDES",IF(P24<IF(H24="",Settings!$C$9,H24),"● BELOW TARGET / DEBAJO","✔ ON TARGET / EN OBJETIVO")))) | T24: =IF(B24="",0,IF(M24="",0,1)) -> 0 | U24: =IF(T24=1,P24,0) -> 0 | V24: =IF(T24=1,IF(O24<0,0,IF(P24<IF(H24="",Settings!$C$9,H24),1,0)),0) -> 0 | W24: =IF(T24=1,IF(O24<0,1,0),0) -> 0 | X24: =IF(T24=1,M24,0) -> 0 | Y24: =IF(T24=1,O24,0) -> 0 | Z24: =IF(B24="",0,1) -> 0
I25: =IF(B25="","",C25+IF(D25="",0,D25/60*Settings!$C$7)+E25+F25+Settings!$C$8) | J25: =IF(B25="","",MAX(0,($I25+(Settings!$C$12+Settings!$C$13)-$G25*(1-(Settings!$C$10+Settings!$C$11+IF(Settings!$C$15="Yes / Sí",Settings!$C$14,0))))/(1-(Settings!$C$10+Settings!$C$11+IF(Settings!$C$15="Yes / Sí",Settings!$C$14,0))))) | K25: =IF(B25="","",IF(1-(Settings!$C$10+Settings!$C$11+IF(Settings!$C$15="Yes / Sí",Settings!$C$14,0))-IF(H25="",Settings!$C$9,H25)<=0,0,MAX(0,IF(Settings!$C$16="Yes / Sí",IF(ROUNDUP(($I25+(Settings!$C$12+Settings!$C$13)-$G25*(1-(Settings!$C$10+Settings!$C$11+IF(Settings!$C$15="Yes / Sí",Settings!$C$14,0))))/(1-(Settings!$C$10+Settings!$C$11+IF(Settings!$C$15="Yes / Sí",Settings!$C$14,0))-IF(H25="",Settings!$C$9,H25)),0)-0.01>=($I25+(Settings!$C$12+Settings!$C$13)-$G25*(1-(Settings!$C$10+Settings!$C$11+IF(Settings!$C$15="Yes / Sí",Settings!$C$14,0))))/(1-(Settings!$C$10+Settings!$C$11+IF(Settings!$C$15="Yes / Sí",Settings!$C$14,0))-IF(H25="",Settings!$C$9,H25)),ROUNDUP(($I25+(Settings!$C$12+Settings!$C$13)-$G25*(1-(Settings!$C$10+Settings!$C$11+IF(Settings!$C$15="Yes / Sí",Settings!$C$14,0))))/(1-(Settings!$C$10+Settings!$C$11+IF(Settings!$C$15="Yes / Sí",Settings!$C$14,0))-IF(H25="",Settings!$C$9,H25)),0)-0.01,ROUNDUP(($I25+(Settings!$C$12+Settings!$C$13)-$G25*(1-(Settings!$C$10+Settings!$C$11+IF(Settings!$C$15="Yes / Sí",Settings!$C$14,0))))/(1-(Settings!$C$10+Settings!$C$11+IF(Settings!$C$15="Yes / Sí",Settings!$C$14,0))-IF(H25="",Settings!$C$9,H25)),0)+0.99),ROUNDUP(($I25+(Settings!$C$12+Settings!$C$13)-$G25*(1-(Settings!$C$10+Settings!$C$11+IF(Settings!$C$15="Yes / Sí",Settings!$C$14,0))))/(1-(Settings!$C$10+Settings!$C$11+IF(Settings!$C$15="Yes / Sí",Settings!$C$14,0))-IF(H25="",Settings!$C$9,H25)),2))))) | L25: =IF(OR(B25="",K25=0),"",(K25+$G25-((K25+$G25)*(Settings!$C$10+Settings!$C$11+IF(Settings!$C$15="Yes / Sí",Settings!$C$14,0))+(Settings!$C$12+Settings!$C$13))-$I25)) | N25: =IF(OR(B25="",M25=""),"",((M25+$G25)*(Settings!$C$10+Settings!$C$11+IF(Settings!$C$15="Yes / Sí",Settings!$C$14,0))+(Settings!$C$12+Settings!$C$13))) | O25: =IF(OR(B25="",M25=""),"",(M25+$G25-((M25+$G25)*(Settings!$C$10+Settings!$C$11+IF(Settings!$C$15="Yes / Sí",Settings!$C$14,0))+(Settings!$C$12+Settings!$C$13))-$I25)) | P25: =IF(O25="","",IF(M25=0,0,O25/M25)) | Q25: =IF(OR(O25="",D25="",D25=0),"",(O25+D25/60*Settings!$C$7)/(D25/60)) | R25: =IF(B25="","",IF(M25="","Enter your price / Escribe tu precio",IF(O25<0,"⚠ LOSING MONEY / PIERDES",IF(P25<IF(H25="",Settings!$C$9,H25),"● BELOW TARGET / DEBAJO","✔ ON TARGET / EN OBJETIVO")))) | T25: =IF(B25="",0,IF(M25="",0,1)) -> 0 | U25: =IF(T25=1,P25,0) -> 0 | V25: =IF(T25=1,IF(O25<0,0,IF(P25<IF(H25="",Settings!$C$9,H25),1,0)),0) -> 0 | W25: =IF(T25=1,IF(O25<0,1,0),0) -> 0 | X25: =IF(T25=1,M25,0) -> 0 | Y25: =IF(T25=1,O25,0) -> 0 | Z25: =IF(B25="",0,1) -> 0
I26: =IF(B26="","",C26+IF(D26="",0,D26/60*Settings!$C$7)+E26+F26+Settings!$C$8) | J26: =IF(B26="","",MAX(0,($I26+(Settings!$C$12+Settings!$C$13)-$G26*(1-(Settings!$C$10+Settings!$C$11+IF(Settings!$C$15="Yes / Sí",Settings!$C$14,0))))/(1-(Settings!$C$10+Settings!$C$11+IF(Settings!$C$15="Yes / Sí",Settings!$C$14,0))))) | K26: =IF(B26="","",IF(1-(Settings!$C$10+Settings!$C$11+IF(Settings!$C$15="Yes / Sí",Settings!$C$14,0))-IF(H26="",Settings!$C$9,H26)<=0,0,MAX(0,IF(Settings!$C$16="Yes / Sí",IF(ROUNDUP(($I26+(Settings!$C$12+Settings!$C$13)-$G26*(1-(Settings!$C$10+Settings!$C$11+IF(Settings!$C$15="Yes / Sí",Settings!$C$14,0))))/(1-(Settings!$C$10+Settings!$C$11+IF(Settings!$C$15="Yes / Sí",Settings!$C$14,0))-IF(H26="",Settings!$C$9,H26)),0)-0.01>=($I26+(Settings!$C$12+Settings!$C$13)-$G26*(1-(Settings!$C$10+Settings!$C$11+IF(Settings!$C$15="Yes / Sí",Settings!$C$14,0))))/(1-(Settings!$C$10+Settings!$C$11+IF(Settings!$C$15="Yes / Sí",Settings!$C$14,0))-IF(H26="",Settings!$C$9,H26)),ROUNDUP(($I26+(Settings!$C$12+Settings!$C$13)-$G26*(1-(Settings!$C$10+Settings!$C$11+IF(Settings!$C$15="Yes / Sí",Settings!$C$14,0))))/(1-(Settings!$C$10+Settings!$C$11+IF(Settings!$C$15="Yes / Sí",Settings!$C$14,0))-IF(H26="",Settings!$C$9,H26)),0)-0.01,ROUNDUP(($I26+(Settings!$C$12+Settings!$C$13)-$G26*(1-(Settings!$C$10+Settings!$C$11+IF(Settings!$C$15="Yes / Sí",Settings!$C$14,0))))/(1-(Settings!$C$10+Settings!$C$11+IF(Settings!$C$15="Yes / Sí",Settings!$C$14,0))-IF(H26="",Settings!$C$9,H26)),0)+0.99),ROUNDUP(($I26+(Settings!$C$12+Settings!$C$13)-$G26*(1-(Settings!$C$10+Settings!$C$11+IF(Settings!$C$15="Yes / Sí",Settings!$C$14,0))))/(1-(Settings!$C$10+Settings!$C$11+IF(Settings!$C$15="Yes / Sí",Settings!$C$14,0))-IF(H26="",Settings!$C$9,H26)),2))))) | L26: =IF(OR(B26="",K26=0),"",(K26+$G26-((K26+$G26)*(Settings!$C$10+Settings!$C$11+IF(Settings!$C$15="Yes / Sí",Settings!$C$14,0))+(Settings!$C$12+Settings!$C$13))-$I26)) | N26: =IF(OR(B26="",M26=""),"",((M26+$G26)*(Settings!$C$10+Settings!$C$11+IF(Settings!$C$15="Yes / Sí",Settings!$C$14,0))+(Settings!$C$12+Settings!$C$13))) | O26: =IF(OR(B26="",M26=""),"",(M26+$G26-((M26+$G26)*(Settings!$C$10+Settings!$C$11+IF(Settings!$C$15="Yes / Sí",Settings!$C$14,0))+(Settings!$C$12+Settings!$C$13))-$I26)) | P26: =IF(O26="","",IF(M26=0,0,O26/M26)) | Q26: =IF(OR(O26="",D26="",D26=0),"",(O26+D26/60*Settings!$C$7)/(D26/60)) | R26: =IF(B26="","",IF(M26="","Enter your price / Escribe tu precio",IF(O26<0,"⚠ LOSING MONEY / PIERDES",IF(P26<IF(H26="",Settings!$C$9,H26),"● BELOW TARGET / DEBAJO","✔ ON TARGET / EN OBJETIVO")))) | T26: =IF(B26="",0,IF(M26="",0,1)) -> 0 | U26: =IF(T26=1,P26,0) -> 0 | V26: =IF(T26=1,IF(O26<0,0,IF(P26<IF(H26="",Settings!$C$9,H26),1,0)),0) -> 0 | W26: =IF(T26=1,IF(O26<0,1,0),0) -> 0 | X26: =IF(T26=1,M26,0) -> 0 | Y26: =IF(T26=1,O26,0) -> 0 | Z26: =IF(B26="",0,1) -> 0
I27: =IF(B27="","",C27+IF(D27="",0,D27/60*Settings!$C$7)+E27+F27+Settings!$C$8) | J27: =IF(B27="","",MAX(0,($I27+(Settings!$C$12+Settings!$C$13)-$G27*(1-(Settings!$C$10+Settings!$C$11+IF(Settings!$C$15="Yes / Sí",Settings!$C$14,0))))/(1-(Settings!$C$10+Settings!$C$11+IF(Settings!$C$15="Yes / Sí",Settings!$C$14,0))))) | K27: =IF(B27="","",IF(1-(Settings!$C$10+Settings!$C$11+IF(Settings!$C$15="Yes / Sí",Settings!$C$14,0))-IF(H27="",Settings!$C$9,H27)<=0,0,MAX(0,IF(Settings!$C$16="Yes / Sí",IF(ROUNDUP(($I27+(Settings!$C$12+Settings!$C$13)-$G27*(1-(Settings!$C$10+Settings!$C$11+IF(Settings!$C$15="Yes / Sí",Settings!$C$14,0))))/(1-(Settings!$C$10+Settings!$C$11+IF(Settings!$C$15="Yes / Sí",Settings!$C$14,0))-IF(H27="",Settings!$C$9,H27)),0)-0.01>=($I27+(Settings!$C$12+Settings!$C$13)-$G27*(1-(Settings!$C$10+Settings!$C$11+IF(Settings!$C$15="Yes / Sí",Settings!$C$14,0))))/(1-(Settings!$C$10+Settings!$C$11+IF(Settings!$C$15="Yes / Sí",Settings!$C$14,0))-IF(H27="",Settings!$C$9,H27)),ROUNDUP(($I27+(Settings!$C$12+Settings!$C$13)-$G27*(1-(Settings!$C$10+Settings!$C$11+IF(Settings!$C$15="Yes / Sí",Settings!$C$14,0))))/(1-(Settings!$C$10+Settings!$C$11+IF(Settings!$C$15="Yes / Sí",Settings!$C$14,0))-IF(H27="",Settings!$C$9,H27)),0)-0.01,ROUNDUP(($I27+(Settings!$C$12+Settings!$C$13)-$G27*(1-(Settings!$C$10+Settings!$C$11+IF(Settings!$C$15="Yes / Sí",Settings!$C$14,0))))/(1-(Settings!$C$10+Settings!$C$11+IF(Settings!$C$15="Yes / Sí",Settings!$C$14,0))-IF(H27="",Settings!$C$9,H27)),0)+0.99),ROUNDUP(($I27+(Settings!$C$12+Settings!$C$13)-$G27*(1-(Settings!$C$10+Settings!$C$11+IF(Settings!$C$15="Yes / Sí",Settings!$C$14,0))))/(1-(Settings!$C$10+Settings!$C$11+IF(Settings!$C$15="Yes / Sí",Settings!$C$14,0))-IF(H27="",Settings!$C$9,H27)),2))))) | L27: =IF(OR(B27="",K27=0),"",(K27+$G27-((K27+$G27)*(Settings!$C$10+Settings!$C$11+IF(Settings!$C$15="Yes / Sí",Settings!$C$14,0))+(Settings!$C$12+Settings!$C$13))-$I27)) | N27: =IF(OR(B27="",M27=""),"",((M27+$G27)*(Settings!$C$10+Settings!$C$11+IF(Settings!$C$15="Yes / Sí",Settings!$C$14,0))+(Settings!$C$12+Settings!$C$13))) | O27: =IF(OR(B27="",M27=""),"",(M27+$G27-((M27+$G27)*(Settings!$C$10+Settings!$C$11+IF(Settings!$C$15="Yes / Sí",Settings!$C$14,0))+(Settings!$C$12+Settings!$C$13))-$I27)) | P27: =IF(O27="","",IF(M27=0,0,O27/M27)) | Q27: =IF(OR(O27="",D27="",D27=0),"",(O27+D27/60*Settings!$C$7)/(D27/60)) | R27: =IF(B27="","",IF(M27="","Enter your price / Escribe tu precio",IF(O27<0,"⚠ LOSING MONEY / PIERDES",IF(P27<IF(H27="",Settings!$C$9,H27),"● BELOW TARGET / DEBAJO","✔ ON TARGET / EN OBJETIVO")))) | T27: =IF(B27="",0,IF(M27="",0,1)) -> 0 | U27: =IF(T27=1,P27,0) -> 0 | V27: =IF(T27=1,IF(O27<0,0,IF(P27<IF(H27="",Settings!$C$9,H27),1,0)),0) -> 0 | W27: =IF(T27=1,IF(O27<0,1,0),0) -> 0 | X27: =IF(T27=1,M27,0) -> 0 | Y27: =IF(T27=1,O27,0) -> 0 | Z27: =IF(B27="",0,1) -> 0
I28: =IF(B28="","",C28+IF(D28="",0,D28/60*Settings!$C$7)+E28+F28+Settings!$C$8) | J28: =IF(B28="","",MAX(0,($I28+(Settings!$C$12+Settings!$C$13)-$G28*(1-(Settings!$C$10+Settings!$C$11+IF(Settings!$C$15="Yes / Sí",Settings!$C$14,0))))/(1-(Settings!$C$10+Settings!$C$11+IF(Settings!$C$15="Yes / Sí",Settings!$C$14,0))))) | K28: =IF(B28="","",IF(1-(Settings!$C$10+Settings!$C$11+IF(Settings!$C$15="Yes / Sí",Settings!$C$14,0))-IF(H28="",Settings!$C$9,H28)<=0,0,MAX(0,IF(Settings!$C$16="Yes / Sí",IF(ROUNDUP(($I28+(Settings!$C$12+Settings!$C$13)-$G28*(1-(Settings!$C$10+Settings!$C$11+IF(Settings!$C$15="Yes / Sí",Settings!$C$14,0))))/(1-(Settings!$C$10+Settings!$C$11+IF(Settings!$C$15="Yes / Sí",Settings!$C$14,0))-IF(H28="",Settings!$C$9,H28)),0)-0.01>=($I28+(Settings!$C$12+Settings!$C$13)-$G28*(1-(Settings!$C$10+Settings!$C$11+IF(Settings!$C$15="Yes / Sí",Settings!$C$14,0))))/(1-(Settings!$C$10+Settings!$C$11+IF(Settings!$C$15="Yes / Sí",Settings!$C$14,0))-IF(H28="",Settings!$C$9,H28)),ROUNDUP(($I28+(Settings!$C$12+Settings!$C$13)-$G28*(1-(Settings!$C$10+Settings!$C$11+IF(Settings!$C$15="Yes / Sí",Settings!$C$14,0))))/(1-(Settings!$C$10+Settings!$C$11+IF(Settings!$C$15="Yes / Sí",Settings!$C$14,0))-IF(H28="",Settings!$C$9,H28)),0)-0.01,ROUNDUP(($I28+(Settings!$C$12+Settings!$C$13)-$G28*(1-(Settings!$C$10+Settings!$C$11+IF(Settings!$C$15="Yes / Sí",Settings!$C$14,0))))/(1-(Settings!$C$10+Settings!$C$11+IF(Settings!$C$15="Yes / Sí",Settings!$C$14,0))-IF(H28="",Settings!$C$9,H28)),0)+0.99),ROUNDUP(($I28+(Settings!$C$12+Settings!$C$13)-$G28*(1-(Settings!$C$10+Settings!$C$11+IF(Settings!$C$15="Yes / Sí",Settings!$C$14,0))))/(1-(Settings!$C$10+Settings!$C$11+IF(Settings!$C$15="Yes / Sí",Settings!$C$14,0))-IF(H28="",Settings!$C$9,H28)),2))))) | L28: =IF(OR(B28="",K28=0),"",(K28+$G28-((K28+$G28)*(Settings!$C$10+Settings!$C$11+IF(Settings!$C$15="Yes / Sí",Settings!$C$14,0))+(Settings!$C$12+Settings!$C$13))-$I28)) | N28: =IF(OR(B28="",M28=""),"",((M28+$G28)*(Settings!$C$10+Settings!$C$11+IF(Settings!$C$15="Yes / Sí",Settings!$C$14,0))+(Settings!$C$12+Settings!$C$13))) | O28: =IF(OR(B28="",M28=""),"",(M28+$G28-((M28+$G28)*(Settings!$C$10+Settings!$C$11+IF(Settings!$C$15="Yes / Sí",Settings!$C$14,0))+(Settings!$C$12+Settings!$C$13))-$I28)) | P28: =IF(O28="","",IF(M28=0,0,O28/M28)) | Q28: =IF(OR(O28="",D28="",D28=0),"",(O28+D28/60*Settings!$C$7)/(D28/60)) | R28: =IF(B28="","",IF(M28="","Enter your price / Escribe tu precio",IF(O28<0,"⚠ LOSING MONEY / PIERDES",IF(P28<IF(H28="",Settings!$C$9,H28),"● BELOW TARGET / DEBAJO","✔ ON TARGET / EN OBJETIVO")))) | T28: =IF(B28="",0,IF(M28="",0,1)) -> 0 | U28: =IF(T28=1,P28,0) -> 0 | V28: =IF(T28=1,IF(O28<0,0,IF(P28<IF(H28="",Settings!$C$9,H28),1,0)),0) -> 0 | W28: =IF(T28=1,IF(O28<0,1,0),0) -> 0 | X28: =IF(T28=1,M28,0) -> 0 | Y28: =IF(T28=1,O28,0) -> 0 | Z28: =IF(B28="",0,1) -> 0
I29: =IF(B29="","",C29+IF(D29="",0,D29/60*Settings!$C$7)+E29+F29+Settings!$C$8) | J29: =IF(B29="","",MAX(0,($I29+(Settings!$C$12+Settings!$C$13)-$G29*(1-(Settings!$C$10+Settings!$C$11+IF(Settings!$C$15="Yes / Sí",Settings!$C$14,0))))/(1-(Settings!$C$10+Settings!$C$11+IF(Settings!$C$15="Yes / Sí",Settings!$C$14,0))))) | K29: =IF(B29="","",IF(1-(Settings!$C$10+Settings!$C$11+IF(Settings!$C$15="Yes / Sí",Settings!$C$14,0))-IF(H29="",Settings!$C$9,H29)<=0,0,MAX(0,IF(Settings!$C$16="Yes / Sí",IF(ROUNDUP(($I29+(Settings!$C$12+Settings!$C$13)-$G29*(1-(Settings!$C$10+Settings!$C$11+IF(Settings!$C$15="Yes / Sí",Settings!$C$14,0))))/(1-(Settings!$C$10+Settings!$C$11+IF(Settings!$C$15="Yes / Sí",Settings!$C$14,0))-IF(H29="",Settings!$C$9,H29)),0)-0.01>=($I29+(Settings!$C$12+Settings!$C$13)-$G29*(1-(Settings!$C$10+Settings!$C$11+IF(Settings!$C$15="Yes / Sí",Settings!$C$14,0))))/(1-(Settings!$C$10+Settings!$C$11+IF(Settings!$C$15="Yes / Sí",Settings!$C$14,0))-IF(H29="",Settings!$C$9,H29)),ROUNDUP(($I29+(Settings!$C$12+Settings!$C$13)-$G29*(1-(Settings!$C$10+Settings!$C$11+IF(Settings!$C$15="Yes / Sí",Settings!$C$14,0))))/(1-(Settings!$C$10+Settings!$C$11+IF(Settings!$C$15="Yes / Sí",Settings!$C$14,0))-IF(H29="",Settings!$C$9,H29)),0)-0.01,ROUNDUP(($I29+(Settings!$C$12+Settings!$C$13)-$G29*(1-(Settings!$C$10+Settings!$C$11+IF(Settings!$C$15="Yes / Sí",Settings!$C$14,0))))/(1-(Settings!$C$10+Settings!$C$11+IF(Settings!$C$15="Yes / Sí",Settings!$C$14,0))-IF(H29="",Settings!$C$9,H29)),0)+0.99),ROUNDUP(($I29+(Settings!$C$12+Settings!$C$13)-$G29*(1-(Settings!$C$10+Settings!$C$11+IF(Settings!$C$15="Yes / Sí",Settings!$C$14,0))))/(1-(Settings!$C$10+Settings!$C$11+IF(Settings!$C$15="Yes / Sí",Settings!$C$14,0))-IF(H29="",Settings!$C$9,H29)),2))))) | L29: =IF(OR(B29="",K29=0),"",(K29+$G29-((K29+$G29)*(Settings!$C$10+Settings!$C$11+IF(Settings!$C$15="Yes / Sí",Settings!$C$14,0))+(Settings!$C$12+Settings!$C$13))-$I29)) | N29: =IF(OR(B29="",M29=""),"",((M29+$G29)*(Settings!$C$10+Settings!$C$11+IF(Settings!$C$15="Yes / Sí",Settings!$C$14,0))+(Settings!$C$12+Settings!$C$13))) | O29: =IF(OR(B29="",M29=""),"",(M29+$G29-((M29+$G29)*(Settings!$C$10+Settings!$C$11+IF(Settings!$C$15="Yes / Sí",Settings!$C$14,0))+(Settings!$C$12+Settings!$C$13))-$I29)) | P29: =IF(O29="","",IF(M29=0,0,O29/M29)) | Q29: =IF(OR(O29="",D29="",D29=0),"",(O29+D29/60*Settings!$C$7)/(D29/60)) | R29: =IF(B29="","",IF(M29="","Enter your price / Escribe tu precio",IF(O29<0,"⚠ LOSING MONEY / PIERDES",IF(P29<IF(H29="",Settings!$C$9,H29),"● BELOW TARGET / DEBAJO","✔ ON TARGET / EN OBJETIVO")))) | T29: =IF(B29="",0,IF(M29="",0,1)) -> 0 | U29: =IF(T29=1,P29,0) -> 0 | V29: =IF(T29=1,IF(O29<0,0,IF(P29<IF(H29="",Settings!$C$9,H29),1,0)),0) -> 0 | W29: =IF(T29=1,IF(O29<0,1,0),0) -> 0 | X29: =IF(T29=1,M29,0) -> 0 | Y29: =IF(T29=1,O29,0) -> 0 | Z29: =IF(B29="",0,1) -> 0
I30: =IF(B30="","",C30+IF(D30="",0,D30/60*Settings!$C$7)+E30+F30+Settings!$C$8) | J30: =IF(B30="","",MAX(0,($I30+(Settings!$C$12+Settings!$C$13)-$G30*(1-(Settings!$C$10+Settings!$C$11+IF(Settings!$C$15="Yes / Sí",Settings!$C$14,0))))/(1-(Settings!$C$10+Settings!$C$11+IF(Settings!$C$15="Yes / Sí",Settings!$C$14,0))))) | K30: =IF(B30="","",IF(1-(Settings!$C$10+Settings!$C$11+IF(Settings!$C$15="Yes / Sí",Settings!$C$14,0))-IF(H30="",Settings!$C$9,H30)<=0,0,MAX(0,IF(Settings!$C$16="Yes / Sí",IF(ROUNDUP(($I30+(Settings!$C$12+Settings!$C$13)-$G30*(1-(Settings!$C$10+Settings!$C$11+IF(Settings!$C$15="Yes / Sí",Settings!$C$14,0))))/(1-(Settings!$C$10+Settings!$C$11+IF(Settings!$C$15="Yes / Sí",Settings!$C$14,0))-IF(H30="",Settings!$C$9,H30)),0)-0.01>=($I30+(Settings!$C$12+Settings!$C$13)-$G30*(1-(Settings!$C$10+Settings!$C$11+IF(Settings!$C$15="Yes / Sí",Settings!$C$14,0))))/(1-(Settings!$C$10+Settings!$C$11+IF(Settings!$C$15="Yes / Sí",Settings!$C$14,0))-IF(H30="",Settings!$C$9,H30)),ROUNDUP(($I30+(Settings!$C$12+Settings!$C$13)-$G30*(1-(Settings!$C$10+Settings!$C$11+IF(Settings!$C$15="Yes / Sí",Settings!$C$14,0))))/(1-(Settings!$C$10+Settings!$C$11+IF(Settings!$C$15="Yes / Sí",Settings!$C$14,0))-IF(H30="",Settings!$C$9,H30)),0)-0.01,ROUNDUP(($I30+(Settings!$C$12+Settings!$C$13)-$G30*(1-(Settings!$C$10+Settings!$C$11+IF(Settings!$C$15="Yes / Sí",Settings!$C$14,0))))/(1-(Settings!$C$10+Settings!$C$11+IF(Settings!$C$15="Yes / Sí",Settings!$C$14,0))-IF(H30="",Settings!$C$9,H30)),0)+0.99),ROUNDUP(($I30+(Settings!$C$12+Settings!$C$13)-$G30*(1-(Settings!$C$10+Settings!$C$11+IF(Settings!$C$15="Yes / Sí",Settings!$C$14,0))))/(1-(Settings!$C$10+Settings!$C$11+IF(Settings!$C$15="Yes / Sí",Settings!$C$14,0))-IF(H30="",Settings!$C$9,H30)),2))))) | L30: =IF(OR(B30="",K30=0),"",(K30+$G30-((K30+$G30)*(Settings!$C$10+Settings!$C$11+IF(Settings!$C$15="Yes / Sí",Settings!$C$14,0))+(Settings!$C$12+Settings!$C$13))-$I30)) | N30: =IF(OR(B30="",M30=""),"",((M30+$G30)*(Settings!$C$10+Settings!$C$11+IF(Settings!$C$15="Yes / Sí",Settings!$C$14,0))+(Settings!$C$12+Settings!$C$13))) | O30: =IF(OR(B30="",M30=""),"",(M30+$G30-((M30+$G30)*(Settings!$C$10+Settings!$C$11+IF(Settings!$C$15="Yes / Sí",Settings!$C$14,0))+(Settings!$C$12+Settings!$C$13))-$I30)) | P30: =IF(O30="","",IF(M30=0,0,O30/M30)) | Q30: =IF(OR(O30="",D30="",D30=0),"",(O30+D30/60*Settings!$C$7)/(D30/60)) | R30: =IF(B30="","",IF(M30="","Enter your price / Escribe tu precio",IF(O30<0,"⚠ LOSING MONEY / PIERDES",IF(P30<IF(H30="",Settings!$C$9,H30),"● BELOW TARGET / DEBAJO","✔ ON TARGET / EN OBJETIVO")))) | T30: =IF(B30="",0,IF(M30="",0,1)) -> 0 | U30: =IF(T30=1,P30,0) -> 0 | V30: =IF(T30=1,IF(O30<0,0,IF(P30<IF(H30="",Settings!$C$9,H30),1,0)),0) -> 0 | W30: =IF(T30=1,IF(O30<0,1,0),0) -> 0 | X30: =IF(T30=1,M30,0) -> 0 | Y30: =IF(T30=1,O30,0) -> 0 | Z30: =IF(B30="",0,1) -> 0
I31: =IF(B31="","",C31+IF(D31="",0,D31/60*Settings!$C$7)+E31+F31+Settings!$C$8) | J31: =IF(B31="","",MAX(0,($I31+(Settings!$C$12+Settings!$C$13)-$G31*(1-(Settings!$C$10+Settings!$C$11+IF(Settings!$C$15="Yes / Sí",Settings!$C$14,0))))/(1-(Settings!$C$10+Settings!$C$11+IF(Settings!$C$15="Yes / Sí",Settings!$C$14,0))))) | K31: =IF(B31="","",IF(1-(Settings!$C$10+Settings!$C$11+IF(Settings!$C$15="Yes / Sí",Settings!$C$14,0))-IF(H31="",Settings!$C$9,H31)<=0,0,MAX(0,IF(Settings!$C$16="Yes / Sí",IF(ROUNDUP(($I31+(Settings!$C$12+Settings!$C$13)-$G31*(1-(Settings!$C$10+Settings!$C$11+IF(Settings!$C$15="Yes / Sí",Settings!$C$14,0))))/(1-(Settings!$C$10+Settings!$C$11+IF(Settings!$C$15="Yes / Sí",Settings!$C$14,0))-IF(H31="",Settings!$C$9,H31)),0)-0.01>=($I31+(Settings!$C$12+Settings!$C$13)-$G31*(1-(Settings!$C$10+Settings!$C$11+IF(Settings!$C$15="Yes / Sí",Settings!$C$14,0))))/(1-(Settings!$C$10+Settings!$C$11+IF(Settings!$C$15="Yes / Sí",Settings!$C$14,0))-IF(H31="",Settings!$C$9,H31)),ROUNDUP(($I31+(Settings!$C$12+Settings!$C$13)-$G31*(1-(Settings!$C$10+Settings!$C$11+IF(Settings!$C$15="Yes / Sí",Settings!$C$14,0))))/(1-(Settings!$C$10+Settings!$C$11+IF(Settings!$C$15="Yes / Sí",Settings!$C$14,0))-IF(H31="",Settings!$C$9,H31)),0)-0.01,ROUNDUP(($I31+(Settings!$C$12+Settings!$C$13)-$G31*(1-(Settings!$C$10+Settings!$C$11+IF(Settings!$C$15="Yes / Sí",Settings!$C$14,0))))/(1-(Settings!$C$10+Settings!$C$11+IF(Settings!$C$15="Yes / Sí",Settings!$C$14,0))-IF(H31="",Settings!$C$9,H31)),0)+0.99),ROUNDUP(($I31+(Settings!$C$12+Settings!$C$13)-$G31*(1-(Settings!$C$10+Settings!$C$11+IF(Settings!$C$15="Yes / Sí",Settings!$C$14,0))))/(1-(Settings!$C$10+Settings!$C$11+IF(Settings!$C$15="Yes / Sí",Settings!$C$14,0))-IF(H31="",Settings!$C$9,H31)),2))))) | L31: =IF(OR(B31="",K31=0),"",(K31+$G31-((K31+$G31)*(Settings!$C$10+Settings!$C$11+IF(Settings!$C$15="Yes / Sí",Settings!$C$14,0))+(Settings!$C$12+Settings!$C$13))-$I31)) | N31: =IF(OR(B31="",M31=""),"",((M31+$G31)*(Settings!$C$10+Settings!$C$11+IF(Settings!$C$15="Yes / Sí",Settings!$C$14,0))+(Settings!$C$12+Settings!$C$13))) | O31: =IF(OR(B31="",M31=""),"",(M31+$G31-((M31+$G31)*(Settings!$C$10+Settings!$C$11+IF(Settings!$C$15="Yes / Sí",Settings!$C$14,0))+(Settings!$C$12+Settings!$C$13))-$I31)) | P31: =IF(O31="","",IF(M31=0,0,O31/M31)) | Q31: =IF(OR(O31="",D31="",D31=0),"",(O31+D31/60*Settings!$C$7)/(D31/60)) | R31: =IF(B31="","",IF(M31="","Enter your price / Escribe tu precio",IF(O31<0,"⚠ LOSING MONEY / PIERDES",IF(P31<IF(H31="",Settings!$C$9,H31),"● BELOW TARGET / DEBAJO","✔ ON TARGET / EN OBJETIVO")))) | T31: =IF(B31="",0,IF(M31="",0,1)) -> 0 | U31: =IF(T31=1,P31,0) -> 0 | V31: =IF(T31=1,IF(O31<0,0,IF(P31<IF(H31="",Settings!$C$9,H31),1,0)),0) -> 0 | W31: =IF(T31=1,IF(O31<0,1,0),0) -> 0 | X31: =IF(T31=1,M31,0) -> 0 | Y31: =IF(T31=1,O31,0) -> 0 | Z31: =IF(B31="",0,1) -> 0
... I211: =IF(B211="","",C211+IF(D211="",0,D211/60*Settings!$C$7)+E211+F211+Settings!$C$8) | J211: =IF(B211="","",MAX(0,($I211+(Settings!$C$12+Settings!$C$13)-$G211*(1-(Settings!$C$10+Settings!$C$11+IF(Settings!$C$15="Yes / Sí",Settings!$C$14,0))))/(1-(Settings!$C$10+Settings!$C$11+IF(Settings!$C$15="Yes / Sí",Settings!$C$14,0))))) | K211: =IF(B211="","",IF(1-(Settings!$C$10+Settings!$C$11+IF(Settings!$C$15="Yes / Sí",Settings!$C$14,0))-IF(H211="",Settings!$C$9,H211)<=0,0,MAX(0,IF(Settings!$C$16="Yes / Sí",IF(ROUNDUP(($I211+(Settings!$C$12+Settings!$C$13)-$G211*(1-(Settings!$C$10+Settings!$C$11+IF(Settings!$C$15="Yes / Sí",Settings!$C$14,0))))/(1-(Settings!$C$10+Settings!$C$11+IF(Settings!$C$15="Yes / Sí",Settings!$C$14,0))-IF(H211="",Settings!$C$9,H211)),0)-0.01>=($I211+(Settings!$C$12+Settings!$C$13)-$G211*(1-(Settings!$C$10+Settings!$C$11+IF(Settings!$C$15="Yes / Sí",Settings!$C$14,0))))/(1-(Settings!$C$10+Settings!$C$11+IF(Settings!$C$15="Yes / Sí",Settings!$C$14,0))-IF(H211="",Settings!$C$9,H211)),ROUNDUP(($I211+(Settings!$C$12+Settings!$C$13)-$G211*(1-(Settings!$C$10+Settings!$C$11+IF(Settings!$C$15="Yes / Sí",Settings!$C$14,0))))/(1-(Settings!$C$10+Settings!$C$11+IF(Settings!$C$15="Yes / Sí",Settings!$C$14,0))-IF(H211="",Settings!$C$9,H211)),0)-0.01,ROUNDUP(($I211+(Settings!$C$12+Settings!$C$13)-$G211*(1-(Settings!$C$10+Settings!$C$11+IF(Settings!$C$15="Yes / Sí",Settings!$C$14,0))))/(1-(Settings!$C$10+Settings!$C$11+IF(Settings!$C$15="Yes / Sí",Settings!$C$14,0))-IF(H211="",Settings!$C$9,H211)),0)+0.99),ROUNDUP(($I211+(Settings!$C$12+Settings!$C$13)-$G211*(1-(Settings!$C$10+Settings!$C$11+IF(Settings!$C$15="Yes / Sí",Settings!$C$14,0))))/(1-(Settings!$C$10+Settings!$C$11+IF(Settings!$C$15="Yes / Sí",Settings!$C$14,0))-IF(H211="",Settings!$C$9,H211)),2))))) | L211: =IF(OR(B211="",K211=0),"",(K211+$G211-((K211+$G211)*(Settings!$C$10+Settings!$C$11+IF(Settings!$C$15="Yes / Sí",Settings!$C$14,0))+(Settings!$C$12+Settings!$C$13))-$I211)) | N211: =IF(OR(B211="",M211=""),"",((M211+$G211)*(Settings!$C$10+Settings!$C$11+IF(Settings!$C$15="Yes / Sí",Settings!$C$14,0))+(Settings!$C$12+Settings!$C$13))) | O211: =IF(OR(B211="",M211=""),"",(M211+$G211-((M211+$G211)*(Settings!$C$10+Settings!$C$11+IF(Settings!$C$15="Yes / Sí",Settings!$C$14,0))+(Settings!$C$12+Settings!$C$13))-$I211)) | P211: =IF(O211="","",IF(M211=0,0,O211/M211)) | Q211: =IF(OR(O211="",D211="",D211=0),"",(O211+D211/60*Settings!$C$7)/(D211/60)) | R211: =IF(B211="","",IF(M211="","Enter your price / Escribe tu precio",IF(O211<0,"⚠ LOSING MONEY / PIERDES",IF(P211<IF(H211="",Settings!$C$9,H211),"● BELOW TARGET / DEBAJO","✔ ON TARGET / EN OBJETIVO")))) | T211: =IF(B211="",0,IF(M211="",0,1)) -> 0 | U211: =IF(T211=1,P211,0) -> 0 | V211: =IF(T211=1,IF(O211<0,0,IF(P211<IF(H211="",Settings!$C$9,H211),1,0)),0) -> 0 | W211: =IF(T211=1,IF(O211<0,1,0),0) -> 0 | X211: =IF(T211=1,M211,0) -> 0 | Y211: =IF(T211=1,O211,0) -> 0 | Z211: =IF(B211="",0,1) -> 0

Sheet Settings
B1: ProfitTrack
B2: Settings / Configuración
B3: Your rate, Etsy fees and rounding. • Tu tarifa, comisiones de Etsy y redondeo.
B6: Your Numbers & Etsy Fees / Tus Números y Comisiones
B7: Your hourly rate ($ / hour) / Tu tarifa por hora | C7: 20 | E7: Pay yourself! What is one hour of your time worth?
B8: Overhead per item ($) / Gastos generales por artículo | C8: 0.5 | E8: Electricity, tools wear, software… spread per item.
B9: Default target profit margin / Margen de ganancia objetivo | C9: 0.3 | E9: Profit as a % of the price, after all costs and fees.
B10: Etsy transaction fee / Comisión de transacción | C10: 0.065 | E10: Etsy US: 6.5% of item price + shipping charged.
B11: Payment processing fee % / Procesamiento de pago % | C11: 0.03 | E11: Etsy Payments US: 3% + $0.25 per order.
B12: Payment processing fixed ($) / Procesamiento fijo | C12: 0.25
B13: Listing fee ($) / Tarifa de publicación | C13: 0.2 | E13: $0.20 per listing / renewal.
B14: Offsite Ads fee / Anuncios externos | C14: 0.15 | E14: 15% (12% if you sell $10k+/year) – only on sales from Offsite Ads.
B15: Include Offsite Ads in prices? / ¿Incluir anuncios externos? | C15: No | E15: Choose Yes to price safely for Offsite Ads sales.
B16: Round prices to .99? / ¿Redondear precios a .99? | C16: Yes / Sí | E16: Yes: $23.41 → $23.99
B18: Etsy fees shown are for US sellers (2026). Fees change and differ by country – check Etsy's Fees & Payments Policy and update these cells. Las comisiones son para vendedores de EE. UU. (2026). Cambian y varían por país – revisa la política de Etsy y actualiza estas celdas.

Sheet Materials
B1: ProfitTrack
B2: Materials Library / Lista de Materiales
B3: Enter what you paid for a pack and how many units it has – the cost per unit is calculated. • Escribe lo que pagaste por el paquete y cuántas unidades trae – el costo por unidad se calcula solo.
B5: Material Material | C5: Supplier Proveedor | D5: Pack Price Precio del Paquete | E5: Units in Pack Unidades | F5: Unit Unidad | G5: Cost per Unit Costo por Unidad | H5: Notes Notas
B6: Soy wax | C6: CandleScience | D6: 45 | E6: 160 | F6: oz | G6: =IF(OR(D6="",E6="",E6=0),"",D6/E6) -> 0.28125
B7: Fragrance oil | C7: CandleScience | D7: 17.6 | E7: 16 | F7: oz | G7: =IF(OR(D7="",E7="",E7=0),"",D7/E7) -> 1.1
B8: Cotton wick | C8: Amazon | D8: 11.99 | E8: 100 | F8: each | G8: =IF(OR(D8="",E8="",E8=0),"",D8/E8) -> 0.1199
B9: Amber jar 8 oz | C9: Uline | D9: 34.8 | E9: 24 | F9: each | G9: =IF(OR(D9="",E9="",E9=0),"",D9/E9) -> 1.45
B10: Product label | C10: Sticker Mule | D10: 30 | E10: 200 | F10: each | G10: =IF(OR(D10="",E10="",E10=0),"",D10/E10) -> 0.15
B11: Sterling silver ear wires | C11: Rio Grande | D11: 24 | E11: 50 | F11: pair | G11: =IF(OR(D11="",E11="",E11=0),"",D11/E11) -> 0.48
B12: Glass beads | C12: Fire Mountain | D12: 12.5 | E12: 250 | F12: each | G12: =IF(OR(D12="",E12="",E12=0),"",D12/E12) -> 0.05
B13: Merino yarn | C13: LoveCrafts | D13: 9.5 | E13: 1 | F13: skein | G13: =IF(OR(D13="",E13="",E13=0),"",D13/E13) -> 9.5
B14: Vinyl sticker paper | C14: Cricut | D14: 14.99 | E14: 20 | F14: sheet | G14: =IF(OR(D14="",E14="",E14=0),"",D14/E14) -> 0.7495
B15: Kraft gift box | C15: Uline | D15: 42 | E15: 100 | F15: each | G15: =IF(OR(D15="",E15="",E15=0),"",D15/E15) -> 0.42
B16: Tissue paper | C16: Dollar Tree | D16: 1.25 | E16: 20 | F16: sheet | G16: =IF(OR(D16="",E16="",E16=0),"",D16/E16) -> 0.0625
B17: Thank-you card | C17: Vistaprint | D17: 25 | E17: 250 | F17: each | G17: =IF(OR(D17="",E17="",E17=0),"",D17/E17) -> 0.1
G18: =IF(OR(D18="",E18="",E18=0),"",D18/E18)
G19: =IF(OR(D19="",E19="",E19=0),"",D19/E19)
G20: =IF(OR(D20="",E20="",E20=0),"",D20/E20)
G21: =IF(OR(D21="",E21="",E21=0),"",D21/E21)
G22: =IF(OR(D22="",E22="",E22=0),"",D22/E22)
G23: =IF(OR(D23="",E23="",E23=0),"",D23/E23)
G24: =IF(OR(D24="",E24="",E24=0),"",D24/E24)
G25: =IF(OR(D25="",E25="",E25=0),"",D25/E25)
G26: =IF(OR(D26="",E26="",E26=0),"",D26/E26)
G27: =IF(OR(D27="",E27="",E27=0),"",D27/E27)
G28: =IF(OR(D28="",E28="",E28=0),"",D28/E28)
G29: =IF(OR(D29="",E29="",E29=0),"",D29/E29)
... G205: =IF(OR(D205="",E205="",E205=0),"",D205/E205)

Sheet Quick Start Guide
B1: ProfitTrack
B2: Quick Start Guide / Guía Rápida
B3: Up and running in 5 minutes. • Listo en 5 minutos.
B6: # | C6: ENGLISH | D6: ESPAÑOL
B7: 1 | C7: Open Settings: enter your hourly rate and overhead per item, choose your default target margin, and check the Etsy fees (US 2026 rates are filled in). | D7: Abre Settings (Configuración): escribe tu tarifa por hora y gastos generales, elige tu margen objetivo y revisa las comisiones de Etsy (tarifas de EE. UU. 2026 ya incluidas).
B8: 2 | C8: Fill the Materials sheet with your supplies: what you paid for a pack and how many units it has. The cost per unit is calculated for you. Replace the example rows. | D8: Llena la hoja Materials con tus materiales: lo que pagaste por el paquete y cuántas unidades trae. El costo por unidad se calcula solo. Reemplaza los ejemplos.
B9: 3 | C9: Calculator – price one product in detail: pick each material from the list and enter the quantity used. Not in your list? Type the name and fill 'Your Cost'. | D9: Calculator – calcula un producto en detalle: elige cada material de la lista y escribe la cantidad usada. ¿No está? Escribe el nombre y llena 'Tu Costo'.
B10: 4 | C10: Add your time (minutes), packaging, shipping label cost and what you charge for shipping (0 = free shipping, built into the price). | D10: Agrega tu tiempo (minutos), empaque, costo de la etiqueta y lo que cobras de envío (0 = envío gratis, incluido en el precio).
B11: 5 | C11: Read your prices: Break-even (no profit), Recommended (covers costs, Etsy fees and your target margin, rounded to .99), your profit per sale and what you earn per hour. | D11: Lee tus precios: Mínimo (sin ganancia), Recomendado (cubre costos, comisiones y tu margen, redondeado a .99), tu ganancia por venta y cuánto ganas por hora.
B12: 6 | C12: Test Your Own Price: type any price to see the fees, profit, margin and a ✔ / ● / ⚠ verdict instantly. | D12: Prueba tu Precio: escribe cualquier precio y verás comisiones, ganancia, margen y un veredicto ✔ / ● / ⚠ al instante.
B13: 7 | C13: Product List – price your whole shop: one row per product with materials $, minutes, packaging and shipping. Enter your current price to see your real margin and $ per hour. | D13: Product List – todo tu catálogo: una fila por producto con materiales $, minutos, empaque y envío. Escribe tu precio actual para ver tu margen real y $ por hora.
B14: 8 | C14: Fix the red ⚠ LOSING MONEY products first, then raise the ● BELOW TARGET ones. The summary cards at the top count them for you. | D14: Arregla primero los productos ⚠ PIERDES DINERO y luego sube los ● DEBAJO DEL OBJETIVO. Las tarjetas de arriba los cuentan por ti.
B15: 9 | C15: Selling through Offsite Ads? Set 'Include Offsite Ads' to Yes in Settings to price safely for those sales. | D15: ¿Vendes con Anuncios Externos? Cambia 'Incluir anuncios externos' a Sí en Configuración para cubrir esas ventas.
B16: 10 | C16: Google Sheets: upload to Google Drive → Open with Google Sheets → File → Save as Google Sheets. Tip: save a blank copy first. | D16: Google Sheets: súbelo a Google Drive → Abrir con Google Sheets → Archivo → Guardar como Hojas de cálculo de Google. Consejo: guarda una copia en blanco.
B18: Color Legend / Leyenda de Colores
C19: Light teal = type your data here | D19: Verde claro = escribe tus datos aquí
C20: Grey = automatic formula – don't type here | D20: Gris = fórmula automática – no escribas aquí
C21: Yellow = settings you can change | D21: Amarillo = ajustes que puedes cambiar
B23: FAQ / Preguntas Frecuentes
C24: Q: What's the difference between markup and margin? A: Margin is profit as a % of the price. A 30% margin on a $30 item means $9 profit after all costs and fees. | D24: P: ¿Diferencia entre markup y margen? R: El margen es la ganancia como % del precio. Un margen de 30% en un artículo de $30 son $9 de ganancia después de costos y comisiones.
C25: Q: Do I include shipping? A: Yes – the label you pay is a cost. If you charge the buyer for shipping, enter it too: Etsy charges fees on it, and the calculator handles that. | D25: P: ¿Incluyo el envío? R: Sí – la etiqueta que pagas es un costo. Si cobras envío, escríbelo también: Etsy cobra comisión sobre él y la calculadora lo considera.
C26: Q: I sell outside the US. A: Change the fee cells in Settings to your country's Etsy rates. Prices are shown with a $ sign but work for any currency. | D26: P: Vendo fuera de EE. UU. R: Cambia las comisiones en Settings a las de tu país. Los precios muestran $ pero funcionan con cualquier moneda.
B28: Phone, Tablet & Computer / Celular, Tableta y Computadora
C29: 💻 Computer (Windows / Mac): open in Microsoft Excel, or in Google Sheets from any browser. Everything works. | D29: 💻 Computadora (Windows / Mac): ábrelo en Microsoft Excel o en Google Sheets desde cualquier navegador. Todo funciona.
C30: 📱 iPhone, iPad & Android — RECOMMENDED: the free Microsoft Excel app or the free Google Sheets app. Formulas, dropdowns, charts and alerts all work. | D30: 📱 iPhone, iPad y Android — RECOMENDADO: la app gratuita Microsoft Excel o la app gratuita Google Sheets. Fórmulas, listas, gráficas y alertas funcionan.
C31: 🍎 Apple Numbers: formulas, Dashboard, charts and alerts work, but Numbers removes dropdown lists from Excel files (you'll see a message – this is normal). Type the option exactly as listed, or re-add a menu: select the cells → Format → Cell → Data Format → Pop-Up Menu. | D31: 🍎 Apple Numbers: las fórmulas, el Panel, las gráficas y las alertas funcionan, pero Numbers elimina las listas desplegables de los archivos de Excel (verás un aviso – es normal). Escribe la opción tal como aparece, o vuelve a crear el menú: selecciona las celdas → Formato → Celda → Formato de datos → Menú desplegable.
