Workbook

Sheet Cover
B4: RESELLER TOOLKIT • KIT PARA REVENDEDORES
B6: ProfitTrack
B9: Reseller Profit Tracker & Dashboard
B10: Registro de Ganancias y Panel para Revendedores
B11: eBay • Facebook Marketplace • Etsy • Poshmark • Other / Otro
B15: WHAT'S INSIDE / CONTENIDO (click to open • clic para abrir)
C17: 📊 Dashboard / Panel
C18: KPIs, profit by platform, monthly trend, Top 5 / Indicadores, ganancia por plataforma, tendencia mensual, Top 5
C20: 🧾 Tracker / Registro
C21: Log every sale – fees, profit & margin auto-calculated / Registra cada venta – comisiones, ganancia y margen automáticos
C23: 🔍 Sourcing List / Lista de Compras (BONUS)
C24: Check profit BEFORE you buy / Calcula la ganancia ANTES de comprar
C26: 🚀 Quick Start Guide / Guía Rápida
C27: Step-by-step setup in 5 minutes / Configuración paso a paso en 5 minutos
B31: 💻 PC / Mac • 📱 iPhone / Android — Excel • Google Sheets | Computadora y celular — Excel • Google Sheets
B33: Start here → Quick Start Guide | Empieza aquí → Guía Rápida
B36: © ProfitTrack • v1.0 • For personal use only – do not resell or redistribute / Solo para uso personal – prohibida su reventa o distribución

Sheet Dashboard
B1: ProfitTrack
B2: Dashboard / Panel de Control
B3: Updates automatically from the Tracker. Returned sales are excluded. • Se actualiza automáticamente desde el Registro. Las ventas devueltas se excluyen.
B6: TOTAL REVENUE | E6: TOTAL PROFIT | H6: AVG. PROFIT MARGIN | K6: NUMBER OF SALES
B7: Ingresos Totales | E7: Ganancia Total | H7: Margen Promedio | K7: Número de Ventas
B8: =SUMIFS(Tracker!$G$6:$G$505,Tracker!$Q$6:$Q$505,1) -> 2259.99 | E8: =SUMIFS(Tracker!$L$6:$L$505,Tracker!$Q$6:$Q$505,1) -> 964.37383 | H8: =IF(B8=0,0,E8/B8) -> 0.42671597 | K8: =SUM(Tracker!$Q$6:$Q$505) -> 19
B9: =SUMIFS(Tracker!$I$6:$I$505,Tracker!$Q$6:$Q$505,1) -> 283.41618 | E9: =IF(K8=0,0,E8/K8) -> 50.756517 | H9: weighted: profit ÷ revenue / ponderado | K9: =SUM(Tracker!$S$6:$S$505) -> 3
B11: Profit by Platform / Ganancia por Plataforma
B12: Platform Plataforma | C12: Sales Ventas | E12: Revenue Ingresos | F12: Profit Ganancia | H12: Margin Margen
B13: eBay | C13: =COUNTIFS(Tracker!$Q$6:$Q$505,1,Tracker!$C$6:$C$505,$B13) -> 7 | E13: =SUMIFS(Tracker!$G$6:$G$505,Tracker!$Q$6:$Q$505,1,Tracker!$C$6:$C$505,$B13) -> 1430.99 | F13: =SUMIFS(Tracker!$L$6:$L$505,Tracker!$Q$6:$Q$505,1,Tracker!$C$6:$C$505,$B13) -> 486.93383 | H13: =IF(E13=0,0,F13/E13) -> 0.34027759
B14: Facebook Marketplace | C14: =COUNTIFS(Tracker!$Q$6:$Q$505,1,Tracker!$C$6:$C$505,$B14) -> 3 | E14: =SUMIFS(Tracker!$G$6:$G$505,Tracker!$Q$6:$Q$505,1,Tracker!$C$6:$C$505,$B14) -> 300 | F14: =SUMIFS(Tracker!$L$6:$L$505,Tracker!$Q$6:$Q$505,1,Tracker!$C$6:$C$505,$B14) -> 162.5 | H14: =IF(E14=0,0,F14/E14) -> 0.54166667
B15: Etsy | C15: =COUNTIFS(Tracker!$Q$6:$Q$505,1,Tracker!$C$6:$C$505,$B15) -> 4 | E15: =SUMIFS(Tracker!$G$6:$G$505,Tracker!$Q$6:$Q$505,1,Tracker!$C$6:$C$505,$B15) -> 198 | F15: =SUMIFS(Tracker!$L$6:$L$505,Tracker!$Q$6:$Q$505,1,Tracker!$C$6:$C$505,$B15) -> 124.44 | H15: =IF(E15=0,0,F15/E15) -> 0.62848485
B16: Poshmark | C16: =COUNTIFS(Tracker!$Q$6:$Q$505,1,Tracker!$C$6:$C$505,$B16) -> 4 | E16: =SUMIFS(Tracker!$G$6:$G$505,Tracker!$Q$6:$Q$505,1,Tracker!$C$6:$C$505,$B16) -> 309 | F16: =SUMIFS(Tracker!$L$6:$L$505,Tracker!$Q$6:$Q$505,1,Tracker!$C$6:$C$505,$B16) -> 189.2 | H16: =IF(E16=0,0,F16/E16) -> 0.61229773
B17: Other | C17: =COUNTIFS(Tracker!$Q$6:$Q$505,1,Tracker!$C$6:$C$505,$B17) -> 1 | E17: =SUMIFS(Tracker!$G$6:$G$505,Tracker!$Q$6:$Q$505,1,Tracker!$C$6:$C$505,$B17) -> 22 | F17: =SUMIFS(Tracker!$L$6:$L$505,Tracker!$Q$6:$Q$505,1,Tracker!$C$6:$C$505,$B17) -> 1.3 | H17: =IF(E17=0,0,F17/E17) -> 0.059090909
B18: TOTAL | C18: =SUM(C13:C17) -> 19 | E18: =SUM(E13:E17) -> 2259.99 | F18: =SUM(F13:F17) -> 964.37383 | H18: =IF(E18=0,0,F18/E18) -> 0.42671597
B19: Totals match the KPI cards above. / Los totales coinciden con los indicadores.
B21: Monthly Profit Trend / Tendencia Mensual de Ganancia
B22: Year / Año: | C22: =IF(COUNT(Tracker!$D$6:$D$505)=0,YEAR(TODAY()),YEAR(MAX(Tracker!$D$6:$D$505))) -> 2026 | E22: ← type a year to change / escribe un año para cambiar
B23: Month Mes | C23: Sales Ventas | E23: Revenue Ingresos | F23: Profit Ganancia | H23: Margin Margen
B24: Jan / Ene | C24: =COUNTIFS(Tracker!$R$6:$R$505,$C$22*100+1) -> 2 | E24: =SUMIFS(Tracker!$G$6:$G$505,Tracker!$R$6:$R$505,$C$22*100+1) -> 134.99 | F24: =SUMIFS(Tracker!$L$6:$L$505,Tracker!$R$6:$R$505,$C$22*100+1) -> 73.616325 | H24: =IF(E24=0,0,F24/E24) -> 0.54534651
B25: Feb / Feb | C25: =COUNTIFS(Tracker!$R$6:$R$505,$C$22*100+2) -> 3 | E25: =SUMIFS(Tracker!$G$6:$G$505,Tracker!$R$6:$R$505,$C$22*100+2) -> 132 | F25: =SUMIFS(Tracker!$L$6:$L$505,Tracker!$R$6:$R$505,$C$22*100+2) -> 81.31 | H25: =IF(E25=0,0,F25/E25) -> 0.61598485
B26: Mar / Mar | C26: =COUNTIFS(Tracker!$R$6:$R$505,$C$22*100+3) -> 2 | E26: =SUMIFS(Tracker!$G$6:$G$505,Tracker!$R$6:$R$505,$C$22*100+3) -> 979 | F26: =SUMIFS(Tracker!$L$6:$L$505,Tracker!$R$6:$R$505,$C$22*100+3) -> 307.1325 | H26: =IF(E26=0,0,F26/E26) -> 0.31372063
B27: Apr / Abr | C27: =COUNTIFS(Tracker!$R$6:$R$505,$C$22*100+4) -> 2 | E27: =SUMIFS(Tracker!$G$6:$G$505,Tracker!$R$6:$R$505,$C$22*100+4) -> 205 | F27: =SUMIFS(Tracker!$L$6:$L$505,Tracker!$R$6:$R$505,$C$22*100+4) -> 140.275 | H27: =IF(E27=0,0,F27/E27) -> 0.68426829
B28: May / May | C28: =COUNTIFS(Tracker!$R$6:$R$505,$C$22*100+5) -> 2 | E28: =SUMIFS(Tracker!$G$6:$G$505,Tracker!$R$6:$R$505,$C$22*100+5) -> 86 | F28: =SUMIFS(Tracker!$L$6:$L$505,Tracker!$R$6:$R$505,$C$22*100+5) -> 32.165 | H28: =IF(E28=0,0,F28/E28) -> 0.37401163
B29: Jun / Jun | C29: =COUNTIFS(Tracker!$R$6:$R$505,$C$22*100+6) -> 2 | E29: =SUMIFS(Tracker!$G$6:$G$505,Tracker!$R$6:$R$505,$C$22*100+6) -> 195 | F29: =SUMIFS(Tracker!$L$6:$L$505,Tracker!$R$6:$R$505,$C$22*100+6) -> 81.175 | H29: =IF(E29=0,0,F29/E29) -> 0.41628205
B30: Jul / Jul | C30: =COUNTIFS(Tracker!$R$6:$R$505,$C$22*100+7) -> 2 | E30: =SUMIFS(Tracker!$G$6:$G$505,Tracker!$R$6:$R$505,$C$22*100+7) -> 157 | F30: =SUMIFS(Tracker!$L$6:$L$505,Tracker!$R$6:$R$505,$C$22*100+7) -> 85.4125 | H30: =IF(E30=0,0,F30/E30) -> 0.54402866
B31: Aug / Ago | C31: =COUNTIFS(Tracker!$R$6:$R$505,$C$22*100+8) -> 1 | E31: =SUMIFS(Tracker!$G$6:$G$505,Tracker!$R$6:$R$505,$C$22*100+8) -> 210 | F31: =SUMIFS(Tracker!$L$6:$L$505,Tracker!$R$6:$R$505,$C$22*100+8) -> 125.175 | H31: =IF(E31=0,0,F31/E31) -> 0.59607143
B32: Sep / Sep | C32: =COUNTIFS(Tracker!$R$6:$R$505,$C$22*100+9) -> 3 | E32: =SUMIFS(Tracker!$G$6:$G$505,Tracker!$R$6:$R$505,$C$22*100+9) -> 161 | F32: =SUMIFS(Tracker!$L$6:$L$505,Tracker!$R$6:$R$505,$C$22*100+9) -> 38.1125 | H32: =IF(E32=0,0,F32/E32) -> 0.2367236
B33: Oct / Oct | C33: =COUNTIFS(Tracker!$R$6:$R$505,$C$22*100+10) -> 0 | E33: =SUMIFS(Tracker!$G$6:$G$505,Tracker!$R$6:$R$505,$C$22*100+10) -> 0 | F33: =SUMIFS(Tracker!$L$6:$L$505,Tracker!$R$6:$R$505,$C$22*100+10) -> 0 | H33: =IF(E33=0,0,F33/E33) -> 0
B34: Nov / Nov | C34: =COUNTIFS(Tracker!$R$6:$R$505,$C$22*100+11) -> 0 | E34: =SUMIFS(Tracker!$G$6:$G$505,Tracker!$R$6:$R$505,$C$22*100+11) -> 0 | F34: =SUMIFS(Tracker!$L$6:$L$505,Tracker!$R$6:$R$505,$C$22*100+11) -> 0 | H34: =IF(E34=0,0,F34/E34) -> 0
B35: Dec / Dic | C35: =COUNTIFS(Tracker!$R$6:$R$505,$C$22*100+12) -> 0 | E35: =SUMIFS(Tracker!$G$6:$G$505,Tracker!$R$6:$R$505,$C$22*100+12) -> 0 | F35: =SUMIFS(Tracker!$L$6:$L$505,Tracker!$R$6:$R$505,$C$22*100+12) -> 0 | H35: =IF(E35=0,0,F35/E35) -> 0
B36: YEAR / AÑO | C36: =SUM(C24:C35) -> 19 | E36: =SUM(E24:E35) -> 2259.99 | F36: =SUM(F24:F35) -> 964.37383 | H36: =IF(E36=0,0,F36/E36) -> 0.42671597
B39: Top 5 Most Profitable Sales / Top 5 Ventas Más Rentables
B40: # | C40: Product Producto | H40: Platform Plataforma | I40: Sale Date Fecha | K40: Net Profit Ganancia | L40: Margin Margen
B41: 1 | C41: =IFERROR(IF(LARGE(Tracker!$P$6:$P$505,1)<-100000000000000,"—",INDEX(Tracker!$B$6:$B$505,MATCH(LARGE(Tracker!$P$6:$P$505,1),Tracker!$P$6:$P$505,0))),"—") -> LEGO Star Wars 75192 (sealed) | H41: =IFERROR(IF(LARGE(Tracker!$P$6:$P$505,1)<-100000000000000,"",INDEX(Tracker!$C$6:$C$505,MATCH(LARGE(Tracker!$P$6:$P$505,1),Tracker!$P$6:$P$505,0))),"") -> eBay | I41: =IFERROR(IF(LARGE(Tracker!$P$6:$P$505,1)<-100000000000000,"",IF(INDEX(Tracker!$D$6:$D$505,MATCH(LARGE(Tracker!$P$6:$P$505,1),Tracker!$P$6:$P$505,0))=0,"",INDEX(Tracker!$D$6:$D$505,MATCH(LARGE(Tracker!$P$6:$P$505,1),Tracker!$P$6:$P$505,0)))),"") -> 46091 | K41: =IFERROR(IF(LARGE(Tracker!$P$6:$P$505,1)<-100000000000000,"",INDEX(Tracker!$L$6:$L$505,MATCH(LARGE(Tracker!$P$6:$P$505,1),Tracker!$P$6:$P$505,0))),"") -> 198.1325 | L41: =IFERROR(IF(LARGE(Tracker!$P$6:$P$505,1)<-100000000000000,"",INDEX(Tracker!$M$6:$M$505,MATCH(LARGE(Tracker!$P$6:$P$505,1),Tracker!$P$6:$P$505,0))),"") -> 0.24797559
B42: 2 | C42: =IFERROR(IF(LARGE(Tracker!$P$6:$P$505,2)<-100000000000000,"—",INDEX(Tracker!$B$6:$B$505,MATCH(LARGE(Tracker!$P$6:$P$505,2),Tracker!$P$6:$P$505,0))),"—") -> Vintage Polaroid SX-70 | H42: =IFERROR(IF(LARGE(Tracker!$P$6:$P$505,2)<-100000000000000,"",INDEX(Tracker!$C$6:$C$505,MATCH(LARGE(Tracker!$P$6:$P$505,2),Tracker!$P$6:$P$505,0))),"") -> eBay | I42: =IFERROR(IF(LARGE(Tracker!$P$6:$P$505,2)<-100000000000000,"",IF(INDEX(Tracker!$D$6:$D$505,MATCH(LARGE(Tracker!$P$6:$P$505,2),Tracker!$P$6:$P$505,0))=0,"",INDEX(Tracker!$D$6:$D$505,MATCH(LARGE(Tracker!$P$6:$P$505,2),Tracker!$P$6:$P$505,0)))),"") -> 46262 | K42: =IFERROR(IF(LARGE(Tracker!$P$6:$P$505,2)<-100000000000000,"",INDEX(Tracker!$L$6:$L$505,MATCH(LARGE(Tracker!$P$6:$P$505,2),Tracker!$P$6:$P$505,0))),"") -> 125.175 | L42: =IFERROR(IF(LARGE(Tracker!$P$6:$P$505,2)<-100000000000000,"",INDEX(Tracker!$M$6:$M$505,MATCH(LARGE(Tracker!$P$6:$P$505,2),Tracker!$P$6:$P$505,0))),"") -> 0.59607143
B43: 3 | C43: =IFERROR(IF(LARGE(Tracker!$P$6:$P$505,3)<-100000000000000,"—",INDEX(Tracker!$B$6:$B$505,MATCH(LARGE(Tracker!$P$6:$P$505,3),Tracker!$P$6:$P$505,0))),"—") -> Coach Tabby Shoulder Bag | H43: =IFERROR(IF(LARGE(Tracker!$P$6:$P$505,3)<-100000000000000,"",INDEX(Tracker!$C$6:$C$505,MATCH(LARGE(Tracker!$P$6:$P$505,3),Tracker!$P$6:$P$505,0))),"") -> Poshmark | I43: =IFERROR(IF(LARGE(Tracker!$P$6:$P$505,3)<-100000000000000,"",IF(INDEX(Tracker!$D$6:$D$505,MATCH(LARGE(Tracker!$P$6:$P$505,3),Tracker!$P$6:$P$505,0))=0,"",INDEX(Tracker!$D$6:$D$505,MATCH(LARGE(Tracker!$P$6:$P$505,3),Tracker!$P$6:$P$505,0)))),"") -> 46103 | K43: =IFERROR(IF(LARGE(Tracker!$P$6:$P$505,3)<-100000000000000,"",INDEX(Tracker!$L$6:$L$505,MATCH(LARGE(Tracker!$P$6:$P$505,3),Tracker!$P$6:$P$505,0))),"") -> 109 | L43: =IFERROR(IF(LARGE(Tracker!$P$6:$P$505,3)<-100000000000000,"",INDEX(Tracker!$M$6:$M$505,MATCH(LARGE(Tracker!$P$6:$P$505,3),Tracker!$P$6:$P$505,0))),"") -> 0.60555556
B44: 4 | C44: =IFERROR(IF(LARGE(Tracker!$P$6:$P$505,4)<-100000000000000,"—",INDEX(Tracker!$B$6:$B$505,MATCH(LARGE(Tracker!$P$6:$P$505,4),Tracker!$P$6:$P$505,0))),"—") -> Mid-Century Teak Side Table | H44: =IFERROR(IF(LARGE(Tracker!$P$6:$P$505,4)<-100000000000000,"",INDEX(Tracker!$C$6:$C$505,MATCH(LARGE(Tracker!$P$6:$P$505,4),Tracker!$P$6:$P$505,0))),"") -> Facebook Marketplace | I44: =IFERROR(IF(LARGE(Tracker!$P$6:$P$505,4)<-100000000000000,"",IF(INDEX(Tracker!$D$6:$D$505,MATCH(LARGE(Tracker!$P$6:$P$505,4),Tracker!$P$6:$P$505,0))=0,"",INDEX(Tracker!$D$6:$D$505,MATCH(LARGE(Tracker!$P$6:$P$505,4),Tracker!$P$6:$P$505,0)))),"") -> 46117 | K44: =IFERROR(IF(LARGE(Tracker!$P$6:$P$505,4)<-100000000000000,"",INDEX(Tracker!$L$6:$L$505,MATCH(LARGE(Tracker!$P$6:$P$505,4),Tracker!$P$6:$P$505,0))),"") -> 100 | L44: =IFERROR(IF(LARGE(Tracker!$P$6:$P$505,4)<-100000000000000,"",INDEX(Tracker!$M$6:$M$505,MATCH(LARGE(Tracker!$P$6:$P$505,4),Tracker!$P$6:$P$505,0))),"") -> 0.66666667
B45: 5 | C45: =IFERROR(IF(LARGE(Tracker!$P$6:$P$505,5)<-100000000000000,"—",INDEX(Tracker!$B$6:$B$505,MATCH(LARGE(Tracker!$P$6:$P$505,5),Tracker!$P$6:$P$505,0))),"—") -> Carhartt Detroit Jacket | H45: =IFERROR(IF(LARGE(Tracker!$P$6:$P$505,5)<-100000000000000,"",INDEX(Tracker!$C$6:$C$505,MATCH(LARGE(Tracker!$P$6:$P$505,5),Tracker!$P$6:$P$505,0))),"") -> eBay | I45: =IFERROR(IF(LARGE(Tracker!$P$6:$P$505,5)<-100000000000000,"",IF(INDEX(Tracker!$D$6:$D$505,MATCH(LARGE(Tracker!$P$6:$P$505,5),Tracker!$P$6:$P$505,0))=0,"",INDEX(Tracker!$D$6:$D$505,MATCH(LARGE(Tracker!$P$6:$P$505,5),Tracker!$P$6:$P$505,0)))),"") -> 46228 | K45: =IFERROR(IF(LARGE(Tracker!$P$6:$P$505,5)<-100000000000000,"",INDEX(Tracker!$L$6:$L$505,MATCH(LARGE(Tracker!$P$6:$P$505,5),Tracker!$P$6:$P$505,0))),"") -> 84.1125 | L45: =IFERROR(IF(LARGE(Tracker!$P$6:$P$505,5)<-100000000000000,"",INDEX(Tracker!$M$6:$M$505,MATCH(LARGE(Tracker!$P$6:$P$505,5),Tracker!$P$6:$P$505,0))),"") -> 0.62305556
B46: Ranked by net profit per sale (returns excluded). / Ordenado por ganancia neta por venta (sin devoluciones).

Sheet Tracker
B1: ProfitTrack
B2: Sales Tracker / Registro de Ventas
B3: Type in the light-teal columns only. Grey columns calculate automatically. • Escribe solo en las columnas verde claro. Las columnas grises se calculan solas.
B5: Product Name Nombre del Producto | C5: Platform Plataforma | D5: Sale Date Fecha de Venta | E5: Purchase Cost Costo de Compra | F5: Shipping In Envío (Entrada) | G5: Sale Price Precio de Venta | H5: Platform Fee % % Comisión | I5: Platform Fee $ Comisión $ | J5: Shipping Out Envío (Salida) | K5: Other Costs Otros Costos | L5: Net Profit Ganancia Neta | M5: Profit Margin % Margen % | N5: Status Estado | O5: Margin Alert (<15%) Alerta de Margen | P5: Helper – do not edit: Rank key | Q5: Helper – do not edit: Valid sale (1/0) | R5: Helper – do not edit: Year-month key | S5: Helper – do not edit: Low margin (1/0)
B6: Nike Air Max 90 – Size 10 | C6: eBay | D6: 46030 | E6: 22 | F6: 0 | G6: 89.99 | H6: 0.1325 | I6: =IF(G6="","",G6*H6) -> 11.923675 | J6: 12.45 | K6: 0 | L6: =IF(OR(B6="",G6=""),"",G6-E6-F6-I6-J6-K6) -> 43.616325 | M6: =IF(L6="","",IF(G6=0,0,L6/G6)) -> 0.48467969 | N6: Delivered / Entregado | O6: =IF(M6="","",IF(M6<0.15,"⚠ LOW MARGIN / MARGEN BAJO","✔ OK")) -> ✔ OK | P6: =IF(Q6=1,L6+ROW()/1000000,-1000000000000000) -> 43.616331 | Q6: =IF(B6="",0,IF(G6="",0,IF(N6="Returned / Devuelto",0,1))) -> 1 | R6: =IF(Q6=1,IF(ISNUMBER(D6),YEAR(D6)*100+MONTH(D6),0),0) -> 202601 | S6: =IF(Q6=1,IF(M6<0.15,1,0),0) -> 0
B7: Levi's 501 Vintage Jeans | C7: Poshmark | D7: 46041 | E7: 6 | F7: 0 | G7: 45 | H7: 0.2 | I7: =IF(G7="","",G7*H7) -> 9 | J7: 0 | K7: 0 | L7: =IF(OR(B7="",G7=""),"",G7-E7-F7-I7-J7-K7) -> 30 | M7: =IF(L7="","",IF(G7=0,0,L7/G7)) -> 0.66666667 | N7: Delivered / Entregado | O7: =IF(M7="","",IF(M7<0.15,"⚠ LOW MARGIN / MARGEN BAJO","✔ OK")) -> ✔ OK | P7: =IF(Q7=1,L7+ROW()/1000000,-1000000000000000) -> 30.000007 | Q7: =IF(B7="",0,IF(G7="",0,IF(N7="Returned / Devuelto",0,1))) -> 1 | R7: =IF(Q7=1,IF(ISNUMBER(D7),YEAR(D7)*100+MONTH(D7),0),0) -> 202601 | S7: =IF(Q7=1,IF(M7<0.15,1,0),0) -> 0
B8: Pyrex Butterprint Bowl Set | C8: Facebook Marketplace | D8: 46056 | E8: 8 | F8: 0 | G8: 40 | H8: 0 | I8: =IF(G8="","",G8*H8) -> 0 | J8: 0 | K8: 0 | L8: =IF(OR(B8="",G8=""),"",G8-E8-F8-I8-J8-K8) -> 32 | M8: =IF(L8="","",IF(G8=0,0,L8/G8)) -> 0.8 | N8: Delivered / Entregado | O8: =IF(M8="","",IF(M8<0.15,"⚠ LOW MARGIN / MARGEN BAJO","✔ OK")) -> ✔ OK | P8: =IF(Q8=1,L8+ROW()/1000000,-1000000000000000) -> 32.000008 | Q8: =IF(B8="",0,IF(G8="",0,IF(N8="Returned / Devuelto",0,1))) -> 1 | R8: =IF(Q8=1,IF(ISNUMBER(D8),YEAR(D8)*100+MONTH(D8),0),0) -> 202602 | S8: =IF(Q8=1,IF(M8<0.15,1,0),0) -> 0
B9: Handmade Ceramic Mug (Vintage) | C9: Etsy | D9: 46067 | E9: 3 | F9: 0 | G9: 28 | H9: 0.095 | I9: =IF(G9="","",G9*H9) -> 2.66 | J9: 6.5 | K9: 0.25 | L9: =IF(OR(B9="",G9=""),"",G9-E9-F9-I9-J9-K9) -> 15.59 | M9: =IF(L9="","",IF(G9=0,0,L9/G9)) -> 0.55678571 | N9: Delivered / Entregado | O9: =IF(M9="","",IF(M9<0.15,"⚠ LOW MARGIN / MARGEN BAJO","✔ OK")) -> ✔ OK | P9: =IF(Q9=1,L9+ROW()/1000000,-1000000000000000) -> 15.590009 | Q9: =IF(B9="",0,IF(G9="",0,IF(N9="Returned / Devuelto",0,1))) -> 1 | R9: =IF(Q9=1,IF(ISNUMBER(D9),YEAR(D9)*100+MONTH(D9),0),0) -> 202602 | S9: =IF(Q9=1,IF(M9<0.15,1,0),0) -> 0
B10: Patagonia Better Sweater – M | C10: eBay | D10: 46080 | E10: 12 | F10: 0 | G10: 64 | H10: 0.1325 | I10: =IF(G10="","",G10*H10) -> 8.48 | J10: 9.8 | K10: 0 | L10: =IF(OR(B10="",G10=""),"",G10-E10-F10-I10-J10-K10) -> 33.72 | M10: =IF(L10="","",IF(G10=0,0,L10/G10)) -> 0.526875 | N10: Delivered / Entregado | O10: =IF(M10="","",IF(M10<0.15,"⚠ LOW MARGIN / MARGEN BAJO","✔ OK")) -> ✔ OK | P10: =IF(Q10=1,L10+ROW()/1000000,-1000000000000000) -> 33.72001 | Q10: =IF(B10="",0,IF(G10="",0,IF(N10="Returned / Devuelto",0,1))) -> 1 | R10: =IF(Q10=1,IF(ISNUMBER(D10),YEAR(D10)*100+MONTH(D10),0),0) -> 202602 | S10: =IF(Q10=1,IF(M10<0.15,1,0),0) -> 0
B11: LEGO Star Wars 75192 (sealed) | C11: eBay | D11: 46091 | E11: 450 | F11: 0 | G11: 799 | H11: 0.1325 | I11: =IF(G11="","",G11*H11) -> 105.8675 | J11: 45 | K11: 0 | L11: =IF(OR(B11="",G11=""),"",G11-E11-F11-I11-J11-K11) -> 198.1325 | M11: =IF(L11="","",IF(G11=0,0,L11/G11)) -> 0.24797559 | N11: Delivered / Entregado | O11: =IF(M11="","",IF(M11<0.15,"⚠ LOW MARGIN / MARGEN BAJO","✔ OK")) -> ✔ OK | P11: =IF(Q11=1,L11+ROW()/1000000,-1000000000000000) -> 198.13251 | Q11: =IF(B11="",0,IF(G11="",0,IF(N11="Returned / Devuelto",0,1))) -> 1 | R11: =IF(Q11=1,IF(ISNUMBER(D11),YEAR(D11)*100+MONTH(D11),0),0) -> 202603 | S11: =IF(Q11=1,IF(M11<0.15,1,0),0) -> 0
B12: Coach Tabby Shoulder Bag | C12: Poshmark | D12: 46103 | E12: 35 | F12: 0 | G12: 180 | H12: 0.2 | I12: =IF(G12="","",G12*H12) -> 36 | J12: 0 | K12: 0 | L12: =IF(OR(B12="",G12=""),"",G12-E12-F12-I12-J12-K12) -> 109 | M12: =IF(L12="","",IF(G12=0,0,L12/G12)) -> 0.60555556 | N12: Delivered / Entregado | O12: =IF(M12="","",IF(M12<0.15,"⚠ LOW MARGIN / MARGEN BAJO","✔ OK")) -> ✔ OK | P12: =IF(Q12=1,L12+ROW()/1000000,-1000000000000000) -> 109.00001 | Q12: =IF(B12="",0,IF(G12="",0,IF(N12="Returned / Devuelto",0,1))) -> 1 | R12: =IF(Q12=1,IF(ISNUMBER(D12),YEAR(D12)*100+MONTH(D12),0),0) -> 202603 | S12: =IF(Q12=1,IF(M12<0.15,1,0),0) -> 0
B13: Mid-Century Teak Side Table | C13: Facebook Marketplace | D13: 46117 | E13: 40 | F13: 0 | G13: 150 | H13: 0 | I13: =IF(G13="","",G13*H13) -> 0 | J13: 0 | K13: 10 | L13: =IF(OR(B13="",G13=""),"",G13-E13-F13-I13-J13-K13) -> 100 | M13: =IF(L13="","",IF(G13=0,0,L13/G13)) -> 0.66666667 | N13: Delivered / Entregado | O13: =IF(M13="","",IF(M13<0.15,"⚠ LOW MARGIN / MARGEN BAJO","✔ OK")) -> ✔ OK | P13: =IF(Q13=1,L13+ROW()/1000000,-1000000000000000) -> 100.00001 | Q13: =IF(B13="",0,IF(G13="",0,IF(N13="Returned / Devuelto",0,1))) -> 1 | R13: =IF(Q13=1,IF(ISNUMBER(D13),YEAR(D13)*100+MONTH(D13),0),0) -> 202604 | S13: =IF(Q13=1,IF(M13<0.15,1,0),0) -> 0
B14: Vintage Band Tee – Nirvana | C14: Etsy | D14: 46130 | E14: 4 | F14: 0 | G14: 55 | H14: 0.095 | I14: =IF(G14="","",G14*H14) -> 5.225 | J14: 5.25 | K14: 0.25 | L14: =IF(OR(B14="",G14=""),"",G14-E14-F14-I14-J14-K14) -> 40.275 | M14: =IF(L14="","",IF(G14=0,0,L14/G14)) -> 0.73227273 | N14: Delivered / Entregado | O14: =IF(M14="","",IF(M14<0.15,"⚠ LOW MARGIN / MARGEN BAJO","✔ OK")) -> ✔ OK | P14: =IF(Q14=1,L14+ROW()/1000000,-1000000000000000) -> 40.275014 | Q14: =IF(B14="",0,IF(G14="",0,IF(N14="Returned / Devuelto",0,1))) -> 1 | R14: =IF(Q14=1,IF(ISNUMBER(D14),YEAR(D14)*100+MONTH(D14),0),0) -> 202604 | S14: =IF(Q14=1,IF(M14<0.15,1,0),0) -> 0
B15: Kitchenaid Mixer Attachment | C15: eBay | D15: 46144 | E15: 15 | F15: 5 | G15: 38 | H15: 0.1325 | I15: =IF(G15="","",G15*H15) -> 5.035 | J15: 9.2 | K15: 0 | L15: =IF(OR(B15="",G15=""),"",G15-E15-F15-I15-J15-K15) -> 3.765 | M15: =IF(L15="","",IF(G15=0,0,L15/G15)) -> 0.099078947 | N15: Delivered / Entregado | O15: =IF(M15="","",IF(M15<0.15,"⚠ LOW MARGIN / MARGEN BAJO","✔ OK")) -> ⚠ LOW MARGIN / MARGEN BAJO | P15: =IF(Q15=1,L15+ROW()/1000000,-1000000000000000) -> 3.765015 | Q15: =IF(B15="",0,IF(G15="",0,IF(N15="Returned / Devuelto",0,1))) -> 1 | R15: =IF(Q15=1,IF(ISNUMBER(D15),YEAR(D15)*100+MONTH(D15),0),0) -> 202605 | S15: =IF(Q15=1,IF(M15<0.15,1,0),0) -> 1
B16: Lululemon Align Leggings | C16: Poshmark | D16: 46158 | E16: 10 | F16: 0 | G16: 48 | H16: 0.2 | I16: =IF(G16="","",G16*H16) -> 9.6 | J16: 0 | K16: 0 | L16: =IF(OR(B16="",G16=""),"",G16-E16-F16-I16-J16-K16) -> 28.4 | M16: =IF(L16="","",IF(G16=0,0,L16/G16)) -> 0.59166667 | N16: Delivered / Entregado | O16: =IF(M16="","",IF(M16<0.15,"⚠ LOW MARGIN / MARGEN BAJO","✔ OK")) -> ✔ OK | P16: =IF(Q16=1,L16+ROW()/1000000,-1000000000000000) -> 28.400016 | Q16: =IF(B16="",0,IF(G16="",0,IF(N16="Returned / Devuelto",0,1))) -> 1 | R16: =IF(Q16=1,IF(ISNUMBER(D16),YEAR(D16)*100+MONTH(D16),0),0) -> 202605 | S16: =IF(Q16=1,IF(M16<0.15,1,0),0) -> 0
B17: Nintendo Switch Games Lot (4) | C17: Facebook Marketplace | D17: 46174 | E17: 60 | F17: 0 | G17: 110 | H17: 0.1 | I17: =IF(G17="","",G17*H17) -> 11 | J17: 8.5 | K17: 0 | L17: =IF(OR(B17="",G17=""),"",G17-E17-F17-I17-J17-K17) -> 30.5 | M17: =IF(L17="","",IF(G17=0,0,L17/G17)) -> 0.27727273 | N17: Delivered / Entregado | O17: =IF(M17="","",IF(M17<0.15,"⚠ LOW MARGIN / MARGEN BAJO","✔ OK")) -> ✔ OK | P17: =IF(Q17=1,L17+ROW()/1000000,-1000000000000000) -> 30.500017 | Q17: =IF(B17="",0,IF(G17="",0,IF(N17="Returned / Devuelto",0,1))) -> 1 | R17: =IF(Q17=1,IF(ISNUMBER(D17),YEAR(D17)*100+MONTH(D17),0),0) -> 202606 | S17: =IF(Q17=1,IF(M17<0.15,1,0),0) -> 0
... B25: Fire-King Jadeite Mug | C25: Etsy | D25: 46291 | E25: 2 | F25: 0 | G25: 30 | H25: 0.095 | I25: =IF(G25="","",G25*H25) -> 2.85 | J25: 7 | K25: 0.25 | L25: =IF(OR(B25="",G25=""),"",G25-E25-F25-I25-J25-K25) -> 17.9 | M25: =IF(L25="","",IF(G25=0,0,L25/G25)) -> 0.59666667 | N25: Pending / Pendiente | O25: =IF(M25="","",IF(M25<0.15,"⚠ LOW MARGIN / MARGEN BAJO","✔ OK")) -> ✔ OK | P25: =IF(Q25=1,L25+ROW()/1000000,-1000000000000000) -> 17.900025 | Q25: =IF(B25="",0,IF(G25="",0,IF(N25="Returned / Devuelto",0,1))) -> 1 | R25: =IF(Q25=1,IF(ISNUMBER(D25),YEAR(D25)*100+MONTH(D25),0),0) -> 202609 | S25: =IF(Q25=1,IF(M25<0.15,1,0),0) -> 0
I26: =IF(G26="","",G26*H26) | L26: =IF(OR(B26="",G26=""),"",G26-E26-F26-I26-J26-K26) | M26: =IF(L26="","",IF(G26=0,0,L26/G26)) | O26: =IF(M26="","",IF(M26<0.15,"⚠ LOW MARGIN / MARGEN BAJO","✔ OK")) | P26: =IF(Q26=1,L26+ROW()/1000000,-1000000000000000) -> -1e+15 | Q26: =IF(B26="",0,IF(G26="",0,IF(N26="Returned / Devuelto",0,1))) -> 0 | R26: =IF(Q26=1,IF(ISNUMBER(D26),YEAR(D26)*100+MONTH(D26),0),0) -> 0 | S26: =IF(Q26=1,IF(M26<0.15,1,0),0) -> 0
I27: =IF(G27="","",G27*H27) | L27: =IF(OR(B27="",G27=""),"",G27-E27-F27-I27-J27-K27) | M27: =IF(L27="","",IF(G27=0,0,L27/G27)) | O27: =IF(M27="","",IF(M27<0.15,"⚠ LOW MARGIN / MARGEN BAJO","✔ OK")) | P27: =IF(Q27=1,L27+ROW()/1000000,-1000000000000000) -> -1e+15 | Q27: =IF(B27="",0,IF(G27="",0,IF(N27="Returned / Devuelto",0,1))) -> 0 | R27: =IF(Q27=1,IF(ISNUMBER(D27),YEAR(D27)*100+MONTH(D27),0),0) -> 0 | S27: =IF(Q27=1,IF(M27<0.15,1,0),0) -> 0
I28: =IF(G28="","",G28*H28) | L28: =IF(OR(B28="",G28=""),"",G28-E28-F28-I28-J28-K28) | M28: =IF(L28="","",IF(G28=0,0,L28/G28)) | O28: =IF(M28="","",IF(M28<0.15,"⚠ LOW MARGIN / MARGEN BAJO","✔ OK")) | P28: =IF(Q28=1,L28+ROW()/1000000,-1000000000000000) -> -1e+15 | Q28: =IF(B28="",0,IF(G28="",0,IF(N28="Returned / Devuelto",0,1))) -> 0 | R28: =IF(Q28=1,IF(ISNUMBER(D28),YEAR(D28)*100+MONTH(D28),0),0) -> 0 | S28: =IF(Q28=1,IF(M28<0.15,1,0),0) -> 0
I29: =IF(G29="","",G29*H29) | L29: =IF(OR(B29="",G29=""),"",G29-E29-F29-I29-J29-K29) | M29: =IF(L29="","",IF(G29=0,0,L29/G29)) | O29: =IF(M29="","",IF(M29<0.15,"⚠ LOW MARGIN / MARGEN BAJO","✔ OK")) | P29: =IF(Q29=1,L29+ROW()/1000000,-1000000000000000) -> -1e+15 | Q29: =IF(B29="",0,IF(G29="",0,IF(N29="Returned / Devuelto",0,1))) -> 0 | R29: =IF(Q29=1,IF(ISNUMBER(D29),YEAR(D29)*100+MONTH(D29),0),0) -> 0 | S29: =IF(Q29=1,IF(M29<0.15,1,0),0) -> 0
I30: =IF(G30="","",G30*H30) | L30: =IF(OR(B30="",G30=""),"",G30-E30-F30-I30-J30-K30) | M30: =IF(L30="","",IF(G30=0,0,L30/G30)) | O30: =IF(M30="","",IF(M30<0.15,"⚠ LOW MARGIN / MARGEN BAJO","✔ OK")) | P30: =IF(Q30=1,L30+ROW()/1000000,-1000000000000000) -> -1e+15 | Q30: =IF(B30="",0,IF(G30="",0,IF(N30="Returned / Devuelto",0,1))) -> 0 | R30: =IF(Q30=1,IF(ISNUMBER(D30),YEAR(D30)*100+MONTH(D30),0),0) -> 0 | S30: =IF(Q30=1,IF(M30<0.15,1,0),0) -> 0
I31: =IF(G31="","",G31*H31) | L31: =IF(OR(B31="",G31=""),"",G31-E31-F31-I31-J31-K31) | M31: =IF(L31="","",IF(G31=0,0,L31/G31)) | O31: =IF(M31="","",IF(M31<0.15,"⚠ LOW MARGIN / MARGEN BAJO","✔ OK")) | P31: =IF(Q31=1,L31+ROW()/1000000,-1000000000000000) -> -1e+15 | Q31: =IF(B31="",0,IF(G31="",0,IF(N31="Returned / Devuelto",0,1))) -> 0 | R31: =IF(Q31=1,IF(ISNUMBER(D31),YEAR(D31)*100+MONTH(D31),0),0) -> 0 | S31: =IF(Q31=1,IF(M31<0.15,1,0),0) -> 0
I32: =IF(G32="","",G32*H32) | L32: =IF(OR(B32="",G32=""),"",G32-E32-F32-I32-J32-K32) | M32: =IF(L32="","",IF(G32=0,0,L32/G32)) | O32: =IF(M32="","",IF(M32<0.15,"⚠ LOW MARGIN / MARGEN BAJO","✔ OK")) | P32: =IF(Q32=1,L32+ROW()/1000000,-1000000000000000) -> -1e+15 | Q32: =IF(B32="",0,IF(G32="",0,IF(N32="Returned / Devuelto",0,1))) -> 0 | R32: =IF(Q32=1,IF(ISNUMBER(D32),YEAR(D32)*100+MONTH(D32),0),0) -> 0 | S32: =IF(Q32=1,IF(M32<0.15,1,0),0) -> 0
I33: =IF(G33="","",G33*H33) | L33: =IF(OR(B33="",G33=""),"",G33-E33-F33-I33-J33-K33) | M33: =IF(L33="","",IF(G33=0,0,L33/G33)) | O33: =IF(M33="","",IF(M33<0.15,"⚠ LOW MARGIN / MARGEN BAJO","✔ OK")) | P33: =IF(Q33=1,L33+ROW()/1000000,-1000000000000000) -> -1e+15 | Q33: =IF(B33="",0,IF(G33="",0,IF(N33="Returned / Devuelto",0,1))) -> 0 | R33: =IF(Q33=1,IF(ISNUMBER(D33),YEAR(D33)*100+MONTH(D33),0),0) -> 0 | S33: =IF(Q33=1,IF(M33<0.15,1,0),0) -> 0
I34: =IF(G34="","",G34*H34) | L34: =IF(OR(B34="",G34=""),"",G34-E34-F34-I34-J34-K34) | M34: =IF(L34="","",IF(G34=0,0,L34/G34)) | O34: =IF(M34="","",IF(M34<0.15,"⚠ LOW MARGIN / MARGEN BAJO","✔ OK")) | P34: =IF(Q34=1,L34+ROW()/1000000,-1000000000000000) -> -1e+15 | Q34: =IF(B34="",0,IF(G34="",0,IF(N34="Returned / Devuelto",0,1))) -> 0 | R34: =IF(Q34=1,IF(ISNUMBER(D34),YEAR(D34)*100+MONTH(D34),0),0) -> 0 | S34: =IF(Q34=1,IF(M34<0.15,1,0),0) -> 0
I35: =IF(G35="","",G35*H35) | L35: =IF(OR(B35="",G35=""),"",G35-E35-F35-I35-J35-K35) | M35: =IF(L35="","",IF(G35=0,0,L35/G35)) | O35: =IF(M35="","",IF(M35<0.15,"⚠ LOW MARGIN / MARGEN BAJO","✔ OK")) | P35: =IF(Q35=1,L35+ROW()/1000000,-1000000000000000) -> -1e+15 | Q35: =IF(B35="",0,IF(G35="",0,IF(N35="Returned / Devuelto",0,1))) -> 0 | R35: =IF(Q35=1,IF(ISNUMBER(D35),YEAR(D35)*100+MONTH(D35),0),0) -> 0 | S35: =IF(Q35=1,IF(M35<0.15,1,0),0) -> 0
I36: =IF(G36="","",G36*H36) | L36: =IF(OR(B36="",G36=""),"",G36-E36-F36-I36-J36-K36) | M36: =IF(L36="","",IF(G36=0,0,L36/G36)) | O36: =IF(M36="","",IF(M36<0.15,"⚠ LOW MARGIN / MARGEN BAJO","✔ OK")) | P36: =IF(Q36=1,L36+ROW()/1000000,-1000000000000000) -> -1e+15 | Q36: =IF(B36="",0,IF(G36="",0,IF(N36="Returned / Devuelto",0,1))) -> 0 | R36: =IF(Q36=1,IF(ISNUMBER(D36),YEAR(D36)*100+MONTH(D36),0),0) -> 0 | S36: =IF(Q36=1,IF(M36<0.15,1,0),0) -> 0
I37: =IF(G37="","",G37*H37) | L37: =IF(OR(B37="",G37=""),"",G37-E37-F37-I37-J37-K37) | M37: =IF(L37="","",IF(G37=0,0,L37/G37)) | O37: =IF(M37="","",IF(M37<0.15,"⚠ LOW MARGIN / MARGEN BAJO","✔ OK")) | P37: =IF(Q37=1,L37+ROW()/1000000,-1000000000000000) -> -1e+15 | Q37: =IF(B37="",0,IF(G37="",0,IF(N37="Returned / Devuelto",0,1))) -> 0 | R37: =IF(Q37=1,IF(ISNUMBER(D37),YEAR(D37)*100+MONTH(D37),0),0) -> 0 | S37: =IF(Q37=1,IF(M37<0.15,1,0),0) -> 0
... I505: =IF(G505="","",G505*H505) | L505: =IF(OR(B505="",G505=""),"",G505-E505-F505-I505-J505-K505) | M505: =IF(L505="","",IF(G505=0,0,L505/G505)) | O505: =IF(M505="","",IF(M505<0.15,"⚠ LOW MARGIN / MARGEN BAJO","✔ OK")) | P505: =IF(Q505=1,L505+ROW()/1000000,-1000000000000000) -> -1e+15 | Q505: =IF(B505="",0,IF(G505="",0,IF(N505="Returned / Devuelto",0,1))) -> 0 | R505: =IF(Q505=1,IF(ISNUMBER(D505),YEAR(D505)*100+MONTH(D505),0),0) -> 0 | S505: =IF(Q505=1,IF(M505<0.15,1,0),0) -> 0

Sheet Sourcing List
B1: ProfitTrack
B2: Sourcing List (Bonus) / Lista de Compras (Bono)
B3: Check the expected profit BEFORE you buy. • Calcula la ganancia esperada ANTES de comprar.
B6: Your Buying Rules / Tus Reglas de Compra
B7: Minimum margin / Margen mínimo | F7: 0.3 | H7: An item gets ✔ BUY only if it meets BOTH rules. 'Max Buy Price' = the most you can pay and still hit your minimum margin. Un artículo obtiene ✔ COMPRAR solo si cumple AMBAS reglas. 'Precio Máx. de Compra' = lo máximo que puedes pagar y aún lograr tu margen mínimo.
B8: Minimum profit per item / Ganancia mínima por artículo | F8: 10
B10: Item Artículo | C10: Where Found Dónde lo Encontré | D10: Target Platform Plataforma | E10: Asking Price Precio de Compra | F10: Shipping In Envío (Entrada) | G10: Est. Sale Price Precio Est. Venta | H10: Fee % % Comisión | I10: Est. Fee $ Comisión Est. $ | J10: Est. Ship Out Envío Est. Salida | K10: Other Costs Otros Costos | L10: Est. Profit Ganancia Est. | M10: Est. Margin Margen Est. | N10: ROI % Retorno % | O10: Max Buy Price Precio Máx. Compra | P10: Decision Decisión | Q10: Notes Notas
B11: Vintage Pendleton Wool Shirt | C11: Goodwill | D11: eBay | E11: 8 | F11: 0 | G11: 55 | H11: 0.1325 | I11: =IF(G11="","",G11*H11) -> 7.2875 | J11: 8.5 | K11: 0 | L11: =IF(OR(B11="",G11=""),"",G11-E11-F11-I11-J11-K11) -> 31.2125 | M11: =IF(L11="","",IF(G11=0,0,L11/G11)) -> 0.5675 | N11: =IF(L11="","",IF(E11+F11=0,"∞",L11/(E11+F11))) -> 3.9015625 | O11: =IF(L11="","",MAX(0,MIN(G11*(1-H11-$F$7),G11*(1-H11)-$F$8)-J11-K11-F11)) -> 22.7125 | P11: =IF(L11="","",IF(AND(M11>=$F$7,L11>=$F$8),"✔ BUY / COMPRAR","✖ PASS / NO COMPRAR")) -> ✔ BUY / COMPRAR | Q11: Check tags / Revisar etiquetas
B12: Le Creuset Dutch Oven 5.5qt | C12: Estate sale | D12: Facebook Marketplace | E12: 60 | F12: 0 | G12: 180 | H12: 0 | I12: =IF(G12="","",G12*H12) -> 0 | J12: 0 | K12: 0 | L12: =IF(OR(B12="",G12=""),"",G12-E12-F12-I12-J12-K12) -> 120 | M12: =IF(L12="","",IF(G12=0,0,L12/G12)) -> 0.66666667 | N12: =IF(L12="","",IF(E12+F12=0,"∞",L12/(E12+F12))) -> 2 | O12: =IF(L12="","",MAX(0,MIN(G12*(1-H12-$F$7),G12*(1-H12)-$F$8)-J12-K12-F12)) -> 126 | P12: =IF(L12="","",IF(AND(M12>=$F$7,L12>=$F$8),"✔ BUY / COMPRAR","✖ PASS / NO COMPRAR")) -> ✔ BUY / COMPRAR | Q12: Local pickup / Recoger local
B13: Target Brand Graphic Tee | C13: Garage sale | D13: Poshmark | E13: 3 | F13: 0 | G13: 12 | H13: 0.2 | I13: =IF(G13="","",G13*H13) -> 2.4 | J13: 0 | K13: 0 | L13: =IF(OR(B13="",G13=""),"",G13-E13-F13-I13-J13-K13) -> 6.6 | M13: =IF(L13="","",IF(G13=0,0,L13/G13)) -> 0.55 | N13: =IF(L13="","",IF(E13+F13=0,"∞",L13/(E13+F13))) -> 2.2 | O13: =IF(L13="","",MAX(0,MIN(G13*(1-H13-$F$7),G13*(1-H13)-$F$8)-J13-K13-F13)) -> 0 | P13: =IF(L13="","",IF(AND(M13>=$F$7,L13>=$F$8),"✔ BUY / COMPRAR","✖ PASS / NO COMPRAR")) -> ✖ PASS / NO COMPRAR
B14: Vintage Pyrex Casserole | C14: Thrift store | D14: Etsy | E14: 12 | F14: 0 | G14: 45 | H14: 0.095 | I14: =IF(G14="","",G14*H14) -> 4.275 | J14: 12 | K14: 0.25 | L14: =IF(OR(B14="",G14=""),"",G14-E14-F14-I14-J14-K14) -> 16.475 | M14: =IF(L14="","",IF(G14=0,0,L14/G14)) -> 0.36611111 | N14: =IF(L14="","",IF(E14+F14=0,"∞",L14/(E14+F14))) -> 1.3729167 | O14: =IF(L14="","",MAX(0,MIN(G14*(1-H14-$F$7),G14*(1-H14)-$F$8)-J14-K14-F14)) -> 14.975 | P14: =IF(L14="","",IF(AND(M14>=$F$7,L14>=$F$8),"✔ BUY / COMPRAR","✖ PASS / NO COMPRAR")) -> ✔ BUY / COMPRAR
B15: Bose QC45 Headphones | C15: FB Marketplace | D15: eBay | E15: 95 | F15: 0 | G15: 140 | H15: 0.1325 | I15: =IF(G15="","",G15*H15) -> 18.55 | J15: 10 | K15: 0 | L15: =IF(OR(B15="",G15=""),"",G15-E15-F15-I15-J15-K15) -> 16.45 | M15: =IF(L15="","",IF(G15=0,0,L15/G15)) -> 0.1175 | N15: =IF(L15="","",IF(E15+F15=0,"∞",L15/(E15+F15))) -> 0.17315789 | O15: =IF(L15="","",MAX(0,MIN(G15*(1-H15-$F$7),G15*(1-H15)-$F$8)-J15-K15-F15)) -> 69.45 | P15: =IF(L15="","",IF(AND(M15>=$F$7,L15>=$F$8),"✔ BUY / COMPRAR","✖ PASS / NO COMPRAR")) -> ✖ PASS / NO COMPRAR | Q15: Test first / Probar primero
I16: =IF(G16="","",G16*H16) | L16: =IF(OR(B16="",G16=""),"",G16-E16-F16-I16-J16-K16) | M16: =IF(L16="","",IF(G16=0,0,L16/G16)) | N16: =IF(L16="","",IF(E16+F16=0,"∞",L16/(E16+F16))) | O16: =IF(L16="","",MAX(0,MIN(G16*(1-H16-$F$7),G16*(1-H16)-$F$8)-J16-K16-F16)) | P16: =IF(L16="","",IF(AND(M16>=$F$7,L16>=$F$8),"✔ BUY / COMPRAR","✖ PASS / NO COMPRAR"))
I17: =IF(G17="","",G17*H17) | L17: =IF(OR(B17="",G17=""),"",G17-E17-F17-I17-J17-K17) | M17: =IF(L17="","",IF(G17=0,0,L17/G17)) | N17: =IF(L17="","",IF(E17+F17=0,"∞",L17/(E17+F17))) | O17: =IF(L17="","",MAX(0,MIN(G17*(1-H17-$F$7),G17*(1-H17)-$F$8)-J17-K17-F17)) | P17: =IF(L17="","",IF(AND(M17>=$F$7,L17>=$F$8),"✔ BUY / COMPRAR","✖ PASS / NO COMPRAR"))
I18: =IF(G18="","",G18*H18) | L18: =IF(OR(B18="",G18=""),"",G18-E18-F18-I18-J18-K18) | M18: =IF(L18="","",IF(G18=0,0,L18/G18)) | N18: =IF(L18="","",IF(E18+F18=0,"∞",L18/(E18+F18))) | O18: =IF(L18="","",MAX(0,MIN(G18*(1-H18-$F$7),G18*(1-H18)-$F$8)-J18-K18-F18)) | P18: =IF(L18="","",IF(AND(M18>=$F$7,L18>=$F$8),"✔ BUY / COMPRAR","✖ PASS / NO COMPRAR"))
I19: =IF(G19="","",G19*H19) | L19: =IF(OR(B19="",G19=""),"",G19-E19-F19-I19-J19-K19) | M19: =IF(L19="","",IF(G19=0,0,L19/G19)) | N19: =IF(L19="","",IF(E19+F19=0,"∞",L19/(E19+F19))) | O19: =IF(L19="","",MAX(0,MIN(G19*(1-H19-$F$7),G19*(1-H19)-$F$8)-J19-K19-F19)) | P19: =IF(L19="","",IF(AND(M19>=$F$7,L19>=$F$8),"✔ BUY / COMPRAR","✖ PASS / NO COMPRAR"))
I20: =IF(G20="","",G20*H20) | L20: =IF(OR(B20="",G20=""),"",G20-E20-F20-I20-J20-K20) | M20: =IF(L20="","",IF(G20=0,0,L20/G20)) | N20: =IF(L20="","",IF(E20+F20=0,"∞",L20/(E20+F20))) | O20: =IF(L20="","",MAX(0,MIN(G20*(1-H20-$F$7),G20*(1-H20)-$F$8)-J20-K20-F20)) | P20: =IF(L20="","",IF(AND(M20>=$F$7,L20>=$F$8),"✔ BUY / COMPRAR","✖ PASS / NO COMPRAR"))
I21: =IF(G21="","",G21*H21) | L21: =IF(OR(B21="",G21=""),"",G21-E21-F21-I21-J21-K21) | M21: =IF(L21="","",IF(G21=0,0,L21/G21)) | N21: =IF(L21="","",IF(E21+F21=0,"∞",L21/(E21+F21))) | O21: =IF(L21="","",MAX(0,MIN(G21*(1-H21-$F$7),G21*(1-H21)-$F$8)-J21-K21-F21)) | P21: =IF(L21="","",IF(AND(M21>=$F$7,L21>=$F$8),"✔ BUY / COMPRAR","✖ PASS / NO COMPRAR"))
I22: =IF(G22="","",G22*H22) | L22: =IF(OR(B22="",G22=""),"",G22-E22-F22-I22-J22-K22) | M22: =IF(L22="","",IF(G22=0,0,L22/G22)) | N22: =IF(L22="","",IF(E22+F22=0,"∞",L22/(E22+F22))) | O22: =IF(L22="","",MAX(0,MIN(G22*(1-H22-$F$7),G22*(1-H22)-$F$8)-J22-K22-F22)) | P22: =IF(L22="","",IF(AND(M22>=$F$7,L22>=$F$8),"✔ BUY / COMPRAR","✖ PASS / NO COMPRAR"))
I23: =IF(G23="","",G23*H23) | L23: =IF(OR(B23="",G23=""),"",G23-E23-F23-I23-J23-K23) | M23: =IF(L23="","",IF(G23=0,0,L23/G23)) | N23: =IF(L23="","",IF(E23+F23=0,"∞",L23/(E23+F23))) | O23: =IF(L23="","",MAX(0,MIN(G23*(1-H23-$F$7),G23*(1-H23)-$F$8)-J23-K23-F23)) | P23: =IF(L23="","",IF(AND(M23>=$F$7,L23>=$F$8),"✔ BUY / COMPRAR","✖ PASS / NO COMPRAR"))
I24: =IF(G24="","",G24*H24) | L24: =IF(OR(B24="",G24=""),"",G24-E24-F24-I24-J24-K24) | M24: =IF(L24="","",IF(G24=0,0,L24/G24)) | N24: =IF(L24="","",IF(E24+F24=0,"∞",L24/(E24+F24))) | O24: =IF(L24="","",MAX(0,MIN(G24*(1-H24-$F$7),G24*(1-H24)-$F$8)-J24-K24-F24)) | P24: =IF(L24="","",IF(AND(M24>=$F$7,L24>=$F$8),"✔ BUY / COMPRAR","✖ PASS / NO COMPRAR"))
I25: =IF(G25="","",G25*H25) | L25: =IF(OR(B25="",G25=""),"",G25-E25-F25-I25-J25-K25) | M25: =IF(L25="","",IF(G25=0,0,L25/G25)) | N25: =IF(L25="","",IF(E25+F25=0,"∞",L25/(E25+F25))) | O25: =IF(L25="","",MAX(0,MIN(G25*(1-H25-$F$7),G25*(1-H25)-$F$8)-J25-K25-F25)) | P25: =IF(L25="","",IF(AND(M25>=$F$7,L25>=$F$8),"✔ BUY / COMPRAR","✖ PASS / NO COMPRAR"))
I26: =IF(G26="","",G26*H26) | L26: =IF(OR(B26="",G26=""),"",G26-E26-F26-I26-J26-K26) | M26: =IF(L26="","",IF(G26=0,0,L26/G26)) | N26: =IF(L26="","",IF(E26+F26=0,"∞",L26/(E26+F26))) | O26: =IF(L26="","",MAX(0,MIN(G26*(1-H26-$F$7),G26*(1-H26)-$F$8)-J26-K26-F26)) | P26: =IF(L26="","",IF(AND(M26>=$F$7,L26>=$F$8),"✔ BUY / COMPRAR","✖ PASS / NO COMPRAR"))
I27: =IF(G27="","",G27*H27) | L27: =IF(OR(B27="",G27=""),"",G27-E27-F27-I27-J27-K27) | M27: =IF(L27="","",IF(G27=0,0,L27/G27)) | N27: =IF(L27="","",IF(E27+F27=0,"∞",L27/(E27+F27))) | O27: =IF(L27="","",MAX(0,MIN(G27*(1-H27-$F$7),G27*(1-H27)-$F$8)-J27-K27-F27)) | P27: =IF(L27="","",IF(AND(M27>=$F$7,L27>=$F$8),"✔ BUY / COMPRAR","✖ PASS / NO COMPRAR"))
... I110: =IF(G110="","",G110*H110) | L110: =IF(OR(B110="",G110=""),"",G110-E110-F110-I110-J110-K110) | M110: =IF(L110="","",IF(G110=0,0,L110/G110)) | N110: =IF(L110="","",IF(E110+F110=0,"∞",L110/(E110+F110))) | O110: =IF(L110="","",MAX(0,MIN(G110*(1-H110-$F$7),G110*(1-H110)-$F$8)-J110-K110-F110)) | P110: =IF(L110="","",IF(AND(M110>=$F$7,L110>=$F$8),"✔ BUY / COMPRAR","✖ PASS / NO COMPRAR"))

Sheet Quick Start Guide
B1: ProfitTrack
B2: Quick Start Guide / Guía Rápida
B3: Up and running in 5 minutes. • Listo en 5 minutos.
B6: # | C6: ENGLISH | D6: ESPAÑOL
B7: 1 | C7: Clear the example data. Go to Tracker, select cells B6:N25 and press Delete. Do the same on Sourcing List (B11:K15 and Q11:Q15). Never delete whole rows or the grey columns. | D7: Borra los datos de ejemplo. Ve a Tracker (Registro), selecciona B6:N25 y presiona Suprimir. Haz lo mismo en Sourcing List (B11:K15 y Q11:Q15). Nunca borres filas completas ni las columnas grises.
B8: 2 | C8: Log each sale on the Tracker — one row per item. Type only in the light-teal columns: Product Name, Platform (dropdown), Sale Date, Purchase Cost, Shipping In, Sale Price, Platform Fee %, Shipping Out, Other Costs and Status (dropdown). | D8: Registra cada venta en Tracker — una fila por artículo. Escribe solo en las columnas verde claro: Nombre, Plataforma (lista), Fecha, Costo de Compra, Envío (Entrada), Precio de Venta, % Comisión, Envío (Salida), Otros Costos y Estado (lista).
B9: 3 | C9: Enter the platform fee as a percent (e.g. 13.25%). See the fee reference table below. If you enter a flat fee instead, put it in 'Other Costs'. | D9: Escribe la comisión como porcentaje (ej. 13.25%). Consulta la tabla de comisiones abajo. Si pagas una tarifa fija, ponla en 'Otros Costos'.
B10: 4 | C10: The grey columns calculate automatically: Platform Fee $ = Sale Price × Fee %; Net Profit = Sale Price − Purchase Cost − Shipping In − Platform Fee $ − Shipping Out − Other Costs; Margin % = Net Profit ÷ Sale Price. | D10: Las columnas grises se calculan solas: Comisión $ = Precio × % Comisión; Ganancia Neta = Precio − Costo − Envío (Entrada) − Comisión $ − Envío (Salida) − Otros Costos; Margen % = Ganancia Neta ÷ Precio.
B11: 5 | C11: Watch the Margin Alert column. Any sale under 15% margin is flagged red '⚠ LOW MARGIN' so you can spot items that aren't worth your time. | D11: Revisa la columna Alerta de Margen. Toda venta con margen menor al 15% se marca en rojo '⚠ MARGEN BAJO' para detectar artículos que no valen la pena.
B12: 6 | C12: If an item is returned, set Status to 'Returned / Devuelto'. It stays in your log (greyed out) but is excluded from every Dashboard number. | D12: Si un artículo se devuelve, cambia el Estado a 'Returned / Devuelto'. Se queda en tu registro (en gris) pero se excluye de todos los números del Panel.
B13: 7 | C13: Open the Dashboard to see your KPIs, profit by platform, the monthly trend chart and your Top 5 sales. Everything updates instantly. Change the yellow Year cell to view another year. | D13: Abre el Dashboard (Panel) para ver tus indicadores, ganancia por plataforma, la gráfica mensual y tus Top 5 ventas. Todo se actualiza al instante. Cambia la celda amarilla del Año para ver otro año.
B14: 8 | C14: BONUS — before buying inventory, use the Sourcing List. Set your minimum margin and minimum profit (yellow cells), enter the asking price and your estimated sale price, and get an instant ✔ BUY / ✖ PASS plus the Max Buy Price to negotiate with. | D14: BONO — antes de comprar mercancía, usa Sourcing List (Lista de Compras). Define tu margen y ganancia mínimos (celdas amarillas), escribe el precio de compra y el precio estimado de venta, y obtén al instante ✔ COMPRAR / ✖ NO COMPRAR y el Precio Máximo de Compra para negociar.
B15: 9 | C15: Google Sheets: upload the file to Google Drive → Open with Google Sheets → File → Save as Google Sheets. All formulas, dropdowns and charts keep working. | D15: Google Sheets: sube el archivo a Google Drive → Abrir con Google Sheets → Archivo → Guardar como Hojas de cálculo de Google. Todas las fórmulas, listas y gráficas siguen funcionando.
B16: 10 | C16: Tip: save a blank copy of this file before you start, and back up your working file monthly. | D16: Consejo: guarda una copia en blanco de este archivo antes de empezar y respalda tu archivo cada mes.
B18: Color Legend / Leyenda de Colores
C19: Light teal = type your data here | D19: Verde claro = escribe tus datos aquí
C20: Grey = automatic formula – don't type here | D20: Gris = fórmula automática – no escribas aquí
C21: Yellow = settings you can change (Year, buying rules) | D21: Amarillo = ajustes que puedes cambiar (Año, reglas de compra)
B23: Platform Fee Reference (approximate) / Referencia de Comisiones (aproximada)
C24: Platform – typical fee / Plataforma – comisión típica | D24: Notes / Notas
C25: eBay – about 13.25% (most categories) | D25: Plus ~$0.30–0.40 per order → add to Other Costs. / Más ~$0.30–0.40 por pedido → agrégalo a Otros Costos.
C26: Poshmark – 20% (sales $15+) | D26: Sales under $15: flat $2.95 → put 0% and $2.95 in Other Costs. / Ventas menores a $15: $2.95 fijo → 0% y $2.95 en Otros Costos.
C27: Etsy – about 9.5% (6.5% transaction + 3% payment) | D27: Plus $0.20 listing + $0.25 processing → Other Costs. / Más $0.20 de publicación + $0.25 de procesamiento → Otros Costos.
C28: Facebook Marketplace – 0% local / ~10% shipped | D28: Local cash pickup has no fee. / La venta local en efectivo no tiene comisión.
C29: Other (Mercari, Depop, Vinted, in-person…) | D29: Enter the rate you actually paid. / Escribe la comisión que realmente pagaste.
B30: Fees change often – always check each platform's current fee page. Rates above are for reference only (US, 2026). / Las comisiones cambian con frecuencia – revisa siempre la página oficial de cada plataforma. Tarifas solo de referencia (EE. UU., 2026).
B32: FAQ / Preguntas Frecuentes
C33: Q: How many sales can I log? A: 500 rows are ready. Need more? Copy the last row down – formulas copy with it (also extend the Tracker ranges on the Dashboard). | D33: P: ¿Cuántas ventas puedo registrar? R: Hay 500 filas listas. ¿Necesitas más? Copia la última fila hacia abajo – las fórmulas se copian (también amplía los rangos del Tracker en el Panel).
C34: Q: Why is Average Margin 'weighted'? A: It's Total Profit ÷ Total Revenue, so a $500 sale counts more than a $5 sale – the most accurate picture of your business. | D34: P: ¿Por qué el Margen Promedio es 'ponderado'? R: Es Ganancia Total ÷ Ingresos Totales, así una venta de $500 pesa más que una de $5 – la imagen más precisa de tu negocio.
C35: Q: A sale has no profit showing. A: Profit appears once Product Name and Sale Price are filled in. | D35: P: Una venta no muestra ganancia. R: La ganancia aparece cuando llenas el Nombre del Producto y el Precio de Venta.
B37: Phone, Tablet & Computer / Celular, Tableta y Computadora
C38: 💻 Computer (Windows / Mac): open in Microsoft Excel, or in Google Sheets from any browser. Everything works. | D38: 💻 Computadora (Windows / Mac): ábrelo en Microsoft Excel o en Google Sheets desde cualquier navegador. Todo funciona.
C39: 📱 iPhone, iPad & Android — RECOMMENDED: the free Microsoft Excel app or the free Google Sheets app. Formulas, dropdowns, charts and alerts all work. | D39: 📱 iPhone, iPad y Android — RECOMENDADO: la app gratuita Microsoft Excel o la app gratuita Google Sheets. Fórmulas, listas, gráficas y alertas funcionan.
C40: 🍎 Apple Numbers: formulas, Dashboard, charts and alerts work, but Numbers removes dropdown lists when it opens Excel files (you'll see a message – this is normal). Type the Platform and Status exactly as in the list (e.g. Returned / Devuelto), or re-add a menu: select the column cells → Format → Cell → Data Format → Pop-Up Menu. | D40: 🍎 Apple Numbers: las fórmulas, el Panel, las gráficas y las alertas funcionan, pero Numbers elimina las listas desplegables al abrir archivos de Excel (verás un aviso – es normal). Escribe la Plataforma y el Estado exactamente como en la lista (ej. Returned / Devuelto), o vuelve a crear el menú: selecciona las celdas de la columna → Formato → Celda → Formato de datos → Menú desplegable.
C41: Options for Platform: eBay · Facebook Marketplace · Etsy · Poshmark · Other. Options for Status: Sold / Vendido · Shipped / Enviado · Delivered / Entregado · Pending / Pendiente · Returned / Devuelto | D41: Opciones de Plataforma: eBay · Facebook Marketplace · Etsy · Poshmark · Other. Opciones de Estado: Sold / Vendido · Shipped / Enviado · Delivered / Entregado · Pending / Pendiente · Returned / Devuelto
